Workbook
Name \a: #REF!
Name CABLE: #REF!
Name CC: #REF!
Name EATET: #REF!
Name Excel_BuiltIn_Print_Area_1: #REF!
Name Excel_BuiltIn_Print_Titles_3: #REF!
Name Excel_BuiltIn_Print_Titles_4: #REF!
Name Excel_BuiltIn_Print_Titles_7: #REF!
Name FRNN: #REF!
Name MATICECODE: #REF!
Name MATRICE: #REF!
Name MODELE: #REF!
Name PGA: #REF!
Name RANGE1: '[1]Cable-data'!$A$8:$K$23
Name RANGE2: '[2]Cable-data'!$A$33:$K$48
Name RANGE3: '[3]Cable-data'!$A$55:$K$70
Name RANGE4: '[4]Cable-data'!$A$33:$K$48
Name RANGE5: '[4]Cable-data'!$A$33:$K$48
Name RANGE6: '[5]CABLE DATA'!$A$31:$C$46
Name RANGE7: '[4]Cable-data'!$A$33:$K$48
Name RANGE8: '[4]Cable-data'!$A$33:$K$48
Name RANGE9: '[4]Cable-data'!$A$33:$K$48
Name RYY5Y: #REF!

Sheet Summary
A1: SUMMARY SHEET
A3: SL.No | B3: DESCRIPTION | C3: TOTAL AMOUNT | D3: RATE PER SQFT
D4: =ROUND(37575.27786,2) -> 37575.28
A5: 1 | B5: CIVIL & INTERIOR | C5: ='Summary- C&I'!C17 -> 82578609 | D5: =C5/$D$4 -> 2197.6845
A6: =A5+1 -> 2 | B6: ELECTRICAL | C6: ='Summary Electrical '!E20 -> 13295070 | D6: =C6/$D$4 -> 353.82491
A7: =A6+1 -> 3 | B7: LIGHT FIXTURES | C7: ='Summary Electrical '!E22 -> 4700000 | D7: =C7/$D$4 -> 125.08223
A8: =A7+1 -> 4 | B8: NETWORK | C8: ='Summary Electrical '!E26 -> 2930397.5 | D8: =C8/$D$4 -> 77.987376
A9: =A8+1 -> 5 | B9: CCTV | C9: ='Summary Electrical '!E27 -> 741914 | D9: =C9/$D$4 -> 19.744736
A10: =A9+1 -> 6 | B10: ACS | C10: ='Summary Electrical '!E28 -> 210700 | D10: =C10/$D$4 -> 5.60741
A11: =A10+1 -> 7 | B11: LMS System | C11: ='Summary Electrical '!E29 -> 1115760 | D11: =C11/$D$4 -> 29.69399
A12: =A11+1 -> 8 | B12: HVAC | C12: ='HVAC Cost-Summary'!C8 -> 14039993 | D12: =C12/$D$4 -> 373.64972
A13: =A12+1 -> 9 | B13: FIRE & SAFETY | C13: =Sprinkler!G34 -> 2425066 | D13: =C13/$D$4 -> 64.538867
A14: =A13+1 -> 10 | B14: PHE WORK | C14: ='PHE Cost-Summary'!$C$9 -> 3428797 | D14: =C14/$D$4 -> 91.251403
A15: =A14+1 -> 11 | B15: EXTERNAL FURNITURE | C15: ='Outdoor Furniture'!F14 -> 2341875 | D15: =C15/$D$4 -> 62.324885
B17: TOTAL | C17: =SUM(C4:C16) -> 1.2780818e+08 | D17: =C17/$D$4 -> 3401.39
B18: GST-18% | C18: =C17*18% -> 23005473
B19: GRAND TOTAL | C19: =SUM(C17:C18) -> 1.5081365e+08

Sheet Summary- C&I
A1: SUMMARY SHEET
A3: SL.No | B3: DESCRIPTION | C3: TOTAL AMOUNT
A5: 1 | B5: Civil Work | C5: ='BOQ-C&I'!G47 -> 2445286.5
A6: 2 | B6: Flooring | C6: ='BOQ-C&I'!G112 -> 10198405
A7: 3 | B7: Ceiling | C7: ='BOQ-C&I'!G248 -> 5418443
A8: 4 | B8: Partition | C8: ='BOQ-C&I'!G348 -> 21727072
A9: 5 | B9: Doors | C9: ='BOQ-C&I'!G373 -> 3818750
A10: 6 | B10: Coustom Furniture | C10: ='BOQ-C&I'!G429 -> 5777491.8
A11: 7 | B11: Painting | C11: ='BOQ-C&I'!G463 -> 4068562
A12: 8 | B12: Miscelleneous | C12: ='BOQ-C&I'!G545 -> 3594484
A13: 9 | B13: Modular Furniture | C13: =Modular!G74 -> 21214157
A14: 11 | B14: Toilet Work | C14: ='Toilet Work'!F82 -> 3865958
A15: 12 | B15: Kitchen Equipment | C15: ='Kitchen Equipment'!G9 -> 450000
B17: TOTAL | C17: =SUM(C5:C16) -> 82578609

Sheet BOQ-C&I
A1: BOQ for Interior fitouts work
A3: Sl.No | B3: Description | C3: Basic Rate | D3: Unit | E3: TOTAL | F3: Rate | G3: Amount
A4: 1 | B4: CIVIL WORK
A5: =A4+0.01 -> 1.01 | B5: PEST CONTROL | D5: Sqm | E5: 3102 | F5: 67 | G5: =F5*E5 -> 207834
B6: Providing Pest control and Anti-termite treatment by appointing a specialised agency as per the specifications mentioned by the Bureau of Indian Standards and Agencies specifications
A8: =A5+0.01 -> 1.02 | B8: SCREED FLOORING | D8: Sqm | E8: 1531.5 | F8: 673 | G8: =F8*E8 -> 1030699.5
B9: Providing and laying PCC screed up to 30 mm avg Ht. of cement concrete ratio 1:3:6 (1unit cement, 3units- sand, 6units- course aggregate) in necessary level & slope, finished smoothly with 6-8mm thick. Layer of cement mortar of 1:1 mix (1unit- cement, 1unit- Fine screened sand) in power float finish with proper curing by logging water or sprinkling water or by laying wet gunny bags etc complete as directed. The cost includes Scaffolding all ancillary works as per base builders guidelines and as per site condition .
A11: =A8+0.01 -> 1.03 | B11: 150mm THICK SOLID BLOCK WALL | D11: Sqm | E11: 288 | F11: 1816 | G11: =F11*E11 -> 523008
B12: Making 150mm thick wall of Solid concrete Block in 1:4 cement mortar, with 2 nos. of 8 mm diameter steel reinforcement in every 4 layer & 2 nos. of hoop iron strips 25mm x 1.6mm, painted with anti-corrosive paint, RCC Lintel at 2400 mm Ht, properly bent and bonded at the end, inclusive of shuttering, scaffolding, Raking of joints and proper curing etc complete. The joints between the RCC and masonry will have hold fasts @ 600mm c/c, with joints finished in chicken mesh 20 gauge and finished with cement plaster
A14: =A11+0.01 -> 1.04 | B14: 100mm THICK SOLID BLOCK WALL | D14: Sqm | E14: 0 | F14: 1547 | G14: =F14*E14 -> 0
B15: Making 150mm thick wall of Solid concrete Block in 1:4 cement mortar, with 2 nos. of 8 mm diameter steel reinforcement in every 4 layer & 2 nos. of hoop iron strips 25mm x 1.6mm, painted with anti-corrosive paint, RCC Lintel at 2400 mm Ht, properly bent and bonded at the end, inclusive of shuttering, scaffolding, Raking of joints and proper curing etc complete. The joints between the RCC and masonry will have hold fasts @ 600mm c/c, with joints finished in chicken mesh 20 gauge and finished with cement plaster
A17: =A11+0.01 -> 1.04 | B17: CEMENT PLASTERING | D17: Sqm | E17: 187 | F17: 484 | G17: =F17*E17 -> 90508
B18: Providing & applying in one coat 12mm thick rough Cement plaster in proper line & level on internal surface of RCC/Bricks/Blocks walls with cement mortar 1:4 finished rough to take on POP punning. Rate shall be inclusive of scaffolding, grooves ,sills, band, curing, surface preparation before the application of plaster.
A20: =A11+0.01 -> 1.04 | B20: GYPROC PLASTER | D20: Sqm | E20: 414 | F20: 471 | G20: =F20*E20 -> 194994
B21: Providing & applying in one coat 12mm thick gyproc plaster in proper line & level on internal surface of RCC/Bricks/Blocks walls with gypsum punning. Rate shall be inclusive of scaffolding, grooves ,sills, band, curing, surface preparation before the application of plaster.
A23: =A20+0.01 -> 1.05 | B23: RCC LINTEL | D23: Rmt | E23: 14 | F23: 1046 | G23: =F23*E23 -> 14644
B24: Providing and laying 150/200x150/200x150/200mm lintel concrete by using reinforced cement concrete of nominal mix 1:1.5:3,The work includes concrete laying, shuttering, scaffolding, curing, 4Nos of 8mm dia Reinforement, etc complete as per the EIC.
A26: =A23+0.01 -> 1.06 | B26: WATER PROOFING | D26: Sqm | E26: 91 | F26: 1009 | G26: =F26*E26 -> 91819
B27: Providing and applying water proofing treatment on sunken / raised areas of toilets, etc. with three coats of tapecrete and sealing all junction, corners and joints of pipes after first coat with epoxy mortar as per approved specifications of the specialist agency including providing 10 years written guarantee against any defects and leakage. (Tapecrete is polymer modified cementious material being manufactured in collaboration with FRC Composite Ltd. Canada. It shall have low permeability with a high resistance to cracking). The rate including over the wall facia to height of 600mm. Only floor area shall be measured and paid for this item
A29: =A26+0.01 -> 1.07 | B29: WATER PROOFING WITH WALL PROTECTION | D29: RMT | E29: 25 | F29: 636 | G29: =F29*E29 -> 15900
B30: Providing and applying water proofing treatment on sunken / raised areas of toilets, etc. with three coats of tapecrete and sealing all junction, corners and joints of pipes after first coat with epoxy mortar as per approved specifications of the specialist agency including providing 10 years written guarantee against any defects and leakage. (Tapecrete is polymer modified cementious material being manufactured in collaboration with FRC Composite Ltd. Canada. It shall have low permeability with a high resistance to cracking). The rate including over the wall facia to height of 600mm. Only floor area shall be measured and paid for this item
A32: =A26+0.01 -> 1.07 | B32: CINDER FILLING | D32: Cum | E32: 14 | F32: 13889 | G32: =F32*E32 -> 194446
B33: Providing cinder filling for the sunken portions a toilet sunken slab and wherever specified with cement mortar 1:3 with approved waterproofing compound including compacting, then the layer of cinder and then surface finishing with cement mortar 1:3 with waterproofing compound evenly to take floor finishing (tiles), inclusive of all leads and lifts, levelling, curing etc. complete as per directions of engineer-in charge
A35: =A32+0.01 -> 1.08 | B35: SCREED CONCRETE OVER CINDER | D35: Sqm | E35: 50 | F35: 673 | G35: =F35*E35 -> 33650
B36: Providing & laying plain cement concrete 1:3:6 for a mimumum thickness of 40mm over prepared bed in toilets with 12mm down size aggregates including the cost of all materials, labour, compaction, levelling, at all levels, leads and lifts, curing, shuttering etc. complete as per instruction of Engineer-in charge
A38: =A35+0.01 -> 1.09 | B38: PLATE DROP OPENING | D38: Nos | E38: 1 | F38: 5699 | G38: =F38*E38 -> 5699
B39: Providing and Fixing Window opening of size 1600 x 450mm , The thickness of the wall ( 150mm ) all round the window to be finished with 18mm thk approved granite, edges chamfered. Complete as per detailed drawing and instructions of the Architect | C39: Basic Rate - 200/Sqft
A41: =A38+0.01 -> 1.1 | B41: GRANITE DOOR JAM | D41: Rmt | E41: 21 | F41: 1390 | G41: =F41*E41 -> 29190
B42: Providing and Fixing Granite door jam , The thickness of the wall ( 150mm ) all round the Door opening to be finished with 18mm thk approved granite, edges chamfered. Complete as per detailed drawing and instructions of the Architect | C42: Basic Rate - 200/Sqft
A44: =A41+0.01 -> 1.11 | B44: GRANITE STEPS | D44: Sqm | E44: 1 | F44: 12895 | G44: =F44*E44 -> 12895
B45: Providing and Fixing Granite Steps , The steps are bulid by solid block a solid block with 150mm riser & 300mm tread to be finished with 18mm thk approved granite, edges chamfered. Complete as per detailed drawing and instructions of the Architect | C45: Basic Rate - 200/Sqft
B47: SUB TOTAL CARRIED TO SUMMARY | G47: =SUM(G4:G46) -> 2445286.5
A48: 3 | B48: FLOORING
A50: =A48+0.01 -> 3.01 | B50: TILE FLOORING | D50: Sqm | E50: 257 | F50: 2125 | G50: =F50*E50 -> 546125
B51: Providing and laying to pattern, 10mm thick tile flooring Tiling using tiles of size given below , colour and make to pattern over Adhesive of make Latricrete / Polyglaze including joints shall be pointed with the matching cement based polymer grout as recommended by Laticrete/ Ardex Endura or approved equivalent, etc., Allow for protective plastic sheet to protect the tile till the handing over, the rate inclusive of providing necessary spacers to ensure uniform joints etc. complete. Rate including Materials, Manpower, Machinery, Tools, Transportation, Shifting to the required location, all wastages like design, pattern and handling, Lead and Lifts and all other necessary works required to complete full scope of Job at all locations and levels as per drawings and technical specifications. | C51: Basic Rate - 65/Sqft
A53: =A50+0.01 -> 3.02 | B53: Same as above 3.01 Tile Flooring | C53: Basic Rate -50/Sqft | D53: Sqm | E53: 93 | F53: 1899 | G53: =F53*E53 -> 176607
A55: =A53+0.01 -> 3.03 | B55: Same as above 3.01 Tile Flooring | C55: Basic Rate -60/Sqft | D55: Sqm | E55: 0 | F55: 2049 | G55: =F55*E55 -> 0
A57: =A55+0.01 -> 3.04 | B57: Same as above 3.01 Tile Flooring | C57: Basic Rate -200/Sqft | D57: Sqm | E57: 93 | F57: 4163 | G57: =F57*E57 -> 387159
A59: =A55+0.01 -> 3.04 | B59: VINYL FLOORING
B60: Providing & laying 3mm thick vinyl flooring over existing floor surface to proper level, line including joint treatment, complete as per detail drawing & Architect's instruction. Cost to include provididng and laying Self levelling screed 3-5 mm thk under the vinyl flooring. | C60: Basic Rate - 240/Sqft | D60: Sqm | E60: 755 | F60: 4400 | G60: =F60*E60 -> 3322000
A62: =A59+0.01 -> 3.05 | B62: GFX FLOORING
B63: Surface Preparation : Grinding the surface using M75 metal grit Primer Application: Providing and applying primer in one coat while simultaneously broadcasting quartz sand. GFX - Seamless Concrete Installation: Providing and installing the GFX - Seamless concrete floor, which is a blend of imported engineered cements from Ardex and polymer additives. Final Polishing: Sanding/grinding of the floor after a minimum interval of 24 hours. Sealer Application: Providing and installing of multiple coats of Green heart sealers Total thickness after self levelling: 5mm Base price : 330/- sft | C63: Basic Rate - 330/- sft | D63: Sqm | E63: QRO | F63: 4529
A65: =A50+0.01 -> 3.02 | B65: ANTI STATIC FLOORING | D65: Sqm | E65: 65 | F65: 2239 | G65: =F65*E65 -> 145535
B66: Providing and laying 2mm thk Anti Static Vinyl flooring of Approved make for areas as indicated. Joints to be perfect machine like straight cut without jagged edges, welded at joints. The Surface to be smooth and in level without any bubbles or creases. Rate to be inclusive of self levelling 3-5 mm thickness. | C66: Basic Rate - 90/Sqft
A68: =A65+0.01 -> 3.03 | B68: EPOXY FLOORING | D68: Sqm | E68: 104 | F68: 1749 | G68: =F68*E68 -> 181896
B69: Providing and applying a 3-coat epoxy floor coating system in the AHU room, including surface preparation by mechanical grinding, application of epoxy primer, high-build 100% solids epoxy base coat (300–500 microns), and an optional UV-resistant topcoat for added durability. The system shall be resistant to chemicals, moisture, and abrasion, with a slip-resistant finish if required. All materials, labour, tools, and equipment shall be included, and the work shall be completed as per manufacturer’s specifications and instructions of the Engineer-in-Charge.
A71: =A68+0.01 -> 3.04 | B71: CARPET FLOORING | D71: Sqm | E71: 1401 | F71: 1968 | G71: =F71*E71 -> 2757168
B72: Supply, Laying of carpet tiles over hardflooring by approved authorised dealer only. Construction-Tufted, Structured Loop PileFace Fibre; ECONYL® Type 6 nylon made with 100% regenerated nylon; Finished Face Weight-490 g/m2; Gauge-47.2/10 cm; Rows-44/10 cm; Tuft Density-224 000/m2; Finished Pile Height-2.5mm; Standard Backing Comfort Lite 90% Recycled content,Polyurethane cushion. Nominal Total Thickness-8.3 mm Nominal Total Weight-3 800 g/m2 | C72: Basic Rate -130/Sqft
A74: =A71+0.01 -> 3.05 | B74: Same as above Carpet Floorig | C74: Basic Rate -150/Sqft | D74: Sqm | E74: 111 | F74: 2317 | G74: =F74*E74 -> 257187
A76: =A74+0.01 -> 3.06 | B76: RAISED FLOORING | D76: Sqm | E76: 22 | F76: 5352 | G76: =F76*E76 -> 117744
B77: Raised Floor: The system should be of nominal 600mm x 600mm (35mm thick) modular panels with heavy-duty pedestals and stringers. The total system weight shall not exceed 40Kg/Sqmt. The system shall be able to withstand a UDL of 800 kg/Sqmt and a point load of 360 kgs/sq.inc Panels: Panels shall be made of steel with an infill of light wt, non-combustible cementitious material. The bottom of the panel shall be embossed in a hemispherical shape to give strength and flexural rigidity. The infill material shall not become loose when the panels are cut. The panel should be able to withstand an ultimate load of at least 2.5 times the designed point load. The entire panel shall be coated with epoxy powder coating of 75-100 microns on the exposed surface. The panel top&bottom sheet shall be 0.7/0.7mm resp. The panels shall have a top covering of anti-static high pressure laminate with resistance of 2x105 - 5x109 ohms. The HPL thickness shall not be less than 1.2mm. Pedestals: The pedestal base shall be square of 100mm X 100mm X 2mm bearing area and assemble to a tube of 22mm dia. With 2mm wall thickness. The pedestal head to be not less than 3mm. The pedestals should be able to accept an axial load of 22,500N and and ultimate load not less the 45,000N. pedestal head shall be galvanized die-cut steel welded to a threaded rod with a counter locking leveling nut.
A79: =A76+0.01 -> 3.07 | B79: RUG FLOORING | D79: Sqm | E79: 15 | F79: 10428 | G79: =F79*E79 -> 156420
B80: Supply and installation of approved Inset Rugs as per finishes schedule, laid over finished substrata with approved edging and protection as required. | C80: Basic Rate - 750/Sqft
A82: =A79+0.01 -> 3.08 | B82: RUBBER FLOORING | D82: Sqm | E82: 16 | F82: 2431 | G82: =F82*E82 -> 38896
B83: Supply and installation of 10 mm thick recycled SBR rubber gym tiles with PU binder, loose-lay / glued (as approved), including primer, edge coving, testing, and finishing, as per manufacturer specification. Rate to include all labor, material, wastage, testing, and finishing. | C83: Basic Rate - 150/Sqft
A85: =A76+0.01 -> 3.07 | B85: ALUMINIUM SKIRTING | D85: Rmt | E85: 1178 | F85: 347 | G85: =F85*E85 -> 408766
B86: Providing & fixing 50mm ht. anodised approved extruded aluminium skirting fixed over masonry wall /opaque partition to proper line & level. The installed skirting shall be provided with approved matchig colour PVC capping, Complete as per manufacturer's specification, installation guidlines & instructions of the Architect.
A88: =A85+0.01 -> 3.08 | B88: TILE SKIRTING | D88: Rmt | E88: 186 | F88: 311 | G88: =F88*E88 -> 57846
B89: Providing & cutting and fixing of Vitrified tile skirting 50 mm high as per pattern shown on relevant drawing including machine cutting of Tile as per required size and 45 degree cut at junctions etc.,. Tile to be bedded in average 12 mm thk cement paste. The work includes paper joint filling with approved material as directed by Engineer In charge of matching color, curing etc complete. The entire work shall be carried out to the satisfaction of the Engineer - in - charge. The rate shall include cleaning of skirting disposal of debris and handing over to the Engineer - in - charge.
A91: =A85+0.01 -> 3.08 | B91: TRANSITION STRIP | D91: Rmt | E91: 106 | F91: 674 | G91: =F91*E91 -> 71444
B92: Providing and fixing Transition strip at junction of carpet and granite floor, carpet and vitrified floor etc., , edge buffing and fixing complete. As per the following specification.
A94: =A88+0.01 -> 3.09 | B94: GRADIENT TRANSITION STRIP | D94: Rmt | E94: 247 | F94: 4407 | G94: =F94*E94 -> 1088529
B95: Providing and fixing Transition strip at junction of carpet and granite floor, carpet and vitrified floor etc., , edge buffing and fixing complete. As per the following specification.
A97: =A94+0.01 -> 3.1 | B97: GRANITE THRESHOLD | D97: Rmt | E97: 32 | F97: 1038 | G97: =F97*E97 -> 33216
B98: Providing and installing 19mm thick polished Granite ledge of 100 to 150mm wide, the exposed edge of the ledge shall be ground to full round shall polished to gloss. The ledge formed shall be installed over a 1:3 cement mortar bedding of average 25mm thick set in cement slurry, the joints shall be grouted in approved matching colour epoxy grout. Price quoted shall be inclusive of lead, lift, required stagging, scaffolding etc., complete as per detail drawing. | C98: Basic Rate -200/Sqft
A100: =A97+0.01 -> 3.11 | B100: RAISED PLATFORM | D100: Sqm | E100: 6 | F100: 2287 | G100: =F100*E100 -> 13722
B101: Providing and constructing 150 mm high raised flooring using solid cement blocks/bricks with screed topping, complete with materials, labour, leveling, curing, finishing and ready to receive final floor finish.
A103: =A100+0.01 -> 3.12 | B103: STEPS | D103: Sqm | E103: 1 | F103: 10741 | G103: =F103*E103 -> 10741
B104: Providing and fixing steps with 300mm tread & 150mm riser made of 25 x 25mm MS Frame Work fixed on to the ground , The top to be covered with a layer of 19mm thk Fire Proof Plywood to be finished with 1mm thk Antistatic Laminate to match with the False Flooring Tile , complete as the detail dwg and the Architects instructions
A106: =A103+0.01 -> 3.13 | B106: 3M MATT | D106: Sqm | E106: 12 | F106: 5517 | G106: =F106*E106 -> 66204
B107: Providing & fixing of rest room matt
A109: =A106+0.01 -> 3.14 | B109: ARTIFICAIL TURF | D109: Sqm | E109: 210 | F109: 1720 | G109: =F109*E109 -> 361200
B110: Supplying and fixing interior artificial turf of approved make, manufactured from high-quality, non-toxic and UV-stabilized polyethylene/polypropylene fibers, with pile height of 20–30 mm, high stitch density, uniform green color, and durable latex or PU backing, suitable for indoor use without loose infill, laid over prepared floor surface (cement/tile/wood) using approved adhesive or fixing method, including surface cleaning, alignment, jointing, edge trimming, and finishing complete in all respects as per drawings, interior designer/engineer’s instructions, and to the satisfaction of the client, | C110: Basic Rate - 110/Sqft
B112: SUB TOTAL CARRIED TO SUMMARY | G112: =SUM(G48:G111) -> 10198405
A113: 4 | B113: FALSE CEILING
A114: =A113+0.01 -> 4.01 | B114: GYPSUM FALSE CEILING | D114: Sqm | E114: 617 | F114: 1278 | G114: =F114*E114 -> 788526 | L114: =E126 -> 189 | M114: =L114*25*1.25*10.764 -> 63574.875
B115: Providing and fixing Suspended False Ceiling which includes Gypsum Plaster board 12mm thk., False Ceiling on 24 gauge G.I. frame work which includes Providing. & fixing G.I. perimeter channels 0.55 mm thk 20mmx30mm,web size 27mm along perimeter of ceiling, screw fixed to brick wall/partition with nylon sleeves & screws @ approx 2'0" c/c. Suspending G.I. intermediate channels size 45 mm,0.9 mm thk, flanges of size15mm each from the soffit 1220mm c/c with ceiling angle 25 x10mm x 0.55mm thk fixed to soffit G.I. cleat & steel expansion fasteners.
B116: Ceiling section of 0.55mm thk having web of 51.5mm & flanges 26 mm each lips 10.5 mm fixed to intermediate channel with connecting clips & perpendicular to int channel @ 457mm c/c.12.5 mm tapered edge Plaster board ( IS 2095-1982 ) screw fixed to ceiling section with 25mm dry wall screws @ 230 mm c/c. Boards to be joint & finished so as to have flush look including filling finishing edges with jointing compound paper tape/cloth gauze & 2 coats of primer suitable for plaster board. Rate to include M.S.framing around A/C ducts where ever necessary.
A118: =A114+0.01 -> 4.02 | B118: GYPSUM FALSE CEILING COVE - SAME AS ABOVE SPEC | D118: Rmt | E118: 527 | F118: 328 | G118: =F118*E118 -> 172856
A120: =A118+0.01 -> 4.03 | B120: GYPSUM FALSE CEILING U SHAPE - SAME AS ABOVE SPEC | D120: Rmt | E120: 27 | F120: 984 | G120: =F120*E120 -> 26568
A122: =A120+0.01 -> 4.04 | B122: MR GRID CEILING | D122: Sqm | E122: 4 | F122: 1615 | G122: =F122*E122 -> 6460
B123: Providing and fixing Suspended False Ceiling which includes Moisture Resistance Gypsum Plaster board 12mm thk., False Ceiling on 24 gauge G.I. frame work which includes Providing. & fixing G.I. perimeter channels 0.55 mm thk 20mmx30mm,web size 27mm along perimeter of ceiling, screw fixed to brick wall/partition with nylon sleeves & screws @ approx 2'0" c/c. Suspending G.I. intermediate channels size 45 mm,0.9 mm thk, flanges of size15mm each from the soffit 1220mm c/c with ceiling angle 25 x10mm x 0.55mm thk fixed to soffit G.I. cleat & steel expansion fasteners.
B124: Ceiling section of 0.55mm thk having web of 51.5mm & flanges 26 mm each lips 10.5 mm fixed to intermediate channel with connecting clips & perpendicular to int channel @ 457mm c/c.12.5 mm tapered edge Plaster board ( IS 2095-1982 ) screw fixed to ceiling section with 25mm dry wall screws @ 230 mm c/c. Boards to be joint & finished so as to have flush look including filling finishing edges with jointing compound paper tape/cloth gauze & 2 coats of primer suitable for plaster board. Rate to include M.S.framing around A/C ducts where ever necessary.
A126: =A122+0.01 -> 4.05 | B126: MODULAR GRID CEILING-GR-1 -600x600MM -0.9NRC | D126: Sqm | E126: 189 | F126: 2431 | G126: =F126*E126 -> 459459
B127: Providing & installing Commercial type suspended modular ceiling consisting of
B128: General requisites
B129: Grids width: 15mm Silhouette with black revel finished in approved shade. The main Runners & cross Tees to have "stab" installation system made of corrosion-protected high tensile steel OR approved equivalent.
B130: Tile specification :
B131: Tile type: Lay-in ceiling type
B132: Tile size: 600mm X 600mm X 15mm thk.
B133: Edge detail : Recessed Bevelled Edge
B134: Light reflectance: up to 0.90 ( 90% )
B135: Humidity resistance: 95% RH
B136: Color: approved RAL
B137: Surface burning characters: Class1, BS 476:Part 7:1987
B138: Smoke Developed: 0 & Flame Spread = 5 as per UL
... B153: All extra tiles occupied by lights and diffusers to be returned to Owner.
A155: =A122+0.01 -> 4.05 | B155: MODULAR GRID CEILING-GR-1 -600x600MM -0.7NRC | D155: Sqm | E155: 64 | F155: 1926 | G155: =F155*E155 -> 123264
B156: Providing & installing Commercial type suspended modular ceiling consisting of
B157: General requisites
...

Sheet M Sheet
A1: Civil Work Measurement Sheet
A2: Sl.No | B2: Description | C2: Unit | D2: Nos | E2: Length | F2: Width | G2: Height | H2: Total QTY
A4: 1 | B4: Pest Control | C4: Sqm
C5: Sqm | D5: 1 | E5: 56.55 | F5: 46.1 | H5: =PRODUCT(D5:G5) -> 2606.955
C6: Sqm | D6: 0.5 | E6: 24.47 | F6: 2.037 | H6: =PRODUCT(D6:G6) -> 24.922695
B7: Kitchen Deduction | C7: Sqm | D7: -1 | E7: 11 | F7: 9.8 | H7: =PRODUCT(D7:G7) -> -107.8
B8: Electrical & AHU Room | C8: Sqm | D8: -1 | E8: 14.5 | F8: 9 | H8: =PRODUCT(D8:G8) -> -130.5
B9: Balcony | C9: Sqm | D9: -1 | E9: 3.3 | F9: 7.9 | H9: =PRODUCT(D9:G9) -> -26.07
B10: Toilet | C10: Sqm | D10: -1 | E10: 6 | F10: 11.25 | H10: =PRODUCT(D10:G10) -> -67.5
B11: Ladies Toilet | C11: Sqm | D11: -1 | E11: 4 | F11: 9.67 | H11: =PRODUCT(D11:G11) -> -38.68
B12: Gents Toilet | C12: Sqm | D12: -1 | E12: 3.95 | F12: 12.42 | H12: =PRODUCT(D12:G12) -> -49.059
B13: Outdoor Seating | C13: Sqm | D13: -1 | E13: 7.6 | F13: 7.786 | H13: =PRODUCT(D13:G13) -> -59.1736
C14: Sqm | D14: -1 | E14: 4.115 | F14: 3.9 | H14: =PRODUCT(D14:G14) -> -16.0485
C15: Sqm | D15: -1 | E15: 3.15 | F15: 22.7 | H15: =PRODUCT(D15:G15) -> -71.505
B16: Near Staircase | C16: Sqm | D16: 1 | E16: 10.85 | F16: 21.65 | H16: =PRODUCT(D16:G16) -> 234.9025
B17: AHU Room | C17: Sqm | D17: -1 | E17: 7.1 | F17: 6.2 | H17: =PRODUCT(D17:G17) -> -44.02
C18: Sqm | D18: 1 | E18: 1.9 | F18: 0.6 | H18: =PRODUCT(D18:G18) -> 1.14
B19: Corner | C19: Sqm | D19: -1 | E19: 1.3 | F19: 15.09 | H19: =PRODUCT(D19:G19) -> -19.617
C20: Sqm | D20: 1 | E20: 12.25 | F20: 23.775 | H20: =PRODUCT(D20:G20) -> 291.24375
B21: Infront of Stair | C21: Sqm | D21: 1 | E21: 1.5 | F21: 1.1 | H21: =PRODUCT(D21:G21) -> 1.65
B22: Infront of Toilet | C22: Sqm | D22: 1 | E22: 3.4 | F22: 1.7 | H22: =PRODUCT(D22:G22) -> 5.78
C23: Sqm | D23: 1 | E23: 13.1 | F23: 26.175 | H23: =PRODUCT(D23:G23) -> 342.8925
B24: Triangle Portion | C24: Sqm | D24: 0.5 | E24: 3.81 | F24: 1.11 | H24: =PRODUCT(D24:G24) -> 2.11455
C25: Sqm | D25: -0.5 | E25: 7.7 | F25: 2.158 | H25: =PRODUCT(D25:G25) -> -8.3083
B26: AHU & Electrical Room Front | C26: Sqm | D26: 1 | E26: 0.8 | F26: 1.9 | H26: =PRODUCT(D26:G26) -> 1.52
C27: Sqm | D27: 1 | E27: 6.6 | F27: 6.625 | H27: =PRODUCT(D27:G27) -> 43.725
C28: Sqm | D28: 1 | E28: 0.8 | F28: 3.75 | H28: =PRODUCT(D28:G28) -> 3
B29: Ladies Toilet | C29: Sqm | D29: 1 | E29: 11.05 | F29: 4.15 | H29: =PRODUCT(D29:G29) -> 45.8575
C30: Sqm | D30: -1 | E30: 1.3 | F30: 1.85 | H30: =PRODUCT(D30:G30) -> -2.405
C31: Sqm | D31: -1 | E31: 2.25 | F31: 4.24 | H31: =PRODUCT(D31:G31) -> -9.54
B32: PH Toilet | C32: Sqm | D32: 1 | E32: 2.4 | F32: 2.15 | H32: =PRODUCT(D32:G32) -> 5.16
C33: Sqm | D33: 1 | E33: 1.25 | F33: 2.4 | H33: =PRODUCT(D33:G33) -> 3
B34: Gents Toilet | C34: Sqm | D34: 1 | E34: 12.22 | F34: 4.15 | H34: =PRODUCT(D34:G34) -> 50.713
C35: Sqm | D35: -1 | E35: 2.32 | F35: 0.6 | H35: =PRODUCT(D35:G35) -> -1.392
B36: Gents Toilet -2 | C36: Sqm | D36: 1 | E36: 11.2 | F36: 4.15 | H36: =PRODUCT(D36:G36) -> 46.48
C37: Sqm | D37: 1 | E37: 2.54 | F37: 1.25 | H37: =PRODUCT(D37:G37) -> 3.175
B38: PH Toilet 02 | C38: Sqm | D38: 1 | E38: 2.54 | F38: 2.15 | H38: =PRODUCT(D38:G38) -> 5.461
B39: Ladies Toilet -2 | C39: Sqm | D39: 1 | E39: 11.2 | F39: 4.15 | H39: =PRODUCT(D39:G39) -> 46.48
C40: Sqm | D40: -1 | E40: 1.3 | F40: 1.95 | H40: =PRODUCT(D40:G40) -> -2.535
C41: Sqm | D41: -1 | E41: 4.44 | F41: 2.25 | H41: =PRODUCT(D41:G41) -> -9.99
B43: Total | H43: =SUM(H5:H42) -> 3102.0291
B44: Add - 5%
B45: Grand Total | H45: =ROUND(SUM(H43:H44),0) -> 3102
A47: 1 | B47: Screed | C47: Sqm
C48: Sqm | D48: 1 | E48: 56.55 | F48: 46.1 | H48: =PRODUCT(D48:G48) -> 2606.955
C49: Sqm | D49: 0.5 | E49: 24.47 | F49: 2.037 | H49: =PRODUCT(D49:G49) -> 24.922695
B50: Kitchen Deduction | C50: Sqm | D50: -1 | E50: 11 | F50: 9.8 | H50: =PRODUCT(D50:G50) -> -107.8
B51: Electrical & AHU Room | C51: Sqm | D51: -1 | E51: 14.5 | F51: 9 | H51: =PRODUCT(D51:G51) -> -130.5
B52: Balcony | C52: Sqm | D52: -1 | E52: 3.3 | F52: 7.9 | H52: =PRODUCT(D52:G52) -> -26.07
B53: Toilet | C53: Sqm | D53: -1 | E53: 6 | F53: 11.25 | H53: =PRODUCT(D53:G53) -> -67.5
B54: Ladies Toilet | C54: Sqm | D54: -1 | E54: 4 | F54: 9.67 | H54: =PRODUCT(D54:G54) -> -38.68
B55: Gents Toilet | C55: Sqm | D55: -1 | E55: 3.95 | F55: 12.42 | H55: =PRODUCT(D55:G55) -> -49.059
B56: Outdoor Seating | C56: Sqm | D56: -1 | E56: 7.6 | F56: 7.786 | H56: =PRODUCT(D56:G56) -> -59.1736
C57: Sqm | D57: -1 | E57: 4.115 | F57: 3.9 | H57: =PRODUCT(D57:G57) -> -16.0485
C58: Sqm | D58: -1 | E58: 3.15 | F58: 22.7 | H58: =PRODUCT(D58:G58) -> -71.505
B59: Near Staircase | C59: Sqm | D59: 1 | E59: 10.85 | F59: 21.65 | H59: =PRODUCT(D59:G59) -> 234.9025
B60: AHU Room | C60: Sqm | D60: -1 | E60: 7.1 | F60: 6.2 | H60: =PRODUCT(D60:G60) -> -44.02
C61: Sqm | D61: 1 | E61: 1.9 | F61: 0.6 | H61: =PRODUCT(D61:G61) -> 1.14
B62: Corner | C62: Sqm | D62: -1 | E62: 1.3 | F62: 15.09 | H62: =PRODUCT(D62:G62) -> -19.617
C63: Sqm | D63: 1 | E63: 12.25 | F63: 23.775 | H63: =PRODUCT(D63:G63) -> 291.24375
B64: Infront of Stair | C64: Sqm | D64: 1 | E64: 1.5 | F64: 1.1 | H64: =PRODUCT(D64:G64) -> 1.65
B65: Infront of Toilet | C65: Sqm | D65: 1 | E65: 3.4 | F65: 1.7 | H65: =PRODUCT(D65:G65) -> 5.78
C66: Sqm | D66: 1 | E66: 13.1 | F66: 26.175 | H66: =PRODUCT(D66:G66) -> 342.8925
B67: Triangle Portion | C67: Sqm | D67: 0.5 | E67: 3.81 | F67: 1.11 | H67: =PRODUCT(D67:G67) -> 2.11455 | J67: =251020 -> 251020
C68: Sqm | D68: -0.5 | E68: 7.7 | F68: 2.158 | H68: =PRODUCT(D68:G68) -> -8.3083 | J68: =J67*1.08 -> 271101.6
B69: AHU & Electrical Room Front | C69: Sqm | D69: 1 | E69: 0.8 | F69: 1.9 | H69: =PRODUCT(D69:G69) -> 1.52
C70: Sqm | D70: 1 | E70: 6.6 | F70: 6.625 | H70: =PRODUCT(D70:G70) -> 43.725
C71: Sqm | D71: 1 | E71: 0.8 | F71: 3.75 | H71: =PRODUCT(D71:G71) -> 3
B72: Column | C72: Sqm | D72: -15 | E72: 0.9 | F72: 0.9 | H72: =PRODUCT(D72:G72) -> -12.15
B73: Column | C73: Sqm | D73: -6 | E73: 1.2 | F73: 1 | H73: =PRODUCT(D73:G73) -> -7.2
B74: Column | C74: Sqm | D74: -2 | E74: 1 | F74: 0.9 | H74: =PRODUCT(D74:G74) -> -1.8
B75: Column | C75: Sqm | D75: -3 | E75: 0.9 | F75: 0.8 | H75: =PRODUCT(D75:G75) -> -2.16
B76: Column | C76: Sqm | D76: -2 | E76: 2.5 | F76: 0.9 | H76: =PRODUCT(D76:G76) -> -4.5
B77: Column | C77: Sqm | D77: -1 | E77: 0.9 | F77: 0.55 | H77: =PRODUCT(D77:G77) -> -0.495
C78: Sqm | D78: -1 | E78: 0.7 | F78: 0.725 | H78: =PRODUCT(D78:G78) -> -0.5075
C79: Sqm | D79: -1 | E79: 1.32 | F79: 0.7 | H79: =PRODUCT(D79:G79) -> -0.924
B80: Shaft | C80: Sqm | D80: -1 | E80: 5.3 | F80: 1.425 | H80: =PRODUCT(D80:G80) -> -7.5525
C81: Sqm | D81: -1 | E81: 1.3 | F81: 1.1 | H81: =PRODUCT(D81:G81) -> -1.43
B82: Ladies Toilet | C82: Sqm | D82: 1 | E82: 11.05 | F82: 4.15 | H82: =PRODUCT(D82:G82) -> 45.8575
C83: Sqm | D83: -1 | E83: 1.3 | F83: 1.85 | H83: =PRODUCT(D83:G83) -> -2.405
C84: Sqm | D84: -1 | E84: 2.25 | F84: 4.24 | H84: =PRODUCT(D84:G84) -> -9.54
B85: PH Toilet | C85: Sqm | D85: 1 | E85: 2.4 | F85: 2.15 | H85: =PRODUCT(D85:G85) -> 5.16
C86: Sqm | D86: 1 | E86: 1.25 | F86: 2.4 | H86: =PRODUCT(D86:G86) -> 3
B87: Gents Toilet | C87: Sqm | D87: 1 | E87: 12.22 | F87: 4.15 | H87: =PRODUCT(D87:G87) -> 50.713
C88: Sqm | D88: -1 | E88: 2.32 | F88: 0.6 | H88: =PRODUCT(D88:G88) -> -1.392
B89: Gents Toilet -2 | C89: Sqm | D89: 1 | E89: 11.2 | F89: 4.15 | H89: =PRODUCT(D89:G89) -> 46.48
C90: Sqm | D90: 1 | E90: 2.54 | F90: 1.25 | H90: =PRODUCT(D90:G90) -> 3.175
B91: PH Toilet 02 | C91: Sqm | D91: 1 | E91: 2.54 | F91: 2.15 | H91: =PRODUCT(D91:G91) -> 5.461
B92: Ladies Toilet -2 | C92: Sqm | D92: 1 | E92: 11.2 | F92: 4.15 | H92: =PRODUCT(D92:G92) -> 46.48
C93: Sqm | D93: -1 | E93: 1.3 | F93: 1.95 | H93: =PRODUCT(D93:G93) -> -2.535
C94: Sqm | D94: -1 | E94: 4.44 | F94: 2.25 | H94: =PRODUCT(D94:G94) -> -9.99
B97: Total | H97: =SUM(H48:H96) -> 3063.3101
B98: Add - 5%
B99: Grand Total | H99: =ROUND(SUM(H97:H98),0) -> 3063
A101: 2 | B101: 150mm ThicK Block work | C101: Sqm
B102: Electrical Room | C102: Sqm | D102: 1 | E102: 1.8 | F102: 2.4 | H102: =PRODUCT(D102:G102) -> 4.32
B103: Electrical Room | C103: Sqm | D103: 1 | E103: 3.5 | F103: 3.5 | H103: =PRODUCT(D103:G103) -> 12.25
C104: Sqm | D104: -1 | E104: 1 | F104: 2.4 | H104: =PRODUCT(D104:G104) -> -2.4
B105: Hand Wash Area | C105: Sqm | D105: 1 | E105: 3 | F105: 3.5 | H105: =PRODUCT(D105:G105) -> 10.5
C106: Sqm | D106: 1 | E106: 4.7 | F106: 3.5 | H106: =PRODUCT(D106:G106) -> 16.45
...

Sheet Modular
A1: BOQ for Interior Furniture
A3: Sl.No | B3: Description | C3: LOCATION | D3: Unit | E3: TOTAL | F3: Rate | G3: Amount
B4: MODULAR FURNITURE
A5: 1 | B5: Linear workstation (1350 x 750mm) | D5: Nos | E5: =33+48+4+8+8+40+8+12+18+2+1+6+39+16+15+1 -> 259 | F5: 9750 | G5: =F5*E5 -> 2525250
A6: =A5+1 -> 2 | B6: Linear workstation with Shelves (1350 x 750mm) | D6: Nos | E6: 0 | F6: 10625 | G6: =F6*E6 -> 0
A7: =A6+1 -> 3 | B7: Height Adjustable work station (1350 x 750mm) | D7: Nos | E7: 21 | F7: 36875 | G7: =F7*E7 -> 774375
A8: =A7+1 -> 4 | B8: L Shape work station (1500 x 1200mm) | D8: Nos | E8: 12 | F8: 20375 | G8: =F8*E8 -> 244500
A9: =A8+1 -> 5 | B9: Pedestal Unit | D9: Nos | E9: =E5+E6+E8+2 -> 273 | F9: 4000 | G9: =F9*E9 -> 1092000
A10: =A9+1 -> 6 | B10: Manager Cabin with Storage unit (2100 x 2100mm) | D10: Nos | E10: 12 | F10: 31250 | G10: =F10*E10 -> 375000
A11: =A10+1 -> 7 | B11: CEO Cabin Table with Side Storage (2100 x 2100mm) | D11: Nos | E11: 1 | F11: 47500 | G11: =F11*E11 -> 47500
A12: =A11+1 -> 8 | B12: Movable & foldable workstation (1650 x 600mm) | D12: Nos | E12: 24 | F12: 31250 | G12: =F12*E12 -> 750000
A13: =A12+1 -> 9 | B13: 8 Pax Table (3000 x 1200mm) | D13: Nos | E13: 2 | F13: 31250 | G13: =F13*E13 -> 62500
A14: =A13+1 -> 10 | B14: 6 Pax Table (2200 x 1200mm) | D14: Nos | E14: 3 | F14: 21875 | G14: =F14*E14 -> 65625
A15: =A14+1 -> 11 | B15: 4 Pax circular Table (1200mm) | D15: Nos | E15: 3 | F15: 13750 | G15: =F15*E15 -> 41250
A16: =A15+1 -> 12 | B16: 3 Pax circular Table (900mm) | D16: Nos | E16: 3 | F16: 10625 | G16: =F16*E16 -> 31875
A17: =A16+1 -> 13 | B17: 15 Pax Table (5620 x 1600mm) | D17: Nos | E17: 1 | F17: 65000 | G17: =F17*E17 -> 65000
A18: =A17+1 -> 14 | B18: Linear Table (1200 x 600mm) | D18: Nos | E18: 8 | F18: 8125 | G18: =F18*E18 -> 65000
A19: =A18+1 -> 15 | B19: Café Table (1200 x 750mm) | D19: Nos | E19: 19 | F19: 18750 | G19: =F19*E19 -> 356250
A20: =A19+1 -> 16 | B20: Café Table (1800 x 750mm) | D20: Nos | E20: 4 | F20: 18750 | G20: =F20*E20 -> 75000
A21: =A20+1 -> 17 | B21: 1200mm Dia Café Table | D21: Nos | E21: 5 | F21: 17500 | G21: =F21*E21 -> 87500
A22: =A21+1 -> 18 | B22: Booth Table | D22: Nos | E22: 5 | F22: 11875 | G22: =F22*E22 -> 59375
B25: CHAIRS
A26: =A22+1 -> 19 | B26: Work Station Chairs : Back Height - Medium Back Back Finish - HNI Standard Response Mesh with adjustable lumbar support Back Frame - Black Color Seat Finish - HNI Standard Fabric Seat Height Adjustment - Pneumatic Mechanism - Weight activated with Seat depth Back Tilt Lock - Mutipoint Lock (3 point Lock) Back Tilt Tension - Adjustable Armrests Type - 3D Adjustable arms Armpads Type - Polyurethane Base Type - 5-Star in black nylon base Greenguard Certified Product BIFMA Certified : (ANSI/BIFMA-X5.1-2017) LCA & EPD Certifications WARRANTY: 10 Years from the date of invoice | D26: Nos | E26: 381 | F26: 11000 | G26: =F26*E26 -> 4191000
A27: =A26+1 -> 20 | B27: VP Cabin Chairs: Back Height - High Back (with Headrest) Back Finish - HNI Standard Response Mesh with adjustable lumbar support Back Frame - Black Color Seat Finish - HNI Standard Fabric Seat Height Adjustment - Pneumatic Mechanism - Weight activated with Seat depth Back Tilt Lock - Mutipoint Lock (3 point Lock) Back Tilt Tension - Adjustable Armrests Type - 3D Adjustable arms Armpads Type - Polyurethane Base Type - 5-Star in black nylon base Greenguard Certified Product BIFMA Certified : (ANSI/BIFMA-X5.1-2017) LCA & EPD Certifications WARRANTY: 10 Years from the date of invoice | C27: VP Cabin | D27: Nos | E27: 12 | F27: 13500 | G27: =F27*E27 -> 162000
A28: =A27+1 -> 21 | B28: Meeting Room Chairs (Equivalent to Helix) : Specification: Back Height - High Back (with Headrest) Back Finish - HNI Standard Response Mesh with adjustable lumbar support Back Frame - Black Color Seat Finish - HNI Standard Fabric Seat Height Adjustment - Pneumatic Mechanism - Weight activated with Seat depth Back Tilt Lock - Mutipoint Lock (3 point Lock) Back Tilt Tension - Adjustable Armrests Type - 4D Adjustable arms Armpads Type - Polyurethane Base Type - 5-Star in black nylon base Greenguard Certified Product BIFMA Certified : (ANSI/BIFMA-X5.1-2017) LCA & EPD Certifications WARRANTY: 10 Years from the date of invoice | C28: Board Room, CEO & Founder Cabin | D28: Nos | E28: 17 | F28: 31250 | G28: =F28*E28 -> 531250
A29: =A28+1 -> 22 | B29: Training Room Chairs | C29: Training Room | D29: Nos | E29: 42 | F29: 17500 | G29: =F29*E29 -> 735000
A30: =A29+1 -> 23 | B30: Café Chairs with Arm rest | D30: Nos | E30: 20 | F30: 5313 | G30: =F30*E30 -> 106260
A31: 24 | B31: Café Chairs without Arm rest | D31: Nos | E31: 44 | F31: 4938 | G31: =F31*E31 -> 217272
B33: LOOSE FURNITURE
A34: =A31+1 -> 25 | B34: Center Table - 600mm Dia | C34: Wellness Room, Media byte Room & VR Room | D34: Nos | E34: 4 | F34: 13750 | G34: =F34*E34 -> 55000
A35: =A34+1 -> 26 | B35: Center Table - 600mm Dia x 750mm Height | C35: War Room ; 2 Pax | D35: Nos | E35: 3 | F35: 13750 | G35: =F35*E35 -> 41250
A36: =A35+1 -> 27 | B36: Center Table - 600mm Dia | C36: Bench Seating | D36: Nos | E36: 1 | F36: 13750 | G36: =F36*E36 -> 13750
A37: =A36+1 -> 28 | B37: Center Table - 600mm Dia - Double Table | C37: Reception | D37: Nos | E37: 1 | F37: 31250 | G37: =F37*E37 -> 31250
A38: =A37+1 -> 29 | B38: Center Table - 670mm Dia | C38: Collab Area | D38: Nos | E38: 6 | F38: 13750 | G38: =F38*E38 -> 82500
A39: =A38+1 -> 30 | B39: Center Table - 800mm Dia | C39: Reception | D39: Nos | E39: 1 | F39: 15000 | G39: =F39*E39 -> 15000
A40: =A39+1 -> 31 | B40: Center Table - 900mm Dia | C40: Collab Near CEO | D40: Nos | E40: 1 | F40: 15000 | G40: =F40*E40 -> 15000
A41: =A40+1 -> 32 | B41: Single seater sofa | C41: Founder Cabin | D41: Nos | E41: 2 | F41: 22500 | G41: =F41*E41 -> 45000
A42: =A41+1 -> 33 | B42: Single seater sofa | C42: 2 Pax meeting Room | D42: Nos | E42: 2 | F42: 16250 | G42: =F42*E42 -> 32500
A43: =A42+1 -> 34 | B43: Single seater sofa | C43: Media Byte Room | D43: Nos | E43: 2 | F43: 17500 | G43: =F43*E43 -> 35000
A44: =A43+1 -> 35 | B44: Single seater sofa | C44: Collab Near CEO | D44: Nos | E44: 1 | F44: 16875 | G44: =F44*E44 -> 16875
A45: =A44+1 -> 36 | B45: Single seater sofa | C45: VR Room | D45: Nos | E45: 2 | F45: 18125 | G45: =F45*E45 -> 36250
A46: =A45+1 -> 37 | B46: NAP Room Sofa | C46: Nap Room | D46: Nos | E46: 2 | F46: 35000 | G46: =F46*E46 -> 70000
... A54: =A53+1 -> 45 | B54: Executive Dining Chairs | C54: Executive Dining | D54: Nos | E54: 14 | F54: 27500 | G54: =F54*E54 -> 385000
A55: =A54+1 -> 46 | B55: Single seater lounge Sofa | D55: Nos | E55: =E12*2 -> 48 | F55: 15625 | G55: =F55*E55 -> 750000
A56: =A55+1 -> 47 | B56: Phone Booth - Single Seater | D56: Nos | E56: 13 | F56: 225000 | G56: =F56*E56 -> 2925000
A57: =A56+1 -> 48 | B57: 4 Pax Pod | D57: Nos | E57: 2 | F57: 562500 | G57: =F57*E57 -> 1125000
A58: =A57+1 -> 49 | B58: Quad Pod | D58: Nos | E58: 2 | F58: 137500 | G58: =F58*E58 -> 275000
A59: =A58+1 -> 50 | B59: Singular POD (900mm Length x 750mm Width x 1200mm Height ) | C59: Collab | D59: Nos | E59: 2 | F59: 51250 | G59: =F59*E59 -> 102500
A60: =A59+1 -> 51 | B60: Booth Seating | D60: Nos | E60: 10 | F60: 50000 | G60: =F60*E60 -> 500000
A61: =A60+1 -> 52 | B61: Laptop Table for POD | C61: Collab | D61: Nos | E61: 8 | F61: 9375 | G61: =F61*E61 -> 75000
A62: =A61+1 -> 53 | B62: Laptop Table - Height Adjustable | C62: Board Room | D62: Nos | E62: 5 | F62: 17500 | G62: =F62*E62 -> 87500
A63: =A62+1 -> 54 | B63: Bunker Bed | C63: Nap Room | D63: Nos | E63: 2 | F63: 32500 | G63: =F63*E63 -> 65000
A64: =A63+1 -> 55 | B64: Pouf | C64: Collab | D64: Nos | E64: 8 | F64: 8125 | G64: =F64*E64 -> 65000
A65: =A64+1 -> 56 | B65: Pouf - Different Shape | C65: Experience Center | D65: Nos | E65: 2 | F65: 10750 | G65: =F65*E65 -> 21500
A66: =A65+1 -> 57 | B66: Café Sofa - 2 Seater | C66: Executive Dining | D66: Nos | E66: 4 | F66: 47500 | G66: =F66*E66 -> 190000
A67: =A66+1 -> 58 | B67: High Bar Chair | C67: Collab | D67: Nos | E67: =6+4+6+14 -> 30 | F67: 10000 | G67: =F67*E67 -> 300000
A68: =A67+1 -> 59 | B68: Movable TV Screen | D68: Nos | E68: 3 | F68: 62500 | G68: =F68*E68 -> 187500
A69: =A68+1 -> 60 | B69: Experience Center Sofa | C69: Experience Center | D69: Nos | E69: 1 | F69: 118750 | G69: =F69*E69 -> 118750
A70: =A69+1 -> 61 | B70: L Shape Table | C70: Collab | D70: Nos | E70: 1 | F70: 168750 | G70: =F70*E70 -> 168750
A71: =A70+1 -> 62 | B71: Board Room Sofa | D71: Nos | E71: 3 | F71: 47500 | G71: =F71*E71 -> 142500
A72: =A71+1 -> 63 | B72: War Room Sofa | C72: War Room | D72: Nos | E72: 1 | F72: 47500 | G72: =F72*E72 -> 47500
B74: Total Modular | G74: =SUM(G5:G73) -> 21214157

Sheet Outdoor Furniture
A1: BOQ for Interior Furniture
A3: Sl.No | B3: Description | C3: Unit | D3: TOTAL | E3: Rate | F3: Amount
B4: EXTERNAL FURNITURE
A5: 1 | B5: Outdoor Café Table (1200mm x 800mm) | C5: Nos | D5: 20 | E5: 25000 | F5: =E5*D5 -> 500000
A6: 2 | B6: 1200mm Dia Café Table | C6: Nos | D6: 5 | E6: 27500 | F6: =E6*D6 -> 137500
A7: 3 | B7: Café Chair | C7: Nos | D7: =D6*4+12*4+3 -> 71 | E7: 5625 | F7: =E7*D7 -> 399375
A8: 4 | B8: Café Sofa | C8: Nos | D8: 14 | E8: 43750 | F8: =E8*D8 -> 612500
A9: 5 | B9: FRP Pot with Plants | C9: Rmt | D9: 28 | E9: 6875 | F9: =E9*D9 -> 192500
A10: 6 | B10: FRP Pot with Plants | C10: Nos | D10: 5 | E10: 6250 | F10: =E10*D10 -> 31250
A11: 7 | B11: CANOPY SERVICE WORK | C11: LS | D11: 1 | E11: 375000 | F11: =E11*D11 -> 375000
A12: 8 | B12: CAFÉ UMPERLLA | C12: Nos | D12: 5 | E12: 18750 | F12: =E12*D12 -> 93750
B14: Total Modular | F14: =SUM(F5:F13) -> 2341875

Sheet Toilet Work
A2: Sl.No | B2: Description | C2: Unit | D2: TOTAL | E2: Rate | F2: Amount
A3: 1.01 | B3: FLOOR CHIPPING | C3: sqm | D3: 87 | E3: 650 | F3: =E3*D3 -> 56550
B4: Chipping and removing of existing concrete with all necessary tools tackles, barricading of the work place, protection of existing finishes, cleaning of the workplace at the end of day's work, clearing of debris, disposing the debris in landfill site allocated by the Municipal Authorities outside the campus and preparing the place to receive the next finish as required, complete as per Project Manager's instructions..
A6: =A3+0.01 -> 1.02 | B6: CONTRUCTION OF 150MM THICK SIZE SOLID BLOCK MASONRY | C6: sqm | D6: 21 | E6: 1816 | F6: =E6*D6 -> 38136
B7: Making 150mm thick wall of Solid concrete Block in 1:4 cement mortar, with 2 nos. of 8 mm diameter steel reinforcement in every 4 layer & 2 nos. of hoop iron strips 25mm x 1.6mm, painted with anti-corrosive paint, RCC Lintel at 2400 mm Ht, properly bent and bonded at the end, inclusive of shuttering, scaffolding, Raking of joints and proper curing etc complete. The joints between the RCC and masonry will have hold fasts @ 600mm c/c, with joints finished in chicken mesh 20 gauge and finished with cement plaster
A9: =A6+0.01 -> 1.03 | B9: PLASTERING | C9: sqm | D9: 205 | E9: 471 | F9: =E9*D9 -> 96555
B10: Providing and applying in one coat, avg 12-15mm thick plaster on internal surface of RCC / brick / block walls in cement mortar 1:4, complete to true line & plumb in all levels and locations & finished rough to take on POP punning. Rate shall include for scaffolding, making grooves, sills, pattas, curing, surface preparation before the application of plaster, providing galvanized chicken mesh to a width of 150 mm at the junctions of masonry and RCC structure (column to wall, wall to beam, lintel to beam, corners of walls/columns etc. complete) including tying in position by using suitable nails / clamps / screws and as directed etc. complete at all levels. The contractor shall make good the grooves, pockets etc. after the scaffolding is removed.
A12: =A9+0.01 -> 1.04 | B12: WATERPROOFING | C12: Sqm | D12: 133 | E12: 1009 | F12: =E12*D12 -> 134197
B13: Providing of water proofing - chemical Treatment – the slab to be cleaned and apply 3 coats of chemical on the floor and on the peripheral walls up to 900mm. Base coat – Applying base coat of 1:6 mortar over chemical treatment on the floor and on the peripheral walls up to 450mm.Cost of the water proofing shall include cleaning of the surface of all dirt and grit before the application. The water proofed area shall be ponded and tested for a minimum of 24 hours or as per manufacturer's specification. Note - Warranty to be provided up to 10 years
B14: Clean surface to remove all dust, foreign matters, loose particles or any deposits of contaminants which could affect the bond between the surface and waterproof coating.
B15: Remove all sharp projections and make surface reasonably smooth
B16: Thoroughly pre-wet all concrete surfaces for at least one hour prior to application of coating, by ponding of water on flat surfaces and by vigorous spraying of water on vertical surfaces.
B17: Remove all water from surfaces prior to applying of water proof coating, so that the surface is only damp or surface dry. Standing water or shiny wet surface shall not be present under any circumstances
B18: Apply water proof coating / Brush Topping as specified for various conditions.
B19: Apply 12mm thick cement plaster 1:4 (1cement : 4 coarse sand) after applications of final coat.
B20: After application of final coat of Tape Crete, allow to air dry for 4-6 hours. Do not use any water for curing during this time.
B21: In case of high temperatures and low humidity combined with high wind condition, cover the coating with polythene sheet to prevent rapid drying.
B22: Maximum 6 hours after final application, moist cure for 24 hours by spraying water. Ensure that at no time during this 24 hour period the coating is completely dry or completely submerged in water.
B23: After moist curing, allow to air dry for 3 days.
B24: After air drying, complete the curing by submersion in water for 24 hours.
B25: Make : Fosroc , Sika India Pvt.Ltd
A27: =A12+0.01 -> 1.05 | B27: CINDER FILLING | C27: cum | D27: 27 | E27: 13889 | F27: =E27*D27 -> 375003
B28: Providing cinder filling for the sunken portions a toilet sunken slab and wherever specified with cement mortar 1:3 with approved waterproofing compound including compacting, then the layer of cinder and then surface finishing with cement mortar 1:3 with waterproofing compound evenly to take floor finishing (tiles), inclusive of all leads and lifts, levelling, curing etc. complete as per directions of engineer-in charge
A30: =A27+0.01 -> 1.06 | B30: SCREED CONCRETE OVER CINDER | C30: Sqm | D30: 87 | E30: 673 | F30: =E30*D30 -> 58551
B31: Providing & laying plain cement concrete 1:3:6 for a mimumum thickness of 40mm over prepared bed in toilets with 12mm down size aggregates including the cost of all materials, labour, compaction, levelling, at all levels, leads and lifts, curing, shuttering etc. complete as per instruction of Engineer-in charge
A33: =A30+0.01 -> 1.07 | B33: WASH BASIN COUNTER - GRANITE | C33: Rmt | D33: 13 | E33: 8659 | F33: =E33*D33 -> 112567
B34: Providing and fixing storage unit with 690mm wide 12 mm thk corian counter top of approved shade garnite to be fixed over on MS support & made of 18mm thk BWR Ply board. as per detailed drawing. Cost inclusive of 150mm high Backspalsh band above counter to mount powet / data sockets as per detail dwg . Make of Ply - Greenply, Archidply . Make of Laminate - Merino, Greenlam, Century .
A36: =A33+0.01 -> 1.08 | B36: VITRIFIED TILE FLOORING | C36: sqm | D36: 87 | E36: 2099 | F36: =E36*D36 -> 182613
B37: Providing and laying vitrified tile flooring with 3mm Spacers over Laticrete Tile Adhisive 4-6mm thk. Joints between tiling to be filled with approved Epoxy grout of approved shade as per manufacturers specifications. Rate to include cost for laying tiles to approved pattern, design as directed by Architect, including curing, acid wash, etc.
A39: =A36+0.01 -> 1.09 | B39: GROUTING ON EXISTING TOILET TILE | C39: sqm | D39: 297 | E39: 269 | F39: =E39*D39 -> 79893
B40: Providing and laying approved Epoxy grout of approved shade as per manufacturers specifications.
A42: =A36+0.01 -> 1.09 | B42: SAME AS ABOVE TILE CLADDING | C42: Sqm | D42: 205 | E42: 3567 | F42: =E42*D42 -> 731235
A44: =A36+0.01 -> 1.09 | B44: GRANITE LEDGE | C44: Rmt | D44: 22 | E44: 923 | F44: =E44*D44 -> 20306
B45: Providing and Fixing , granit top of the ledge to be finished with 18mm thk approved granite, edges chamfered. Complete as per detailed drawing and instructions of the Architect
A47: =A44+0.01 -> 1.1 | B47: GRANITE DOOR JAM | C47: Rmt | D47: 24 | E47: 1845 | F47: =E47*D47 -> 44280
B48: Providing and Fixing , granit top of the ledge to be finished with 18mm thk approved granite, edges chamfered. Complete as per detailed drawing and instructions of the Architect
A50: =A47+0.01 -> 1.11 | B50: GRANITE RAMP | C50: Sqm | E50: 6391 | F50: =E50*D50 -> 0
B51: Providing and Fixing , granit top of the Ramp to be finished with 18mm thk approved granite, edges chamfered. Complete as per detailed drawing and instructions of the Architect
A53: =A50+0.01 -> 1.12 | B53: Granite Skirting | C53: Rmt | D53: 80 | E53: 923 | F53: =E53*D53 -> 73840
B54: Providing and Fixing , 100mm ht granit top of the Skirting to be finished with 18mm thk approved granite, edges chamfered. Complete as per detailed drawing and instructions of the Architect
A56: =A47+0.01 -> 1.11 | B56: METAL GRID CEILING -600 x 600mm | C56: Rmt | D56: 117 | E56: 3071 | F56: =E56*D56 -> 359307
B57: Providing and Fixing Metal Grid False Ceiling tiles of 0.4mm thick GI sheets with 600mmx600mm size manufactured out of galvanised iron, and size of the tile can be customized as per the architect/designer requirement with a finish powder coated finish are formed in the grid to complete the job , the grid would be 15mm shilouted grid made of 0.4mm gi sheet ,and the grid would be hung to the true ceiling by using M6 Hook type anchor fastener , GI wire complete as per the Drawing and instructions of the Architect
A59: =A56+0.01 -> 1.12 | B59: MR GRID CEILING | C59: Sqm | D59: 23 | E59: 1615 | F59: =E59*D59 -> 37145
B60: Providing and fixing Suspended False Ceiling which includes Moisture Resistance Gypsum Plaster board 12mm thk., False Ceiling on 24 gauge G.I. frame work which includes Providing. & fixing G.I. perimeter channels 0.55 mm thk 20mmx30mm,web size 27mm along perimeter of ceiling, screw fixed to brick wall/partition with nylon sleeves & screws @ approx 2'0" c/c. Suspending G.I. intermediate channels size 45 mm,0.9 mm thk, flanges of size15mm each from the soffit 1220mm c/c with ceiling angle 25 x10mm x 0.55mm thk fixed to soffit G.I. cleat & steel expansion fasteners.
B61: Ceiling section of 0.55mm thk having web of 51.5mm & flanges 26 mm each lips 10.5 mm fixed to intermediate channel with connecting clips & perpendicular to int channel @ 457mm c/c.12.5 mm tapered edge Plaster board ( IS 2095-1982 ) screw fixed to ceiling section with 25mm dry wall screws @ 230 mm c/c. Boards to be joint & finished so as to have flush look including filling finishing edges with jointing compound paper tape/cloth gauze & 2 coats of primer suitable for plaster board. Rate to include M.S.framing around A/C ducts where ever necessary.
A63: =A59+0.01 -> 1.13 | B63: ='[6]BOQ-C&I'!B417 -> PELMET | C63: Rmt | D63: 66 | E63: 1435 | F63: =E63*D63 -> 94710
B64: ='[6]BOQ-C&I'!B418 -> Providing and fixing pelmets made of 18mm Pre laminated ply of size 150x150mm wide along windows and glazed area and with necessary wood support, and also to mount the Blinds and Pull Down screens. The edges on the glazing side has to finished with enamel paint / Edge banding . Vertical support Ply to be anchored to the structural beam. Fixing detail may vary as per site conditions. Rate to be inclusive of the same. Make of Ply- Archid ply, Green ply, Century
A67: =A56+0.01 -> 1.12 | B67: MIRROR PANELING | C67: Sqm | D67: 27 | E67: 6660 | F67: =E67*D67 -> 179820
B68: Providing & fabricating 6mm tk Mirror Glass panelling of approved make & shade on to the existing solid wall over 12mm thk Marine Ply backing and aluminium/GI frame work ,complete as per the detailed dwg or the instructions of the Architects.
B69: Consider Aluminium "U" channel of 5mm thk at the ht of 2400mm ht for horizontal & vertical groove
A71: =A67+0.01 -> 1.13 | B71: SOLID FLUSH DOOR
B72: Size : - 1000 x 2400mm | C72: Nos | D72: 5 | E72: 47500 | F72: =E72*D72 -> 237500
B73: Size : - 600 x 2400mm | C73: Nos | D73: 2 | E73: 47500 | F73: =E73*D73 -> 95000
B74: Aluminium Door Frame - Providing and fixing doors with aluminium door frame of size 100 X 25 mm with rebate, size with 32 mm thk fluh door finished in 1 mm thk laminate of approved shade .with hardwares.
A76: =A71+0.01 -> 1.14 | B76: Toilet Cubicals | C76: Mos | D76: 15 | E76: 42500 | F76: =E76*D76 -> 637500
A78: =A76+0.01 -> 1.15 | B78: Urinal Divider | C78: Nos | D78: 6 | E78: 6875 | F78: =E78*D78 -> 41250
A80: =A78+0.01 -> 1.16 | B80: LOCKER UNIT | C80: Nos | D80: 48 | E80: 3750 | F80: =E80*D80 -> 180000
B82: TOTAL | F82: =SUM(F3:F81) -> 3865958

Sheet Kitchen Equipment
A1: BOQ for Kitchen Equipmet
A3: Sl.No | B3: Description | C3: Reference Images | D3: Unit | E3: TOTAL | F3: Rate | G3: Amount
A4: 1 | B4: SS SINK COUNTER - Size (2100 x 1200) | D4: Nos | E4: 2 | F4: 56250 | G4: =F4*E4 -> 112500
A5: 2 | B5: SS STORAGE UNIT | D5: Sqm | E5: 13 | F5: 18750 | G5: =F5*E5 -> 243750
B6: SS STORAGE UNIT with Shuter | D6: Sqm | E6: 3 | F6: 31250 | G6: =F6*E6 -> 93750
A7: 3 | B7: Plate Rack | D7: Nos | E7: 0 | F7: 31250 | G7: =F7*E7 -> 0
B9: TOTAL | G9: =SUM(G4:G8) -> 450000

Sheet Summary  Electrical 
A1: Project: Indegene_3F
A2: Scope of Work : Electrical and ELV | E2: Area | F2: Date : 11.11.2025
A3: Purpose - Tender | E3: 0 | F3: Rev No : R0
A4: SUMMARY
A5: S.No | B5: Description | C5: Amount (Supply) | D5: Amount (Installation) | E5: Amount (Supply+Installation) | F5: Remarks
A7: A | B7: Electrical Works : internal
A8: 1 | B8: LT Switchgear : | C8: ='Internal Electrical Works '!G74 -> 153326 | D8: ='Internal Electrical Works '!H74 -> 9250 | E8: =C8+D8 -> 162576
A9: 2 | B9: MCB Distribution Boards : | C9: ='Internal Electrical Works '!G214 -> 501239 | D9: ='Internal Electrical Works '!H214 -> 29888 | E9: =C9+D9 -> 531127
A10: 3 | B10: Low Voltage Cables and End Termination : | C10: ='Internal Electrical Works '!G301 -> 709420 | D10: ='Internal Electrical Works '!H301 -> 56834 | E10: =C10+D10 -> 766254
A11: 4 | B11: Swicthes and Sockets : | C11: ='Internal Electrical Works '!G348 -> 1623704 | D11: ='Internal Electrical Works '!H348 -> 207997 | E11: =C11+D11 -> 1831701
A12: 5 | B12: Circuit Mains | C12: ='Internal Electrical Works '!G366 -> 4533550 | D12: ='Internal Electrical Works '!H366 -> 837350 | E12: =C12+D12 -> 5370900
A13: 6 | B13: Point Wiring | C13: ='Internal Electrical Works '!G378 -> 1387710 | D13: ='Internal Electrical Works '!H378 -> 541090 | E13: =C13+D13 -> 1928800
A14: 7 | B14: Cable Trays/Raceways | C14: ='Internal Electrical Works '!G439 -> 1577253 | D14: ='Internal Electrical Works '!H439 -> 304831 | E14: =C14+D14 -> 1882084
A15: 8 | B15: Earthing | C15: ='Internal Electrical Works '!G469 -> 226001 | D15: ='Internal Electrical Works '!H469 -> 52827 | E15: =C15+D15 -> 278828
A16: 9 | B16: Pipes (Electrical/IT/AV/CCTV/ACS) | C16: ='Internal Electrical Works '!G492 -> 149700 | D16: ='Internal Electrical Works '!H492 -> 93900 | E16: =C16+D16 -> 243600
A17: 10 | B17: Structural Works | C17: ='Internal Electrical Works '!G499 -> 10350 | D17: ='Internal Electrical Works '!H499 -> 5100 | E17: =C17+D17 -> 15450
A18: 11 | B18: Miscellaneous Works | C18: ='Internal Electrical Works '!G515 -> 53125 | D18: ='Internal Electrical Works '!H515 -> 230625 | E18: =C18+D18 -> 283750
C20: =SUM(C3:C18) -> 10925378 | D20: =SUM(D3:D18) -> 2369692 | E20: =SUM(E8:E19) -> 13295070
A22: B | B22: Light Fixtures | C22: =1200*3500 -> 4200000 | D22: 500000 | E22: =D22+C22 -> 4700000
A24: C | B24: UPS | C24: ='UPS-Indegene'!G12 -> 0 | D24: ='UPS-Indegene'!H12 -> 0 | E24: =C24+D24 -> 0
A26: D | B26: IT Networking | C26: =IT!G105 -> 2720115.7 | D26: =IT!H105 -> 210281.8 | E26: =C26+D26 -> 2930397.5
A27: E | B27: CCTV | C27: =CCTV!G32 -> 629072 | D27: =CCTV!H32 -> 112842 | E27: =C27+D27 -> 741914
A28: F | B28: Access Control System | C28: =ACS!G39 -> 166100 | D28: =ACS!H39 -> 44600 | E28: =C28+D28 -> 210700
A29: G | B29: LMS System | C29: ='LMS '!I13 -> 1064520 | D29: ='LMS '!J13 -> 51240 | E29: =C29+D29 -> 1115760
B32: Total Amount | E32: =SUM(E23:E31) -> 4998771.5
B33: GST
B34: Grand Total
B36: EXCLUSIONS:
B37: Software for ACS /Attendence management
B38: Fixed Deposit to Electricity board, Power Sanction and Approvals,Solar panels.
B39: Video conferencing / Display/ Projector - AV System related works
B40: Intrusion system
B41: Active Components & Servers, Switches, Rack for Access Control
B42: Novec/ Vesda system
B43: Isolation transformer for UPS
B44: Taxes shall be extra as applicable
B45: UPS - Existing UPS shall be utilised
... B47: IT / Networking Exclusion : Networking Active components , Software, Wi Fi devices, Server, Router, Active Switch, Firewall ,EPABX ,IT Equipment-. Printers, Fax, Photocopier,, Office Equipment, laptop, desktop, speaker phones etc

Sheet Internal Electrical Works 
A1: Project: Indegene_3F | I1: Date : 27.01.2026
A2: Electrical Works | I2: Rev No : R1
A4: Sl No | B4: ITEM DESCRIPTION | C4: UNIT | D4: Total QTY | E4: Rate | G4: Total Amount (Supply) | H4: Total Amount (Installation) | I4: Remarks
D5: Total | E5: Supply | F5: Installation
A7: 1 | B7: LT SWITCHGEAR
B9: Installation, testing and commissioning of Low voltage switchgear's, free standing, Cubical type, dead front, Frame and Doors:2mm, Internal Partations:1.6mm thick, Gland Plates:3mm Thick, powder coated (Paint Shade: RAL 7032/7035), indoor type with vermin proof hinged lockable doors for each compartment, bus bar interconnections for incoming and outgoing including feeders earthing and painting and as per specifications comprising of ACB,MCCB and MCB horizontal and vertical aluminum bus bar, earth bus bar as per SLD. All meters shall be digital with LED display, whereever mentioned and shall have RS 485 Modbus RTU half duplex communication interface for provision of BMS connectivity and wired accordingly. Provide required NO/NC potential free contacts wires and terminal blocks in the cable alley for BMS operation (Optional).The swtichboards are to be tested as per IS 8623 -1977 specifications. The busbars are of high conductivity Al. alloy E91E IS 5082 specification and cable entries will be from either top or bottom depending on location. LT Switchgear shall be as per technical specification and single line diagram
A11: 1.1 | B11: MDB -3F(S-1) | C11: Nos | D11: =1*0 -> 0 | E11: 312500 | F11: 62500 | G11: =IF($D11="","",IFERROR($D11*E11,"")) -> 0 | H11: =IF($D11="","",IFERROR($D11*F11,"")) -> 0
B12: MDB -3F (S-1) - Existing Panle modifications as per the Single line diagram and technical specifications.(Indoor -IP 42)
A14: 1.2 | B14: MDB -3F(S-2) | C14: Nos | D14: =1*0 -> 0 | E14: 250000 | F14: 22500 | G14: =IF($D14="","",IFERROR($D14*E14,"")) -> 0 | H14: =IF($D14="","",IFERROR($D14*F14,"")) -> 0
B15: MDB -3F (S-2) - Existing Panle modifications as per the Single line diagram and technical specifications.(Indoor -IP 42)
A17: 1.3 | B17: UPS I/P PANEL-1 | C17: Nos | D17: =1*0 -> 0 | E17: 62500 | F17: 18000 | G17: =IF($D17="","",IFERROR($D17*E17,"")) -> 0 | H17: =IF($D17="","",IFERROR($D17*F17,"")) -> 0
B18: UPS I/P PANEL-1 - Existing Panle modifications as per the Single line diagram and technical specifications.(Indoor -IP 42)
A20: 1.4 | B20: UPS I/P PANEL-2 | C20: Nos | D20: =1*0 -> 0 | E20: 62500 | F20: 18000 | G20: =IF($D20="","",IFERROR($D20*E20,"")) -> 0 | H20: =IF($D20="","",IFERROR($D20*F20,"")) -> 0
B21: UPS I/P PANEL-2 - Existing Panle modifications as per the Single line diagram and technical specifications.(Indoor -IP 42)
A23: 1.5 | B23: UPS O/P PANEL-1 | C23: Nos | D23: =1*0 -> 0 | E23: 31250 | F23: 18000 | G23: =IF($D23="","",IFERROR($D23*E23,"")) -> 0 | H23: =IF($D23="","",IFERROR($D23*F23,"")) -> 0
B24: UPS O/P PANEL -1 Existing Panle modifications as per the Single line diagram and technical specifications.(Indoor -IP 42)
A26: 1.6 | B26: UPS O/P PANEL-2 | C26: Nos | D26: =1*0 -> 0 | E26: 31250 | F26: 15000 | G26: =IF($D26="","",IFERROR($D26*E26,"")) -> 0 | H26: =IF($D26="","",IFERROR($D26*F26,"")) -> 0
B27: UPS O/P PANEL -2 Existing Panle modifications as per the Single line diagram and technical specifications.(Indoor -IP 42)
A29: 1.7 | B29: UPS O/P PANEL-3 | C29: Nos | D29: =1*0 -> 0 | E29: 31250 | F29: 15000 | G29: =IF($D29="","",IFERROR($D29*E29,"")) -> 0 | H29: =IF($D29="","",IFERROR($D29*F29,"")) -> 0
B30: UPS O/P PANEL -3 Existing Panle modifications as per the Single line diagram and technical specifications.(Indoor -IP 42)
A32: 1.7 | B32: UPS O/P PANEL-4 | C32: Nos | D32: =1*0 -> 0 | E32: 31250 | F32: 15000 | G32: =IF($D32="","",IFERROR($D32*E32,"")) -> 0 | H32: =IF($D32="","",IFERROR($D32*F32,"")) -> 0
B33: UPS O/P PANEL -4 Existing Panle modifications as per the Single line diagram and technical specifications.(Indoor -IP 42)
A35: 1.8 | B35: VRF AC Panel (Proposed) | C35: Nos | D35: =1*0 -> 0 | E35: 193750 | F35: 15000 | G35: =IF($D35="","",IFERROR($D35*E35,"")) -> 0 | H35: =IF($D35="","",IFERROR($D35*F35,"")) -> 0
B36: VRF AC Panel shall be as per Single line diagram and technical specifications.(Indoor -IP 42)
A38: 1.9 | B38: Kitchen (Proposed) | C38: Nos | D38: =1*0 -> 0 | E38: 156250 | F38: 15000 | G38: =IF($D38="","",IFERROR($D38*E38,"")) -> 0 | H38: =IF($D38="","",IFERROR($D38*F38,"")) -> 0
B39: Kitchen Panel shall be as per Single line diagram and technical specifications.(Indoor -IP 42)
A41: 1.1 | B41: Supply and installation of MCB ISOLATORS
A42: a | B42: 160A 4P MCCB in metallic enclosure -IP 42 (Without Release) | C42: Nos | D42: =4*0 -> 0 | E42: 27808 | F42: 5250 | G42: =IF($D42="","",IFERROR($D42*E42,"")) -> 0 | H42: =IF($D42="","",IFERROR($D42*F42,"")) -> 0
A43: b | B43: 80A 4P MCCB in metallic enclosure -IP 42 (Without Release) | C43: Nos | D43: =4*0 -> 0 | E43: 13780 | F43: 2250 | G43: =IF($D43="","",IFERROR($D43*E43,"")) -> 0 | H43: =IF($D43="","",IFERROR($D43*F43,"")) -> 0
A44: c | B44: 80A 4P MCB in metallic enclosure -IP 42 | C44: Nos | D44: 0 | E44: 11531 | F44: 1500 | G44: =IF($D44="","",IFERROR($D44*E44,"")) -> 0 | H44: =IF($D44="","",IFERROR($D44*F44,"")) -> 0
A45: d | B45: 80A 4P MCB in metallic enclosure -IP 65 | C45: Nos | D45: 0 | E45: 11531 | F45: 1500 | G45: =IF($D45="","",IFERROR($D45*E45,"")) -> 0 | H45: =IF($D45="","",IFERROR($D45*F45,"")) -> 0
A46: e | B46: 63A 4P MCB in metallic enclosure -IP 42 | C46: Nos | D46: 0 | E46: 6596 | F46: 1125 | G46: =IF($D46="","",IFERROR($D46*E46,"")) -> 0 | H46: =IF($D46="","",IFERROR($D46*F46,"")) -> 0
A47: f | B47: 63A 4P MCB in metallic enclosure -IP 65 (Suitable to terminate 16/25 sqmm Cables) | C47: Nos | D47: 6 | E47: 6596 | F47: 1125 | G47: =IF($D47="","",IFERROR($D47*E47,"")) -> 39576 | H47: =IF($D47="","",IFERROR($D47*F47,"")) -> 6750
A48: g | B48: 40A 4P MCB in metallic enclosure -IP 42 | C48: Nos | D48: 0 | E48: 6219 | F48: 750 | G48: =IF($D48="","",IFERROR($D48*E48,"")) -> 0 | H48: =IF($D48="","",IFERROR($D48*F48,"")) -> 0
A49: h | B49: 40A 4P MCB in metallic enclosure -IP 65 (Suitable to terminate 16/25 sqmm Cables) | C49: Nos | D49: 0 | E49: 6219 | F49: 750 | G49: =IF($D49="","",IFERROR($D49*E49,"")) -> 0 | H49: =IF($D49="","",IFERROR($D49*F49,"")) -> 0
A50: i | B50: 25A 4P MCB in metallic enclosure -IP 42 | C50: Nos | D50: 0 | E50: 4764 | F50: 750 | G50: =IF($D50="","",IFERROR($D50*E50,"")) -> 0 | H50: =IF($D50="","",IFERROR($D50*F50,"")) -> 0
A51: j | B51: 25A 4P MCB in metallic enclosure -IP 65 | C51: Nos | D51: 0 | E51: 4764 | F51: 750 | G51: =IF($D51="","",IFERROR($D51*E51,"")) -> 0 | H51: =IF($D51="","",IFERROR($D51*F51,"")) -> 0
A52: i1 | B52: 20A 4P MCB in metallic enclosure -IP 42 | C52: Nos | D52: 0 | E52: 4764 | F52: 750 | G52: =IF($D52="","",IFERROR($D52*E52,"")) -> 0 | H52: =IF($D52="","",IFERROR($D52*F52,"")) -> 0
A53: j2 | B53: 20A 4P MCB in metallic enclosure -IP 65 (Isolator Type) | C53: Nos | D53: =2*0 -> 0 | E53: 4764 | F53: 750 | G53: =IF($D53="","",IFERROR($D53*E53,"")) -> 0 | H53: =IF($D53="","",IFERROR($D53*F53,"")) -> 0
A54: k | B54: 63A DP MCB in metallic enclosure -IP 42 | C54: Nos | D54: =2*0 -> 0 | E54: 3544 | F54: 750 | G54: =IF($D54="","",IFERROR($D54*E54,"")) -> 0 | H54: =IF($D54="","",IFERROR($D54*F54,"")) -> 0
A55: l | B55: 63A DP MCB in metallic enclosure -IP 65 | C55: Nos | D55: 0 | E55: 3544 | F55: 750 | G55: =IF($D55="","",IFERROR($D55*E55,"")) -> 0 | H55: =IF($D55="","",IFERROR($D55*F55,"")) -> 0
A56: m | B56: 40A DP MCB in metallic enclosure -IP 42 | C56: Nos | D56: 0 | E56: 3544 | F56: 750 | G56: =IF($D56="","",IFERROR($D56*E56,"")) -> 0 | H56: =IF($D56="","",IFERROR($D56*F56,"")) -> 0
A57: n | B57: 40A DP MCB in metallic enclosure -IP 65 | C57: Nos | D57: 0 | E57: 3544 | F57: 750 | G57: =IF($D57="","",IFERROR($D57*E57,"")) -> 0 | H57: =IF($D57="","",IFERROR($D57*F57,"")) -> 0
A58: o | B58: 25A DP MCB in metallic enclosure -IP 42 | C58: Nos | D58: 0 | E58: 2473 | F58: 525 | G58: =IF($D58="","",IFERROR($D58*E58,"")) -> 0 | H58: =IF($D58="","",IFERROR($D58*F58,"")) -> 0
A59: p | B59: 25A DP MCB in metallic enclosure -IP 65 | C59: Nos | D59: 0 | E59: 2473 | F59: 525 | G59: =IF($D59="","",IFERROR($D59*E59,"")) -> 0 | H59: =IF($D59="","",IFERROR($D59*F59,"")) -> 0
A60: q | B60: 20A DP MCB in metallic enclosure -IP 42 | C60: Nos | D60: 0 | E60: 2473 | F60: 525 | G60: =IF($D60="","",IFERROR($D60*E60,"")) -> 0 | H60: =IF($D60="","",IFERROR($D60*F60,"")) -> 0
A61: r | B61: 20A DP MCB in metallic enclosure -IP 65 | C61: Nos | D61: 0 | E61: 2473 | F61: 525 | G61: =IF($D61="","",IFERROR($D61*E61,"")) -> 0 | H61: =IF($D61="","",IFERROR($D61*F61,"")) -> 0
A62: s | B62: 20A DP ELCB in metallic enclosure -IP 42 | C62: Nos | D62: 0 | E62: 5670 | F62: 750 | G62: =IF($D62="","",IFERROR($D62*E62,"")) -> 0 | H62: =IF($D62="","",IFERROR($D62*F62,"")) -> 0
A63: t | B63: 20A DP ELCB in metallic enclosure -IP 65 | C63: Nos | D63: 0 | E63: 5670 | F63: 750 | G63: =IF($D63="","",IFERROR($D63*E63,"")) -> 0 | H63: =IF($D63="","",IFERROR($D63*F63,"")) -> 0
A65: 1.8.1 | B65: PLUG IN TAPOFF BOX : 400A,25kA, 4P Microprocessor based MCCB with OC/SC/EF release with Dual Source Energy Meter along with required CT's and other related accessories in metallic enclosure - IP 42.Plugin Box to be fixed in the existing builder panel | C65: Nos | D65: =2*0 -> 0 | E65: 193750 | F65: 3750 | G65: =IF($D65="","",IFERROR($D65*E65,"")) -> 0 | H65: =IF($D65="","",IFERROR($D65*F65,"")) -> 0
A66: 1.8.2 | B66: PLUG IN TAPOFF BOX : 250,25kA, 4P Microprocessor based MCCB with OC/SC/EF release with Dual Source Energy Meter along with required CT's and other related accessories in metallic enclosure - IP 42.Plugin Box to be fixed in the existing builder panel | C66: Nos | D66: =2*0 -> 0 | E66: 168750 | F66: 3750 | G66: =IF($D66="","",IFERROR($D66*E66,"")) -> 0 | H66: =IF($D66="","",IFERROR($D66*F66,"")) -> 0
A67: 1.8.3 | B67: PLUG IN TAPOFF BOX : 160,25kA, 4P Microprocessor based MCCB with OC/SC/EF release with Dual Source Energy Meter along with required CT's and other related accessories in metallic enclosure - IP 42.Plugin Box to be fixed in the existing builder panel | C67: Nos | D67: =2*0 -> 0 | E67: 143750 | F67: 3750 | G67: =IF($D67="","",IFERROR($D67*E67,"")) -> 0 | H67: =IF($D67="","",IFERROR($D67*F67,"")) -> 0
A68: 1.8.4 | B68: ATS : 160,25kA, 4P Microprocessor based MCCB with OC/SC/EF release with Dual Source Energy Meter along with required CT's and other related accessories in metallic enclosure - IP 42. | C68: Nos | D68: =1*0 -> 0 | E68: 268750 | F68: 3750 | G68: =IF($D68="","",IFERROR($D68*E68,"")) -> 0 | H68: =IF($D68="","",IFERROR($D68*F68,"")) -> 0
A70: 1.9 | B70: STARTERS
A71: a | B71: Supply and Installation of 1.1 kW Similar to Motor KW of fan slelected by OEM of unit as per approved TDS VFD-DOL/STAR DELTA starter with contactor, MPCB, overload relay, ON-OFF push buttons, Auto/Manual, ON/OFF/Trip indicating lamps, NO/NC Contacts and potential free contacts with required accessories and provied universal sockets as shown in SLD, refere Single line diagram and technical specifications. | C71: Nos | D71: RO | E71: 29375 | F71: 1250 | G71: =IF($D71="","",IFERROR($D71*E71,"")) | H71: =IF($D71="","",IFERROR($D71*F71,""))
A72: b | B72: Supply and Installation of 3.0kW Similar to Motor KW of fan slelected by OEM of unit as per approved TDS DOL/STAR DELTA starter with contactor, MPCB, overload relay, ON-OFF push buttons, Auto/Manual, ON/OFF/Trip indicating lamps, NO/NC Contacts and potential free contacts with required accessories and provied universal sockets as shown in SLD, refere Single line diagram and technical specifications. | C72: Nos | D72: 2 | E72: 56875 | F72: 1250 | G72: =IF($D72="","",IFERROR($D72*E72,"")) -> 113750 | H72: =IF($D72="","",IFERROR($D72*F72,"")) -> 2500
B74: Total - Section-1 | G74: =SUM(G7:G73) -> 153326 | H74: =SUM(H7:H73) -> 9250
A76: 2 | B76: MCB Distribution boards (IP 45)
B77: Supply, installation of Metal door MCB DBs with CRCA sheet, powder coated, MS Powdercoated box on top / bottom & on sides. MCBs shall be rated for 10kA with current limiting feature. Bus bars shall be with tinned copper with seperate earth bus/neutral bus per phase along with yellow ferrules with circuit numer. Dummy ways to be covered with blank plates. All outgoings shall be labeled & laminated. As built drawing A3 OR A4(SLD) shall be affixed on inside face of DB door. Rates quoted shall include Phase separator and necessary mounting arrangement as requied along with the green wire for door earthing. Enclosure shall be suitable to accommodate incomer, phase isolators if any & outgoings. All Distribution boards shall be of double door type and shall be of Sheet steel enclosure confirming to IP42 grade.Note : Cost to exclude the powder coated DB frame around the DB. The same is captured in Item No: 9.0
A79: a | B79: 6 Way MCB Distribution Board - LDB | C79: Nos | D79: 0 | E79: 27026 | F79: 1500 | G79: =IF($D79="","",IFERROR($D79*E79,"")) -> 0 | H79: =IF($D79="","",IFERROR($D79*F79,"")) -> 0
B80: MCB DB comprising the following
B81: Type of DB - 8 way MCB DB (Double Door) - 7 SEGMENT
B82: 25A 4P MCB - 1 No. as incomer
B83: 25A DP RCCB, 30mA, 2 Module - 3 Nos. as Sub incomer per phase
B84: 6-10A SP MCB, 10 kA - 12 Nos. as outgoings : MCB are of 'C' Curve
B85: The rate shall include providing Cu. bus barsinterconnection, separate earth bus, separate neutral bus for each phases, Blank Plates and incluuding necessary connected civil works like chipping, rough plastering etc.
A87: b | B87: 8 Way MCB Distribution Board - LDB | C87: Nos | D87: 0 | E87: 27881 | F87: 1975 | G87: =IF($D87="","",IFERROR($D87*E87,"")) -> 0 | H87: =IF($D87="","",IFERROR($D87*F87,"")) -> 0
B88: MCB DB comprising the following
B89: Type of DB - 8 way MCB DB (Double Door) - 7 SEGMENT
B90: 40A TPN MCB - 1 No. as incomer
B91: 32A DP RCCB, 30mA, 2 Module - 3 Nos. as Sub incomer per phase
B92: 6-10A SP MCB, 10 kA - 18 Nos. as outgoings : MCB are of 'C' Curve
B93: The rate shall include providing Cu. bus barsinterconnection, separate earth bus, separate neutral bus for each phases, Blank Plates and incluuding necessary connected civil works like chipping, rough plastering etc.
A95: c | B95: 12 Way MCB Distribution Board - LDB | C95: Nos | D95: 3 | E95: 38106 | F95: 1975 | G95: =IF($D95="","",IFERROR($D95*E95,"")) -> 114318 | H95: =IF($D95="","",IFERROR($D95*F95,"")) -> 5925
B96: MCB DB comprising the following
B97: Type of DB - 12 way MCB DB (Double Door) - 7 SEGMENT
B98: 40A 4P MCB - 1 No. as incomer
B99: 40A DP RCCB, 30mA, 2 Module - 3 Nos. as Sub incomer per phase
B100: 6-10A SP MCB, 10 kA - 36 Nos. as outgoings : MCB are of 'C' Curve
B101: The rate shall include providing Cu. bus barsinterconnection, separate earth bus, separate neutral bus for each phases, Blank Plates and incluuding necessary connected civil works like chipping, rough plastering etc.
A103: d | B103: 8 Way MCB Distribution Board - PDB | C103: Nos | D103: 0 | E103: 32881 | F103: 1650 | G103: =IF($D103="","",IFERROR($D103*E103,"")) -> 0 | H103: =IF($D103="","",IFERROR($D103*F103,"")) -> 0
B104: MCB DB comprising the following
B105: Type of DB - 8 way MCB DB (Double Door) - 7 SEGMENT
B106: 40A 4P MCB - 1 No. as incomer
B107: 32A DP RCCB, 30mA, 2 Module - 3 Nos. as Sub incomer per phase
B108: 16A SP MCB, 10 kA - 18 Nos. as outgoings : MCB are of 'C' Curve
B109: The rate shall include providing Cu. bus barsinterconnection, separate earth bus, separate neutral bus for each phases, Blank Plates and incluuding necessary connected civil works like chipping, rough plastering etc.
A111: e | B111: 12 Way MCB Distribution Board - PDB | C111: Nos | D111: 0 | E111: 38106 | F111: 1800 | G111: =IF($D111="","",IFERROR($D111*E111,"")) -> 0 | H111: =IF($D111="","",IFERROR($D111*F111,"")) -> 0
B112: MCB DB comprising the following
B113: Type of DB - 12 way MCB DB (Double Door) - 7 SEGMENT
B114: 40A 4P MCB - 1 No. as incomer
B115: 32A DP RCCB, 30mA, 2 Module - 3 Nos. as Sub incomer per phase
B116: 16A SP MCB, 10 kA - 30 Nos. as outgoings : MCB are of 'C' Curve
B117: The rate shall include providing Cu. bus barsinterconnection, separate earth bus, separate neutral bus for each phases, Blank Plates and incluuding necessary connected civil works like chipping, rough plastering etc.
A119: f | B119: 12 Way MCB Distribution Board - PDB | C119: Nos | D119: 4 | E119: 33106 | F119: 2050 | G119: =IF($D119="","",IFERROR($D119*E119,"")) -> 132424 | H119: =IF($D119="","",IFERROR($D119*F119,"")) -> 8200
B120: MCB DB comprising the following
B121: Type of DB - 12 way MCB DB (Double Door) - 7 SEGMENT
B122: 63A TPN MCB - 1 No. as incomer
B123: 40A DP RCCB, 30mA, 2 Module - 3 Nos. as Sub incomer per phase
B124: 16A SP MCB, 10 kA - 36 Nos. as outgoings : MCB are of 'C' Curve
...

Sheet Electrical - Indegene
A1: Project: Indegene_3F | I1: Date : 27.01.2026
A2: Electrical Works | I2: Rev No : R1
A4: Sl No | B4: ITEM DESCRIPTION | C4: UNIT | D4: Total QTY | E4: Rate | G4: Total Amount (Supply) | H4: Total Amount (Installation) | I4: Remarks
D5: Total | E5: Supply | F5: Installation
A7: 1 | B7: LT SWITCHGEAR
B9: Installation, testing and commissioning of Low voltage switchgear's, free standing, Cubical type, dead front, Frame and Doors:2mm, Internal Partations:1.6mm thick, Gland Plates:3mm Thick, powder coated (Paint Shade: RAL 7032/7035), indoor type with vermin proof hinged lockable doors for each compartment, bus bar interconnections for incoming and outgoing including feeders earthing and painting and as per specifications comprising of ACB,MCCB and MCB horizontal and vertical aluminum bus bar, earth bus bar as per SLD. All meters shall be digital with LED display, whereever mentioned and shall have RS 485 Modbus RTU half duplex communication interface for provision of BMS connectivity and wired accordingly. Provide required NO/NC potential free contacts wires and terminal blocks in the cable alley for BMS operation (Optional).The swtichboards are to be tested as per IS 8623 -1977 specifications. The busbars are of high conductivity Al. alloy E91E IS 5082 specification and cable entries will be from either top or bottom depending on location. LT Switchgear shall be as per technical specification and single line diagram | I9: As Confirmed by client Existing panels are retained and reused.Please quote for Removing and Reinstallation.
A11: 1.1 | B11: MDB -3F(S-1) | C11: Nos | D11: =1 -> 1 | G11: =IF($D11="","",IFERROR($D11*E11,"")) -> 0 | H11: =IF($D11="","",IFERROR($D11*F11,"")) -> 0
B12: MDB -3F (S-1) - Existing Panle modifications as per the Single line diagram and technical specifications.(Indoor -IP 42)
A14: 1.3 | B14: UPS I/P PANEL-1 | C14: Nos | D14: =1 -> 1 | G14: =IF($D14="","",IFERROR($D14*E14,"")) -> 0 | H14: =IF($D14="","",IFERROR($D14*F14,"")) -> 0
B15: UPS I/P PANEL-1 - Existing Panle modifications as per the Single line diagram and technical specifications.(Indoor -IP 42)
A17: 1.4 | B17: UPS I/P PANEL-2 | C17: Nos | D17: =1 -> 1 | G17: =IF($D17="","",IFERROR($D17*E17,"")) -> 0 | H17: =IF($D17="","",IFERROR($D17*F17,"")) -> 0
B18: UPS I/P PANEL-2 - Existing Panle modifications as per the Single line diagram and technical specifications.(Indoor -IP 42)
A20: 1.5 | B20: UPS O/P PANEL-1 | C20: Nos | D20: =1 -> 1 | G20: =IF($D20="","",IFERROR($D20*E20,"")) -> 0 | H20: =IF($D20="","",IFERROR($D20*F20,"")) -> 0
B21: UPS O/P PANEL -1 Existing Panle modifications as per the Single line diagram and technical specifications.(Indoor -IP 42)
A23: 1.6 | B23: UPS O/P PANEL-2 | C23: Nos | D23: =1 -> 1 | G23: =IF($D23="","",IFERROR($D23*E23,"")) -> 0 | H23: =IF($D23="","",IFERROR($D23*F23,"")) -> 0
B24: UPS O/P PANEL -2 Existing Panle modifications as per the Single line diagram and technical specifications.(Indoor -IP 42)
A26: 1.7 | B26: UPS O/P PANEL-3 | C26: Nos | D26: =1 -> 1 | G26: =IF($D26="","",IFERROR($D26*E26,"")) -> 0 | H26: =IF($D26="","",IFERROR($D26*F26,"")) -> 0
B27: UPS O/P PANEL -3 Existing Panle modifications as per the Single line diagram and technical specifications.(Indoor -IP 42)
A29: 1.7 | B29: UPS O/P PANEL-4 | C29: Nos | D29: =1 -> 1 | G29: =IF($D29="","",IFERROR($D29*E29,"")) -> 0 | H29: =IF($D29="","",IFERROR($D29*F29,"")) -> 0
B30: UPS O/P PANEL -3 Existing Panle modifications as per the Single line diagram and technical specifications.(Indoor -IP 42)
A32: 1.8 | B32: VRF AC Panel (Proposed) | C32: Nos | D32: =1 -> 1 | G32: =IF($D32="","",IFERROR($D32*E32,"")) -> 0 | H32: =IF($D32="","",IFERROR($D32*F32,"")) -> 0
B33: VRF AC Panel shall be as per Single line diagram and technical specifications.(Indoor -IP 42)
A35: 1.9 | B35: Kitchen (Proposed) | C35: Nos | D35: =1 -> 1 | G35: =IF($D35="","",IFERROR($D35*E35,"")) -> 0 | H35: =IF($D35="","",IFERROR($D35*F35,"")) -> 0
B36: Kitchen Panel shall be as per Single line diagram and technical specifications.(Indoor -IP 42)
A38: 1.1 | B38: Supply and installation of MCB ISOLATORS
A39: a | B39: 160A 4P MCCB in metallic enclosure -IP 42 (Without Release) | C39: Nos | D39: 4 | G39: =IF($D39="","",IFERROR($D39*E39,"")) -> 0 | H39: =IF($D39="","",IFERROR($D39*F39,"")) -> 0 | I39: 80+80 KVA UPS , 2 Nos (I/O)
A40: b | B40: 80A 4P MCCB in metallic enclosure -IP 42 (Without Release) | C40: Nos | D40: 4 | G40: =IF($D40="","",IFERROR($D40*E40,"")) -> 0 | H40: =IF($D40="","",IFERROR($D40*F40,"")) -> 0 | I40: 40+40 KVA UPS , 2 Nos (I/O)
A41: c | B41: 80A 4P MCB in metallic enclosure -IP 42 | C41: Nos | D41: 0 | G41: =IF($D41="","",IFERROR($D41*E41,"")) -> 0 | H41: =IF($D41="","",IFERROR($D41*F41,"")) -> 0
A42: d | B42: 80A 4P MCB in metallic enclosure -IP 65 | C42: Nos | D42: 0 | G42: =IF($D42="","",IFERROR($D42*E42,"")) -> 0 | H42: =IF($D42="","",IFERROR($D42*F42,"")) -> 0
A43: e | B43: 63A 4P MCB in metallic enclosure -IP 42 | C43: Nos | D43: 0 | G43: =IF($D43="","",IFERROR($D43*E43,"")) -> 0 | H43: =IF($D43="","",IFERROR($D43*F43,"")) -> 0
A44: f | B44: 63A 4P MCB in metallic enclosure -IP 65 (Suitable to terminate 16/25 sqmm Cables) | C44: Nos | D44: =4*0 -> 0 | G44: =IF($D44="","",IFERROR($D44*E44,"")) -> 0 | H44: =IF($D44="","",IFERROR($D44*F44,"")) -> 0
A45: g | B45: 40A 4P MCB in metallic enclosure -IP 42 | C45: Nos | D45: 0 | G45: =IF($D45="","",IFERROR($D45*E45,"")) -> 0 | H45: =IF($D45="","",IFERROR($D45*F45,"")) -> 0
A46: h | B46: 40A 4P MCB in metallic enclosure -IP 65 (Suitable to terminate 16/25 sqmm Cables) | C46: Nos | D46: =10*0 -> 0 | G46: =IF($D46="","",IFERROR($D46*E46,"")) -> 0 | H46: =IF($D46="","",IFERROR($D46*F46,"")) -> 0 | I46: DX ODU&VRF ODU
A47: i | B47: 25A 4P MCB in metallic enclosure -IP 42 | C47: Nos | D47: 0 | G47: =IF($D47="","",IFERROR($D47*E47,"")) -> 0 | H47: =IF($D47="","",IFERROR($D47*F47,"")) -> 0
A48: j | B48: 25A 4P MCB in metallic enclosure -IP 65 | C48: Nos | D48: 0 | G48: =IF($D48="","",IFERROR($D48*E48,"")) -> 0 | H48: =IF($D48="","",IFERROR($D48*F48,"")) -> 0
A49: i1 | B49: 20A 4P MCB in metallic enclosure -IP 42 | C49: Nos | D49: 0 | G49: =IF($D49="","",IFERROR($D49*E49,"")) -> 0 | H49: =IF($D49="","",IFERROR($D49*F49,"")) -> 0
A50: j2 | B50: 20A 4P MCB in metallic enclosure -IP 65 (Isolator Type) | C50: Nos | D50: 0 | G50: =IF($D50="","",IFERROR($D50*E50,"")) -> 0 | H50: =IF($D50="","",IFERROR($D50*F50,"")) -> 0
A51: k | B51: 63A DP MCB in metallic enclosure -IP 42 | C51: Nos | D51: 2 | G51: =IF($D51="","",IFERROR($D51*E51,"")) -> 0 | H51: =IF($D51="","",IFERROR($D51*F51,"")) -> 0 | I51: Inverter
A52: l | B52: 63A DP MCB in metallic enclosure -IP 65 | C52: Nos | D52: 0 | G52: =IF($D52="","",IFERROR($D52*E52,"")) -> 0 | H52: =IF($D52="","",IFERROR($D52*F52,"")) -> 0
A53: m | B53: 40A DP MCB in metallic enclosure -IP 42 | C53: Nos | D53: 0 | G53: =IF($D53="","",IFERROR($D53*E53,"")) -> 0 | H53: =IF($D53="","",IFERROR($D53*F53,"")) -> 0
A54: n | B54: 40A DP MCB in metallic enclosure -IP 65 | C54: Nos | D54: 0 | G54: =IF($D54="","",IFERROR($D54*E54,"")) -> 0 | H54: =IF($D54="","",IFERROR($D54*F54,"")) -> 0
A55: o | B55: 25A DP MCB in metallic enclosure -IP 42 | C55: Nos | D55: 0 | G55: =IF($D55="","",IFERROR($D55*E55,"")) -> 0 | H55: =IF($D55="","",IFERROR($D55*F55,"")) -> 0
A56: p | B56: 25A DP MCB in metallic enclosure -IP 65 | C56: Nos | D56: 0 | G56: =IF($D56="","",IFERROR($D56*E56,"")) -> 0 | H56: =IF($D56="","",IFERROR($D56*F56,"")) -> 0
A57: q | B57: 20A DP MCB in metallic enclosure -IP 42 | C57: Nos | D57: =2*0 -> 0 | G57: =IF($D57="","",IFERROR($D57*E57,"")) -> 0 | H57: =IF($D57="","",IFERROR($D57*F57,"")) -> 0 | I57: For 3TR DX Unit islolation Purpose
A58: r | B58: 20A DP MCB in metallic enclosure -IP 65 | C58: Nos | D58: =6*0 -> 0 | G58: =IF($D58="","",IFERROR($D58*E58,"")) -> 0 | H58: =IF($D58="","",IFERROR($D58*F58,"")) -> 0 | I58: DX ODU,F&E Units
A59: s | B59: 20A DP ELCB in metallic enclosure -IP 42 | C59: Nos | D59: 0 | G59: =IF($D59="","",IFERROR($D59*E59,"")) -> 0 | H59: =IF($D59="","",IFERROR($D59*F59,"")) -> 0
A60: t | B60: 20A DP ELCB in metallic enclosure -IP 65 | C60: Nos | D60: 0 | G60: =IF($D60="","",IFERROR($D60*E60,"")) -> 0 | H60: =IF($D60="","",IFERROR($D60*F60,"")) -> 0
A62: 1.8.1 | B62: PLUG IN TAPOFF BOX : 400A,25kA, 4P Microprocessor based MCCB with OC/SC/EF release with Dual Source Energy Meter along with required CT's and other related accessories in metallic enclosure - IP 42.Plugin Box to be fixed in the existing builder panel | C62: Nos | D62: 2 | G62: =IF($D62="","",IFERROR($D62*E62,"")) -> 0 | H62: =IF($D62="","",IFERROR($D62*F62,"")) -> 0 | I62: Builder to Confirm
A63: 1.8.2 | B63: PLUG IN TAPOFF BOX : 250,25kA, 4P Microprocessor based MCCB with OC/SC/EF release with Dual Source Energy Meter along with required CT's and other related accessories in metallic enclosure - IP 42.Plugin Box to be fixed in the existing builder panel | C63: Nos | D63: 2 | G63: =IF($D63="","",IFERROR($D63*E63,"")) -> 0 | H63: =IF($D63="","",IFERROR($D63*F63,"")) -> 0 | I63: Builder to Confirm
A64: 1.8.3 | B64: PLUG IN TAPOFF BOX : 160,25kA, 4P Microprocessor based MCCB with OC/SC/EF release with Dual Source Energy Meter along with required CT's and other related accessories in metallic enclosure - IP 42.Plugin Box to be fixed in the existing builder panel | C64: Nos | D64: 2 | G64: =IF($D64="","",IFERROR($D64*E64,"")) -> 0 | H64: =IF($D64="","",IFERROR($D64*F64,"")) -> 0 | I64: Builder to Confirm
A65: 1.8.4 | B65: ATS : 160,25kA, 4P Microprocessor based MCCB with OC/SC/EF release with Dual Source Energy Meter along with required CT's and other related accessories in metallic enclosure - IP 42. | C65: Nos | D65: 1 | G65: =IF($D65="","",IFERROR($D65*E65,"")) -> 0 | H65: =IF($D65="","",IFERROR($D65*F65,"")) -> 0 | I65: Builder to Confirm
A67: 1.9 | B67: STARTERS
A68: a | B68: Supply and Installation of 1.1 kW Similar to Motor KW of fan slelected by OEM of unit as per approved TDS VFD-DOL/STAR DELTA starter with contactor, MPCB, overload relay, ON-OFF push buttons, Auto/Manual, ON/OFF/Trip indicating lamps, NO/NC Contacts and potential free contacts with required accessories and provied universal sockets as shown in SLD, refere Single line diagram and technical specifications. | C68: Nos | D68: RO | G68: =IF($D68="","",IFERROR($D68*E68,"")) | H68: =IF($D68="","",IFERROR($D68*F68,""))
A69: b | B69: Supply and Installation of 3.0kW Similar to Motor KW of fan slelected by OEM of unit as per approved TDS DOL/STAR DELTA starter with contactor, MPCB, overload relay, ON-OFF push buttons, Auto/Manual, ON/OFF/Trip indicating lamps, NO/NC Contacts and potential free contacts with required accessories and provied universal sockets as shown in SLD, refere Single line diagram and technical specifications. | C69: Nos | D69: =2*0 -> 0 | G69: =IF($D69="","",IFERROR($D69*E69,"")) -> 0 | H69: =IF($D69="","",IFERROR($D69*F69,"")) -> 0 | I69: Toilet Exhasut
B71: Total - Section-1 | G71: =SUM(G7:G70) -> 0 | H71: =SUM(H7:H70) -> 0
A73: 3 | B73: LOW VOLTAGE CABLES AND END TERMINATION
A75: 3.1 | B75: Low voltage Aluminium conductor cables
B76: Supply and laying of 1100 V grade, XLPE insulated,extruded PVC Inner Sheathed and extruded FRLS-PVC Outer sheatehed , aluminium conductor, Armoured power cable as per specifications. The cable shall be laid in cable trays as required. The cable shall be clamped at regular intervals to the suppoprts in trench or to cable trays or brick wall using MS clamps and fasteners. Rate shall exclude the cost of cable trays and termination in this item. The rate shall include cost for Cable identification labels at both ends clearly mentioning the cable specs & also at appropriate intervals along the cable route should be provided. The labels shall be engraved / anodized aluminium with white letters on black background. | I76: Qty varies as per Site Condition
B77: NOTE: Cables will not be procured based on BOQ only. True measurements will be taken by Contractor before ordering, based on Drawings.
A79: a | B79: 3.5CX 150Sqmm Alu.arm Cable | C79: Rmt | D79: 50 | G79: =IF($D79="","",IFERROR($D79*E79,"")) -> 0 | H79: =IF($D79="","",IFERROR($D79*F79,"")) -> 0
A80: b | B80: 3.5CX 120Sqmm Alu.arm Cable | C80: Rmt | D80: 450 | G80: =IF($D80="","",IFERROR($D80*E80,"")) -> 0 | H80: =IF($D80="","",IFERROR($D80*F80,"")) -> 0 | I80: 80KVA Input
A81: c | B81: 3.5CX 95Sqmm Alu.arm Cable | C81: Rmt | D81: 150 | G81: =IF($D81="","",IFERROR($D81*E81,"")) -> 0 | H81: =IF($D81="","",IFERROR($D81*F81,"")) -> 0
A82: d | B82: 3.5CX 70Sqmm Alu.arm Cable | C82: Rmt | D82: 0 | G82: =IF($D82="","",IFERROR($D82*E82,"")) -> 0 | H82: =IF($D82="","",IFERROR($D82*F82,"")) -> 0
A83: e | B83: 3.5CX 50Sqmm Alu.arm Cable | C83: Rmt | D83: 450 | G83: =IF($D83="","",IFERROR($D83*E83,"")) -> 0 | H83: =IF($D83="","",IFERROR($D83*F83,"")) -> 0 | I83: Kitchen Panel,40kVA
A84: f | B84: 3.5CX 35Sqmm Alu.arm Cable | C84: Rmt | D84: 100 | G84: =IF($D84="","",IFERROR($D84*E84,"")) -> 0 | H84: =IF($D84="","",IFERROR($D84*F84,"")) -> 0 | I84: VRF AC Panel
A85: g | B85: 4CX 25Sqmm Alu.arm Cable | C85: Rmt | D85: 0 | G85: =IF($D85="","",IFERROR($D85*E85,"")) -> 0 | H85: =IF($D85="","",IFERROR($D85*F85,"")) -> 0
A86: h | B86: 4CX 16Sqmm Alu.arm Cable | C86: Rmt | D86: =240+130+130+130+130+70+70+70+46+200 -> 1216 | G86: =IF($D86="","",IFERROR($D86*E86,"")) -> 0 | H86: =IF($D86="","",IFERROR($D86*F86,"")) -> 0 | I86: LDB,PDB,DX unist Input
A87: i | B87: 4CX 10Sqmm Alu.arm Cable | C87: Rmt | D87: 0 | G87: =IF($D87="","",IFERROR($D87*E87,"")) -> 0 | H87: =IF($D87="","",IFERROR($D87*F87,"")) -> 0
A88: j | B88: 3.5CX 185Sqmm Alu.arm Cable | C88: Rmt | D88: 350 | G88: =IF($D88="","",IFERROR($D88*E88,"")) -> 0 | H88: =IF($D88="","",IFERROR($D88*F88,"")) -> 0 | I88: Incommer, AC panel
A89: j | B89: 3.5CX 240Sqmm Alu.arm Cable | C89: Rmt | D89: 0 | G89: =IF($D89="","",IFERROR($D89*E89,"")) -> 0 | H89: =IF($D89="","",IFERROR($D89*F89,"")) -> 0
A91: 3.2 | B91: Low Voltage Copper Conductor Cables
B92: Supply and laying of 1100 V grade, XLPE insulated,extruded PVC Inner Sheathed and extruded FRLS-PVC Outer sheatehed copper conductor, Armoured/Un armoured power cable as per specifications. The cable shall be laid in indoor trenches / cable trays as required. The cable shall be clamped at regular intervals to the suppoprts in trench or to cable trays or brick wall using MS clamps and fasteners. Rate shall exclude the cost of cable trays and termination in this item.
B93: Armoured Copper Cables :
A95: a | B95: 4Cx 25sqmm Cu Arm Cable | C95: Rmt | D95: 0 | G95: =IF($D95="","",IFERROR($D95*E95,"")) -> 0 | H95: =IF($D95="","",IFERROR($D95*F95,"")) -> 0
A96: b | B96: 4Cx 16sqmm Cu Arm Cable | C96: Rmt | D96: =46+110+25+25+120+120 -> 446 | G96: =IF($D96="","",IFERROR($D96*E96,"")) -> 0 | H96: =IF($D96="","",IFERROR($D96*F96,"")) -> 0
A97: c | B97: 4Cx 10sqmm Cu Arm Cable | C97: Rmt | D97: =20+20+30+(5*7) -> 105 | G97: =IF($D97="","",IFERROR($D97*E97,"")) -> 0 | H97: =IF($D97="","",IFERROR($D97*F97,"")) -> 0
A98: d | B98: 4Cx 6sqmm Cu Arm Cable | C98: Rmt | D98: =150*0 -> 0 | G98: =IF($D98="","",IFERROR($D98*E98,"")) -> 0 | H98: =IF($D98="","",IFERROR($D98*F98,"")) -> 0
A99: e | B99: 4Cx 4sqmm Cu Arm Cable | C99: Rmt | D99: =30+(2*7) -> 44 | G99: =IF($D99="","",IFERROR($D99*E99,"")) -> 0 | H99: =IF($D99="","",IFERROR($D99*F99,"")) -> 0
A100: f | B100: 3Cx 6sqmm Cu Arm. Cable | C100: Rmt | D100: =120+25 -> 145 | G100: =IF($D100="","",IFERROR($D100*E100,"")) -> 0 | H100: =IF($D100="","",IFERROR($D100*F100,"")) -> 0
A101: g | B101: 3Cx 4sqmm Cu Arm. Cable | C101: Rmt | D101: =(70+70+70)*0 -> 0 | G101: =IF($D101="","",IFERROR($D101*E101,"")) -> 0 | H101: =IF($D101="","",IFERROR($D101*F101,"")) -> 0
G102: =IF($D102="","",IFERROR($D102*E102,"")) | H102: =IF($D102="","",IFERROR($D102*F102,""))
A103: 3.3 | B103: Copper Flexible Cables :
A105: a | B105: 1Cx95sqmm Cu Flexible Cable | C105: Rmt | D105: 300 | G105: =IF($D105="","",IFERROR($D105*E105,"")) -> 0 | H105: =IF($D105="","",IFERROR($D105*F105,"")) -> 0 | I105: Isolator to isolation TRf an Iso Trf to O/P isoltor
A106: b | B106: 1Cx70sqmm Cu Flexible Cable | C106: Rmt | D106: 0 | G106: =IF($D106="","",IFERROR($D106*E106,"")) -> 0 | H106: =IF($D106="","",IFERROR($D106*F106,"")) -> 0
A107: c | B107: 1Cx50sqmm Cu Flexible Cable | C107: Rmt | D107: 0 | G107: =IF($D107="","",IFERROR($D107*E107,"")) -> 0 | H107: =IF($D107="","",IFERROR($D107*F107,"")) -> 0
A108: d | B108: 1Cx35sqmm Cu Flexible Cable | C108: Rmt | D108: 180 | G108: =IF($D108="","",IFERROR($D108*E108,"")) -> 0 | H108: =IF($D108="","",IFERROR($D108*F108,"")) -> 0
A109: e | B109: 1Cx25sqmm Cu Flexible Cable | C109: Rmt | D109: 0 | G109: =IF($D109="","",IFERROR($D109*E109,"")) -> 0 | H109: =IF($D109="","",IFERROR($D109*F109,"")) -> 0
A110: f | B110: 1Cx16sqmm Cu Flexible Cable | C110: Rmt | D110: 0 | G110: =IF($D110="","",IFERROR($D110*E110,"")) -> 0 | H110: =IF($D110="","",IFERROR($D110*F110,"")) -> 0 | I110: Isolator to isolation TRf an Iso Trf to O/P isoltor
A111: g | B111: 1Cx10sqmm Cu Flexible Cable | C111: Rmt | D111: 75 | G111: =IF($D111="","",IFERROR($D111*E111,"")) -> 0 | H111: =IF($D111="","",IFERROR($D111*F111,"")) -> 0
A112: h | B112: 1Cx6sqmm Cu Flexible Cable | C112: Rmt | D112: 0 | G112: =IF($D112="","",IFERROR($D112*E112,"")) -> 0 | H112: =IF($D112="","",IFERROR($D112*F112,"")) -> 0
A113: i | B113: 4Cx6sqmm Cu Flexible Cable | C113: Rmt | D113: 0 | G113: =IF($D113="","",IFERROR($D113*E113,"")) -> 0 | H113: =IF($D113="","",IFERROR($D113*F113,"")) -> 0
A114: j | B114: 4Cx10sqmm Cu Flexible Cable | C114: Rmt | D114: 0 | G114: =IF($D114="","",IFERROR($D114*E114,"")) -> 0 | H114: =IF($D114="","",IFERROR($D114*F114,"")) -> 0
A115: k | B115: 3Cx6sqmm Cu Flexible Cable | C115: Rmt | D115: 0 | G115: =IF($D115="","",IFERROR($D115*E115,"")) -> 0 | H115: =IF($D115="","",IFERROR($D115*F115,"")) -> 0
A117: 3.4 | B117: LOW VOLTAGE CABLE END TERMINATION:
B118: Supply and providing LV cable end termination for below listed cable with copper lugs, brass cable glands, tapping, crimping, etc. complete. Single Compression Glands : Cable Size Below 150 Sqmm Double Compression Glands : Cable size above 185sqmm and Single core cables 400 sqmm and above The Quoted rate is inclusive of Gland earthing using copper shim and earth wire and also the cable tag near the cable termination showing the size of the cable and the location of from and TO
A119: a | B119: 3.5CX 150Sqmm Alu.arm Cable | C119: Nos | D119: 2 | G119: =IF($D119="","",IFERROR($D119*E119,"")) -> 0 | H119: =IF($D119="","",IFERROR($D119*F119,"")) -> 0
A120: a | B120: 3.5CX 120Sqmm Alu.arm Cable | C120: Nos | D120: 16 | G120: =IF($D120="","",IFERROR($D120*E120,"")) -> 0 | H120: =IF($D120="","",IFERROR($D120*F120,"")) -> 0
A121: b | B121: 3.5CX 95Sqmm Alu.arm Cable | C121: Nos | D121: 4 | G121: =IF($D121="","",IFERROR($D121*E121,"")) -> 0 | H121: =IF($D121="","",IFERROR($D121*F121,"")) -> 0
A122: c | B122: 3.5CX 70Sqmm Alu.arm Cable | C122: Nos | D122: 0 | G122: =IF($D122="","",IFERROR($D122*E122,"")) -> 0 | H122: =IF($D122="","",IFERROR($D122*F122,"")) -> 0
A123: d | B123: 3.5CX 50Sqmm Alu.arm Cable | C123: Nos | D123: 4 | G123: =IF($D123="","",IFERROR($D123*E123,"")) -> 0 | H123: =IF($D123="","",IFERROR($D123*F123,"")) -> 0
...

Sheet UPS-Indegene
A1: Project: Indegene_3F | I1: Date : 11.11.2025
A2: Scope of Work : Electrical | I2: Rev No : R0
A3: Purpose - UPS TENDER
A4: Sl No | B4: ITEM DESCRIPTION | C4: UNIT | D4: QTY | E4: Rate | G4: Amount | I4: Remarks
E5: Supply | F5: Installation | G5: Supply | H5: Installation
A7: 1 | B7: Installation , testing and ReCommissioning of EXISTING 80 kVA UPS(Conventional) , 3Ø IN / 3Ø OUT ALONG WITH EXTERNAL ISOLATION TRANSFORMER ,Batteries ,Battery rack, connecting cables from UPS & batteries etc. This Cost Inclusive of Cabling, Breaker etc., | C7: Nos | D7: 1 | G7: =IF($D7="","",IFERROR($D7*E7,"")) -> 0 | H7: =IF($D7="","",IFERROR($D7*F7,"")) -> 0
A8: 2 | B8: Installation , testing and Re Commissioning of EXISTING 40 kVA UPS(Conventional) , 3Ø IN / 3Ø OUT ALONG WITH EXTERNAL ISOLATION TRANSFORMER ,Batteries ,Battery rack, connecting cables from UPS & batteries etc. This Cost Inclusive of Cabling, Breaker etc., | C8: Nos | D8: 1 | G8: =IF($D8="","",IFERROR($D8*E8,"")) -> 0 | H8: =IF($D8="","",IFERROR($D8*F8,"")) -> 0
A9: 3 | B9: Installation , testing and Re Commissioning of EXISTING 10 kVA UPS(Conventional) , 3Ø IN / 1Ø OUT ALONG with Batteries ,Battery rack, connecting cables from UPS & batteries etc. | C9: Nos | D9: 1 | G9: =IF($D9="","",IFERROR($D9*E9,"")) -> 0 | H9: =IF($D9="","",IFERROR($D9*F9,"")) -> 0
A10: 4 | B10: Installation , testing and Re Commissioning of EXISTING 5 / 3 kVA UPS(Conventional) , 1Ø IN / 1Ø OUT ALONG with Batteries ,Battery rack, connecting cables from UPS & batteries etc. This Cost Inclusive of Cabling, Breaker etc., | C10: Nos | D10: 1 | G10: =IF($D10="","",IFERROR($D10*E10,"")) -> 0 | H10: =IF($D10="","",IFERROR($D10*F10,"")) -> 0
B12: Total | G12: =SUM(G7:G11) -> 0 | H12: =SUM(H7:H11) -> 0 | I12: =G12+H12 -> 0
B13: GST
B14: GRAND TOTAL

Sheet IT
A1: ESTIMATION FOR NETWORK
A2: Project: Indegene_3F | H2: Date: | I2: 11.11.2025
A3: Location: | H3: Revision | I3: R0
A4: Project no: | H4: Document No:
A6: S.no | B6: Description | C6: Unit | D6: 3F Qty | E6: Rate | G6: Amount | I6: Remarks
E7: Supply | F7: Installation | G7: Supply | H7: Installation
A8: 1 | B8: DATA
A9: 1.1 | B9: 4-pair, Cat 6 UTP Cable, roll of 305m, Grey | C9: Box | D9: 48 | E9: 16800 | F9: 600 | G9: =IF($E9="","",IFERROR($E9*D9,"")) -> 806400 | H9: =IF($F9="","",IFERROR($F9*D9,"")) -> 28800
A10: 1.2 | B10: Cat 6 UTP Information Outlet for Workstation end | C10: Nos | D10: 210 | E10: 420 | F10: 60 | G10: =IF($E10="","",IFERROR($E10*D10,"")) -> 88200 | H10: =IF($F10="","",IFERROR($F10*D10,"")) -> 12600
A11: 1.3 | B11: Cat6 RJ45-RJ45 UTP Patch Cords, color matched, Yellow - Field end, 7 ft | C11: Nos | D11: =D10:D10 -> 210 | E11: 240 | F11: 12 | G11: =IF($E11="","",IFERROR($E11*D11,"")) -> 50400 | H11: =IF($F11="","",IFERROR($F11*D11,"")) -> 2520
A12: 1.4 | B12: Single Face Plates (80%) | C12: Nos | D12: =D10*0.8 -> 168 | E12: 90 | F12: 24 | G12: =IF($E12="","",IFERROR($E12*D12,"")) -> 15120 | H12: =IF($F12="","",IFERROR($F12*D12,"")) -> 4032
A13: 1.5 | B13: Dual Face Plates (20%) | C13: Nos | D13: =D10*0.1 -> 21 | E13: 96 | F13: 24 | G13: =IF($E13="","",IFERROR($E13*D13,"")) -> 2016 | H13: =IF($F13="","",IFERROR($F13*D13,"")) -> 504
A14: 1.6 | B14: Quad Face Plates | C14: Nos | D14: 0 | E14: 102 | F14: 24 | G14: =IF($E14="","",IFERROR($E14*D14,"")) -> 0 | H14: =IF($F14="","",IFERROR($F14*D14,"")) -> 0
A15: 1.7 | B15: Blank Inserts | C15: Nos | D15: 0 | E15: 18 | F15: 6 | G15: =IF($E15="","",IFERROR($E15*D15,"")) -> 0 | H15: =IF($F15="","",IFERROR($F15*D15,"")) -> 0
A16: 1.8 | B16: Supply and fixing of Metal box suitable information outlet , flush/surface type in position . The rate shall exclude the cost of faceplate and Information Outlet. | C16: Nos | D16: =D10*5% -> 10.5 | E16: 42 | F16: 12 | G16: =IF($E16="","",IFERROR($E16*D16,"")) -> 441 | H16: =IF($F16="","",IFERROR($F16*D16,"")) -> 126
A17: 1.9 | B17: 4-pair, Cat 6 UTP FRLS Cable | C17: Mtrs | D17: 50 | E17: 38 | F17: 14 | G17: =IF($E17="","",IFERROR($E17*D17,"")) -> 1900 | H17: =IF($F17="","",IFERROR($F17*D17,"")) -> 700
A19: =A8+1 -> 2 | B19: HUB ROOM SIDE - DATA
A20: 2.1 | B20: Cat 6 24 Port Angled Discrete Jack panel - fully loaded (1U).The rate shall include the cost of Patch Panel, Information Outlets with all the required supporting accessories. | C20: Nos | D20: 11 | E20: 14400 | F20: 600 | G20: =IF($E20="","",IFERROR($E20*D20,"")) -> 158400 | H20: =IF($F20="","",IFERROR($F20*D20,"")) -> 6600
A21: 2.2 | B21: Cat 6 UTP 10ft patch cords-Jack Panel side - 20% | C21: Nos | D21: =(D20*20)*0.2 -> 44 | E21: 270 | F21: 12 | G21: =IF($E21="","",IFERROR($E21*D21,"")) -> 11880 | H21: =IF($F21="","",IFERROR($F21*D21,"")) -> 528
A22: 2.3 | B22: Cat 6 UTP 7ft patch cords-Jack Panel side - 60% | C22: Nos | D22: =(D20*20)*0.6 -> 132 | E22: 216 | F22: 12 | G22: =IF($E22="","",IFERROR($E22*D22,"")) -> 28512 | H22: =IF($F22="","",IFERROR($F22*D22,"")) -> 1584
A23: 2.4 | B23: Cat 6 UTP 4ft patch cords-Jack Panel side - 20% | C23: Nos | D23: =(D20*20)*0.2 -> 44 | E23: 180 | F23: 12 | G23: =IF($E23="","",IFERROR($E23*D23,"")) -> 7920 | H23: =IF($F23="","",IFERROR($F23*D23,"")) -> 528
A25: =A19+1 -> 3 | B25: VOICE
A26: 3.1 | B26: 4-pair, Cat 6 UTP Cable, roll of 305m, Grey | C26: Box | D26: 4 | E26: 16800 | F26: 360 | G26: =IF($E26="","",IFERROR($E26*D26,"")) -> 67200 | H26: =IF($F26="","",IFERROR($F26*D26,"")) -> 1440
A27: 3.2 | B27: Cat 6 UTP Information Outlet for Workstation end | C27: Nos | D27: 15 | E27: 420 | F27: 60 | G27: =IF($E27="","",IFERROR($E27*D27,"")) -> 6300 | H27: =IF($F27="","",IFERROR($F27*D27,"")) -> 900
A28: 3.3 | B28: Cat6 RJ45-RJ45 UTP Patch Cords, color matched, Yellow - Field end, 7 ft | C28: Nos | D28: =D27:D27 -> 15 | E28: 240 | F28: 12 | G28: =IF($E28="","",IFERROR($E28*D28,"")) -> 3600 | H28: =IF($F28="","",IFERROR($F28*D28,"")) -> 180
A29: 3.4 | B29: Single Face Plates (80%) | C29: Nos | D29: =D27*0.8 -> 12 | E29: 90 | F29: 24 | G29: =IF($E29="","",IFERROR($E29*D29,"")) -> 1080 | H29: =IF($F29="","",IFERROR($F29*D29,"")) -> 288
A30: 3.5 | B30: Dual Face Plates (20%) | C30: Nos | D30: =D27*0.1 -> 1.5 | E30: 96 | F30: 24 | G30: =IF($E30="","",IFERROR($E30*D30,"")) -> 144 | H30: =IF($F30="","",IFERROR($F30*D30,"")) -> 36
A31: 3.6 | B31: Quad Face Plates | C31: Nos | D31: 0 | E31: 102 | F31: 24 | G31: =IF($E31="","",IFERROR($E31*D31,"")) -> 0 | H31: =IF($F31="","",IFERROR($F31*D31,"")) -> 0
A32: 3.7 | B32: Blank Inserts | C32: Nos | D32: 0 | E32: 18 | F32: 6 | G32: =IF($E32="","",IFERROR($E32*D32,"")) -> 0 | H32: =IF($F32="","",IFERROR($F32*D32,"")) -> 0
A33: 3.8 | B33: Supply and fixing of Metal box suitable information outlet , flush/surface type in position . The rate shall exclude the cost of faceplate and Information Outlet. | C33: Nos | D33: =D27*5% -> 0.75 | E33: 42 | F33: 12 | G33: =IF($E33="","",IFERROR($E33*D33,"")) -> 31.5 | H33: =IF($F33="","",IFERROR($F33*D33,"")) -> 9
A34: 3.9 | B34: 4-pair, Cat 6 UTP FRLS Cable | C34: Mtrs | D34: 0 | E34: 54 | F34: 14 | G34: =IF($E34="","",IFERROR($E34*D34,"")) -> 0 | H34: =IF($F34="","",IFERROR($F34*D34,"")) -> 0
A36: =A25+1 -> 4 | B36: HUB ROOM SIDE - VOICE
A37: 4.1 | B37: Cat 6 24 Port Angled Discrete Jack panel - fully loaded (1U).The rate shall include the cost of Patch Panel, Information Outlets with all the required supporting accessories. | C37: Nos | D37: 1 | E37: 9600 | F37: 600 | G37: =IF($E37="","",IFERROR($E37*D37,"")) -> 9600 | H37: =IF($F37="","",IFERROR($F37*D37,"")) -> 600
A38: 4.2 | B38: Cat 6 UTP 10ft patch cords-Jack Panel side - 20% | C38: Nos | D38: =(D37*24)*0.2 -> 4.8 | E38: 270 | F38: 12 | G38: =IF($E38="","",IFERROR($E38*D38,"")) -> 1296 | H38: =IF($F38="","",IFERROR($F38*D38,"")) -> 57.6
A39: 4.3 | B39: Cat 6 UTP 7ft patch cords-Jack Panel side - 60% | C39: Nos | D39: =(D37*24)*0.6 -> 14.4 | E39: 216 | F39: 12 | G39: =IF($E39="","",IFERROR($E39*D39,"")) -> 3110.4 | H39: =IF($F39="","",IFERROR($F39*D39,"")) -> 172.8
A40: 4.4 | B40: Cat 6 UTP 4ft patch cords-Jack Panel side - 20% | C40: Nos | D40: =(D37*24)*0.2 -> 4.8 | E40: 180 | F40: 12 | G40: =IF($E40="","",IFERROR($E40*D40,"")) -> 864 | H40: =IF($F40="","",IFERROR($F40*D40,"")) -> 57.6
A42: 5 | B42: WIFI - DATA | I42: Actual Based on Heat map
A43: 5.1 | B43: 4-pair, Cat 6A UTP Cable, roll of 305m, Grey | C43: Box | D43: 25 | E43: 19200 | F43: 360 | G43: =IF($E43="","",IFERROR($E43*D43,"")) -> 480000 | H43: =IF($F43="","",IFERROR($F43*D43,"")) -> 9000
A44: 5.2 | B44: Cat6A UTP Information Outlet for Workstation end | C44: Nos | D44: =45*2 -> 90 | E44: 330 | F44: 36 | G44: =IF($E44="","",IFERROR($E44*D44,"")) -> 29700 | H44: =IF($F44="","",IFERROR($F44*D44,"")) -> 3240
A45: 5.3 | B45: Cat6A RJ45-RJ45 UTP Patch Cords, color matched, Yellow - Field end, 7 ft | C45: Nos | D45: =D44:D44 -> 90 | E45: 240 | F45: 12 | G45: =IF($E45="","",IFERROR($E45*D45,"")) -> 21600 | H45: =IF($F45="","",IFERROR($F45*D45,"")) -> 1080
A46: 5.4 | B46: Single Face Plates (100%) | C46: Nos | D46: =D44 -> 90 | E46: 90 | F46: 24 | G46: =IF($E46="","",IFERROR($E46*D46,"")) -> 8100 | H46: =IF($F46="","",IFERROR($F46*D46,"")) -> 2160
A47: 5.5 | B47: Dual Face Plates | C47: Nos | D47: =D44*0 -> 0 | E47: 96 | F47: 24 | G47: =IF($E47="","",IFERROR($E47*D47,"")) -> 0 | H47: =IF($F47="","",IFERROR($F47*D47,"")) -> 0
A48: 5.6 | B48: Quad Face Plates | C48: Nos | D48: 0 | E48: 102 | F48: 24 | G48: =IF($E48="","",IFERROR($E48*D48,"")) -> 0 | H48: =IF($F48="","",IFERROR($F48*D48,"")) -> 0
A49: 5.7 | B49: Blank Inserts | C49: Nos | D49: 0 | E49: 18 | F49: 6 | G49: =IF($E49="","",IFERROR($E49*D49,"")) -> 0 | H49: =IF($F49="","",IFERROR($F49*D49,"")) -> 0
A50: 5.8 | B50: Supply and fixing of Metal box suitable information outlet , flush/surface type in position . The rate shall exclude the cost of faceplate and Information Outlet. | C50: Nos | D50: =D44 -> 90 | E50: 42 | F50: 12 | G50: =IF($E50="","",IFERROR($E50*D50,"")) -> 3780 | H50: =IF($F50="","",IFERROR($F50*D50,"")) -> 1080
A52: 6 | B52: HUB ROOM SIDE -WIFI
A53: 6.1 | B53: Cat 6A 24 Port Angled Discrete Jack panel - fully loaded (1U).The rate shall include the cost of Patch Panel, Information Outlets with all the required supporting accessories. | C53: Nos | D53: 4 | E53: 14400 | F53: 600 | G53: =IF($E53="","",IFERROR($E53*D53,"")) -> 57600 | H53: =IF($F53="","",IFERROR($F53*D53,"")) -> 2400
A54: 6.1 | B54: Cat 6A 8 Port Angled Discrete Jack panel - fully loaded (1U).The rate shall include the cost of Patch Panel, Information Outlets with all the required supporting accessories. | C54: Nos | D54: 0 | E54: 11040 | F54: 600 | G54: =IF($E54="","",IFERROR($E54*D54,"")) -> 0 | H54: =IF($F54="","",IFERROR($F54*D54,"")) -> 0
A55: 6.2 | B55: Cat 6A UTP 10ft patch cords-Jack Panel side - 20% | C55: Nos | D55: =(D53*24)*0.2 -> 19.2 | E55: 330 | F55: 24 | G55: =IF($E55="","",IFERROR($E55*D55,"")) -> 6336 | H55: =IF($F55="","",IFERROR($F55*D55,"")) -> 460.8
A56: 6.3 | B56: Cat 6A UTP 7ft patch cords-Jack Panel side - 60% | C56: Nos | D56: =(D53*24)*0.6 -> 57.6 | E56: 288 | F56: 24 | G56: =IF($E56="","",IFERROR($E56*D56,"")) -> 16588.8 | H56: =IF($F56="","",IFERROR($F56*D56,"")) -> 1382.4
A57: 6.4 | B57: Cat 6A UTP 4ft patch cords-Jack Panel side - 20% | C57: Nos | D57: =(D53*24)*0.2 -> 19.2 | E57: 240 | F57: 18 | G57: =IF($E57="","",IFERROR($E57*D57,"")) -> 4608 | H57: =IF($F57="","",IFERROR($F57*D57,"")) -> 345.6
A59: 7 | B59: Fiber Backbone Cable
A60: 7.1 | B60: 12 Core MM - OM3 Indoor /Outdoor Fiber Optic Cable | C60: Mtrs | D60: 200 | E60: 252 | F60: 24 | G60: =IF($E60="","",IFERROR($E60*D60,"")) -> 50400 | H60: =IF($F60="","",IFERROR($F60*D60,"")) -> 4800
A61: 7.2 | B61: 1U Sliding Face Plate shelf (Front Face Plate full single Plate type) | C61: Each | D61: 2 | E61: 15000 | F61: 600 | G61: =IF($E61="","",IFERROR($E61*D61,"")) -> 30000 | H61: =IF($F61="","",IFERROR($F61*D61,"")) -> 1200
A62: 7.3 | B62: Front Face Plate Panel, Accepts 24 Duplex LC Adapters | C62: Each | D62: 2 | E62: 9000 | F62: 180 | G62: =IF($E62="","",IFERROR($E62*D62,"")) -> 18000 | H62: =IF($F62="","",IFERROR($F62*D62,"")) -> 360
A63: 7.4 | B63: LC Duplex Adapter | C63: Each | D63: 2 | E63: 960 | F63: 120 | G63: =IF($E63="","",IFERROR($E63*D63,"")) -> 1920 | H63: =IF($F63="","",IFERROR($F63*D63,"")) -> 240
A64: 7.5 | B64: LC, MM Pigtail, 3 Feet 50/125 | C64: Each | D64: 2 | E64: 1500 | F64: 120 | G64: =IF($E64="","",IFERROR($E64*D64,"")) -> 3000 | H64: =IF($F64="","",IFERROR($F64*D64,"")) -> 240
A65: 7.6 | B65: RoloSplice Kit 2 Fusion Splice Trays, for 1U Fiber Shelf | C65: Each | D65: 2 | E65: 6000 | F65: 120 | G65: =IF($E65="","",IFERROR($E65*D65,"")) -> 12000 | H65: =IF($F65="","",IFERROR($F65*D65,"")) -> 240
A66: 7.7 | B66: Multimode Fiber Patch chords of 3 meters- LC TO LC | C66: Each | D66: 2 | E66: 804 | F66: 60 | G66: =IF($E66="","",IFERROR($E66*D66,"")) -> 1608 | H66: =IF($F66="","",IFERROR($F66*D66,"")) -> 120
A67: 7.8 | B67: Multimode Fiber Patch chords of 10 meters- LC TO LC | C67: Each | D67: 2 | E67: 1080 | F67: 60 | G67: =IF($E67="","",IFERROR($E67*D67,"")) -> 2160 | H67: =IF($F67="","",IFERROR($F67*D67,"")) -> 120
A69: 8 | B69: RACKS & WIRE MANAGERS
A70: 8.1 | B70: 45U, 2 Post Open Rack | C70: Set | D70: 4 | E70: 126000 | F70: 6000 | G70: =IF($E70="","",IFERROR($E70*D70,"")) -> 504000 | H70: =IF($F70="","",IFERROR($F70*D70,"")) -> 24000
B71: High Density 8'' Vertical cable Manager
B72: High Density 12'' Vertical cable Manager
B73: 2U Horizantal Cable Manager, Fingure Duct Style
B74: Ladder Set
B75: 2U, 5/15amps Horizontal PDU
B76: Velcro Cable Tie Black, 25m
A78: 8.2 | B78: 42U Rack Frame/800X800- Closed network Rack | C78: Set | D78: 1 | E78: 150000 | F78: 6000 | G78: =IF($E78="","",IFERROR($E78*D78,"")) -> 150000 | H78: =IF($F78="","",IFERROR($F78*D78,"")) -> 6000
B79: Casters Set of 4/Tp3
B80: Levellers
B81: 19" Adopter kit /42U/Loops
B82: Perforated Door/42/800/Convex/
B83: Perforated Door/42/800/Dual
B84: Side Panels/800/42U/Vented
B85: Swing Handle /Mechnical Lock / Single Point / Common Key/Die Cast Metal
B86: 1Ph, 230V, 32/40A, Zero U standard Vertcal rack mount power distribution unit with 12 X Indian Round Pin 5/15A, (Inlet Plug Not Installed, Recommended IEC30932A 2P +E), 16A MCB X 2 Circuits- PDU Rating 5KVA/4.5KVA/Bottom feed-3Mt/ Black
B87: Horz. Cable Organiser/1U/Loop
B88: Shelf/1000
B89: Mounting Hardware-CR (Pack of 20)
B90: Velcro/ cable Tie Wraps
... B92: Labels for Outlets/ Faceplates/ Panels
A94: 8.3 | B94: 06 U wall mount rack with required mounting accessories, Rate shall include required accessories, tools and tackles, transportation, material and labor etc., complete as instructed by Engineer In charge. The contractor should follow the safety measures inside the premises. | C94: Set | D94: RO | E94: 6600 | F94: 1800 | G94: =IF($E94="","",IFERROR($E94*D94,"")) | H94: =IF($F94="","",IFERROR($F94*D94,""))
A95: 8.4 | B95: 09 U wall mount rack with required mounting accessories, Rate shall include required accessories, tools and tackles, transportation, material and labor etc., complete as instructed by Engineer In charge. The contractor should follow the safety measures inside the premises. | C95: Set | D95: RO | E95: 10200 | F95: 1800 | G95: =IF($E95="","",IFERROR($E95*D95,"")) | H95: =IF($F95="","",IFERROR($F95*D95,""))
A96: 8.5 | B96: 15 U wall mount rack with required mounting accessories, Rate shall include required accessories, tools and tackles, transportation, material and labor etc., complete as instructed by Engineer In charge. The contractor should follow the safety measures inside the premises. | C96: Set | D96: RO | E96: 15000 | F96: 1800 | G96: =IF($E96="","",IFERROR($E96*D96,"")) | H96: =IF($F96="","",IFERROR($F96*D96,""))
A97: 8.6 | B97: Fluke Test ,Commissioning along with test report | C97: Ports | D97: =D10+D27+D44 -> 315 | E97: 0 | F97: 210 | G97: =IF($E97="","",IFERROR($E97*D97,"")) -> 0 | H97: =IF($F97="","",IFERROR($F97*D97,"")) -> 66150
A99: 9 | B99: PVC pipes
B100: Supply and laying of 2 mm thick rigid FRLS PVC conduits in concealed conduit system using conduit accessories like junction boxes, collars, bends, elbows, binding wires, etc.
A101: 9.1 | B101: 32 mm dia conduit | C101: Mtrs | D101: 150 | E101: 54 | F101: 24 | G101: =IF($E101="","",IFERROR($E101*D101,"")) -> 8100 | H101: =IF($F101="","",IFERROR($F101*D101,"")) -> 3600
A102: 9.2 | B102: 25 mm dia conduit | C102: Mtrs | D102: 1100 | E102: 42 | F102: 18 | G102: =IF($E102="","",IFERROR($E102*D102,"")) -> 46200 | H102: =IF($F102="","",IFERROR($F102*D102,"")) -> 19800
A103: 9.3 | B103: 19 mm dia conduit | C103: Mtrs | E103: 36 | F103: 14 | G103: =IF($E103="","",IFERROR($E103*D103,"")) -> 0 | H103: =IF($F103="","",IFERROR($F103*D103,"")) -> 0
B105: TOTAL AMOUNT | G105: =SUM(G8:G104) -> 2720115.7 | H105: =SUM(H8:H104) -> 210281.8 | I105: =G105+H105 -> 2930397.5
B106: TAX
B107: GRAND TOTAL - SUPPLY+INSTALLATION+TAXES
B109: EXCLUSIONS
A110: 1 | B110: Active Components (Network Switch,Servers & it's Racks)
A111: 2 | B111: Computing and storage equipment
A112: 3 | B112: WIFI Equipment and software/HSIA
A113: 4 | B113: Telephony Equipment and software
A114: 5 | B114: Network Printing
...

Sheet CCTV
A2: ESTIMATION FOR CCTV
A3: Project: Indegene_3F | H3: Date: | I3: 11.11.2025
A4: Location: | H4: Revision | I4: R0
A5: Project no: | H5: Document No:
A7: S.no | B7: Description | C7: Unit | D7: Qty | E7: Rate | G7: Amount | I7: Remarks
E8: Supply | F8: Installation | G8: Supply | H8: Installation
A9: 1 | B9: UL approved, Dome Indoor type 2MP,Ceiling/Wall/Surface Mounted ,1920x1080@30fps resolution Dome type network Camera, 15m IR Distance 2.8 - 12 mm Verofocal Lens @ F1.6 & 120dB Wide Dynamic Range, H.264, H.265/MJPEG, WDR, 1/3”Progressive CMOS, Fixed-focal, (Field of View-90°),IR cut filter 12V DC & PoE(802.3af), Day / Night ,on board storage facility.Standards: IP67, IK10, ONVIF, multiple streams, video motion detection, camera tamper alarm, ONVIF compliant,Network Disconnetced ,IP Adress Conflit,Illegal Login,HDD Full,HDD error . The Camera shall be wall / ceiling mounted. The Rate shall include the cost of accessories required for mounting the cameras | C9: Nos | D9: =85*0 -> 0 | E9: 6000 | F9: 240 | G9: =IF($D9="","",IFERROR($D9*E9,"")) -> 0 | H9: =IF($D9="","",IFERROR($D9*F9,"")) -> 0
A10: 2 | B10: UL approved, Out door type (IP 66) 2MP 30fps resolution IR Bullet type Network Camera, (Field of View-60°) 15m IR Distance 2.8 - 12 mm @ F1.4, motorized lens (-Z) & 120dB Wide Dynamic Range, H.265, H.265+, 12V DC & PoE(802.3af), Min. Illumination 0.005 lux @(F1.2, AGC ON), Shutter Speed 1/30 s ~ /100,000s, IR cut filter with auto switch, ONVIF Profile S, PSIA, CGI, 3D Digital noise reduction (video motion detection, camera tamper alarm, ONVIF compliant, and NEMA 4X-rated Housing).The Camera shall be wall / ceiling mounted. The Rate shall include the cost of accessories required for mounting the cameras | C10: Nos | D10: =1*0 -> 0 | E10: 17400 | F10: 900 | G10: =IF($D10="","",IFERROR($D10*E10,"")) -> 0 | H10: =IF($D10="","",IFERROR($D10*F10,"")) -> 0
A11: 3 | B11: Supply, installation, testing and Commissioning of 16 Channel NVR Ultra 4 K resolution and recording software with Storage capacity of 90Days .Network Throughput : Input 320 Mbps out put 320 Mbps : Resolution : 1080p (1920x1080):Frame rate : 1-25/30 FPS;Supports multi Stream,Compression format,Play back : 16 chan at 1080P Simultanious Play back ;Recording Bit Rate : 320Mbps;Recording Mode : Schedule (Regular Continous,Motion etection,Alarm Stop);Recording interval : 1-120 min (default 60 min);Pre Event Recording Interval : 1-30 sec;Post Event Recording Interval : 10-300 sec;Video Detection : Motion Detection MD Zones Video Loss Camera Blank ,Trigger events : Recording; Tour; Alarm;Video Push; Email; FTP;Snapshot; Buzzer; Remote playback, remote backup, remote I/O control and remote desktop configuration;2 HDMI/1 VGA output, Video output up to 12MP resolution, 3 USB & serial port interface, 4 SATA interfaces, Up to 8TB capacity for each HDD, 300 W Power Cosumption,2 Gigabit Ethernet network interfaces ;Storage : Internal HDD 4 SATA Ports supports upto 32TB,External HDD 1 eSATA Port ,ANR technology Vendor should submit the storage calculation & the components considered in detail. | C11: No | D11: =3*0 -> 0 | E11: 78000 | F11: 4200 | G11: =IF($D11="","",IFERROR($D11*E11,"")) -> 0 | H11: =IF($D11="","",IFERROR($D11*F11,"")) -> 0
A12: 4 | B12: Supply, installation, testing and Commissioning of 8 Channel NVR Ultra 4 K resolution and recording software with Storage capacity of 90Days .Network Throughput : Input 320 Mbps out put 320 Mbps : Resolution : 1080p (1920x1080):Frame rate : 1-25/30 FPS;Supports multi Stream,Compression format,Play back : 16 chan at 1080P Simultanious Play back ;Recording Bit Rate : 320Mbps;Recording Mode : Schedule (Regular Continous,Motion etection,Alarm Stop);Recording interval : 1-120 min (default 60 min);Pre Event Recording Interval : 1-30 sec;Post Event Recording Interval : 10-300 sec;Video Detection : Motion Detection MD Zones Video Loss Camera Blank ,Trigger events : Recording; Tour; Alarm;Video Push; Email; FTP;Snapshot; Buzzer; Remote playback, remote backup, remote I/O control and remote desktop configuration;2 HDMI/1 VGA output, Video output up to 12MP resolution, 3 USB & serial port interface, 4 SATA interfaces, Up to 8TB capacity for each HDD, 300 W Power Cosumption,2 Gigabit Ethernet network interfaces ;Storage : Internal HDD 4 SATA Ports supports upto 32TB,External HDD 1 eSATA Port ,ANR technology Vendor should submit the storage calculation & the components considered in detail. | C12: No | D12: =1*0 -> 0 | E12: 54000 | F12: 4200 | G12: =IF($D12="","",IFERROR($D12*E12,"")) -> 0 | H12: =IF($D12="","",IFERROR($D12*F12,"")) -> 0
A13: 5 | B13: CAT 6A PoE Cable, as per the survey done, Rate shall include required accessories, tools etc., complete as required. | C13: Mtr | D13: =85*75 -> 6375 | E13: 72 | F13: 14 | G13: =IF($D13="","",IFERROR($D13*E13,"")) -> 459000 | H13: =IF($D13="","",IFERROR($D13*F13,"")) -> 89250
A14: 6 | B14: Cat 6A Sngle Information Outlets including faceplates and backbox accessories.(CCTV) | C14: Nos | D14: 86 | E14: 420 | F14: 60 | G14: =IF($D14="","",IFERROR($D14*E14,"")) -> 36120 | H14: =IF($D14="","",IFERROR($D14*F14,"")) -> 5160
A15: 7 | B15: Cat 6A PoE 24 Port Angled Discrete Jack panel - fully loaded (1U).The rate shall include the cost of Patch Panel, Information Outlets with all the required supporting accessories.(CCTV) | C15: Nos | D15: =4 -> 4 | E15: 14256 | F15: 2484 | G15: =IF($D15="","",IFERROR($D15*E15,"")) -> 57024 | H15: =IF($D15="","",IFERROR($D15*F15,"")) -> 9936
A16: 8 | B16: Cat 6A poE 12 Port Angled Discrete Jack panel - fully loaded (1U).The rate shall include the cost of Patch Panel, Information Outlets with all the required supporting accessories.(CCTV) | C16: Mtr | D16: 0 | E16: 4200 | F16: 360 | G16: =IF($D16="","",IFERROR($D16*E16,"")) -> 0 | H16: =IF($D16="","",IFERROR($D16*F16,"")) -> 0
A17: 9 | B17: Cat 6A, 7ft Gigabit Snagless Molded Patch Cable (RJ-45 Male) with factory crimping, these patch cords will suffice for connecting between Data Outlet & CCTV | C17: No | D17: 0 | E17: 252 | F17: 12 | G17: =IF($D17="","",IFERROR($D17*E17,"")) -> 0 | H17: =IF($D17="","",IFERROR($D17*F17,"")) -> 0
A18: 10 | B18: Cat 6A, 4ft Gigabit Snagless Molded Patch Cable (RJ-45 Male) with factory crimping, these patch cords will suffice for connecting between Data Outlet & CCTV (100%) | C18: No | D18: =86*2 -> 172 | E18: 374 | F18: 18 | G18: =IF($D18="","",IFERROR($D18*E18,"")) -> 64328 | H18: =IF($D18="","",IFERROR($D18*F18,"")) -> 3096
A19: 11 | B19: Supply, installation, testing and Commissioning of Client lisences to monitor from internal LAN and remote, | C19: No | D19: 0 | E19: 18000 | F19: 0 | G19: =IF($D19="","",IFERROR($D19*E19,"")) -> 0 | H19: =IF($D19="","",IFERROR($D19*F19,"")) -> 0
A20: 12 | B20: Supply, installation, testing and Commissioning of Client PC with i5 Processor, 16GB RAM(Expandable up to 32GB), 1TB HDD, Keyboard, mouse, NVIDIA graphics card with dual monitor output Genunine Windows 10/ latest windows operating system CPU | C20: No | D20: 0 | E20: 54000 | F20: 2400 | G20: =IF($D20="","",IFERROR($D20*E20,"")) -> 0 | H20: =IF($D20="","",IFERROR($D20*F20,"")) -> 0
A21: 13 | B21: 42", Full HD 1920x1080 Monitor Multiple connectivity, with Base and wall mount kit, suitable for 24/7 operation. Rate shall include required accessories, tools etc., complete as required. | C21: No | D21: 0 | E21: 42000 | F21: 1200 | G21: =IF($D21="","",IFERROR($D21*E21,"")) -> 0 | H21: =IF($D21="","",IFERROR($D21*F21,"")) -> 0
A22: 14 | B22: 06 U wall mount rack with required mounting accessories, Rate shall include required accessories, tools etc., complete as required. | C22: No | D22: 0 | E22: 9000 | F22: 240 | G22: =IF($D22="","",IFERROR($D22*E22,"")) -> 0 | H22: =IF($D22="","",IFERROR($D22*F22,"")) -> 0
A23: 15 | B23: PVC pipes
B24: Supply and laying of 2 mm thick rigid FRLS PVC conduits in concealed conduit system using conduit accessories like junction boxes, collars, bends, elbows, binding wires, etc.
A25: a | B25: 32 mm dia conduit | C25: Mtrs | D25: 0 | E25: 54 | F25: 24 | G25: =IF($D25="","",IFERROR($D25*E25,"")) -> 0 | H25: =IF($D25="","",IFERROR($D25*F25,"")) -> 0
A26: b | B26: 25 mm dia conduit | C26: Mtrs | D26: 300 | E26: 42 | F26: 18 | G26: =IF($D26="","",IFERROR($D26*E26,"")) -> 12600 | H26: =IF($D26="","",IFERROR($D26*F26,"")) -> 5400
A27: c | B27: 19 mm dia conduit | C27: Mtrs | D27: 0 | E27: 36 | F27: 14 | G27: =IF($D27="","",IFERROR($D27*E27,"")) -> 0 | H27: =IF($D27="","",IFERROR($D27*F27,"")) -> 0
A28: 16 | B28: 1.5 meter length, Powder coated MS 25 mm dia Conduit supports for CCTV cameras with required supporting /mounting accessories complete. | C28: No | D28: =35*0 -> 0 | E28: 1440 | F28: 360 | G28: =IF($D28="","",IFERROR($D28*E28,"")) -> 0 | H28: =IF($D28="","",IFERROR($D28*F28,"")) -> 0
A29: 17 | B29: 6.5 Mts height outdoor type CCTV Pole with required mounting accessories | C29: No | D29: 0 | E29: 9000 | F29: 600 | G29: =IF($D29="","",IFERROR($D29*E29,"")) -> 0 | H29: =IF($D29="","",IFERROR($D29*F29,"")) -> 0
A30: 18 | B30: Supervision, Programming, Testing & Commissioning, Documentation, Training. | C30: LS | D30: 0 | E30: 0 | F30: 90000 | G30: =IF($D30="","",IFERROR($D30*E30,"")) -> 0 | H30: =IF($D30="","",IFERROR($D30*F30,"")) -> 0
B32: TOTAL AMOUNT | G32: =SUM(G9:G30) -> 629072 | H32: =SUM(H9:H30) -> 112842 | I32: =G32+H32 -> 741914
B33: TAX
B34: GRAND TOTAL - SUPPLY + INSTALLATION +TAXES
B36: Makes:
B37: CAMERAS & SOFTWARE: Bosch Honeywell Axis
B38: NVR: Bosch Honeywell Axis
B39: CAT 6A Cables : Commscope,Systimax
B40: RACKS : Rittal ,Valrack,Netrack
B42: Exclusions:
B43: Active components, Network Switch & servers ,Wifi Equipmnet
B44: Note:
B45: All Devices shall be of Enterprize Class Only

Sheet CCTV - Indegene 
A2: ESTIMATION FOR CCTV
A3: Project: Indegene_3F | H3: Date: | I3: 11.11.2025
A4: Location: | H4: Revision | I4: R0
A5: Project no: | H5: Document No:
A7: S.no | B7: Description | C7: Unit | D7: Qty | E7: Rate | G7: Amount | I7: Remarks
E8: Supply | F8: Installation | G8: Supply | H8: Installation
A9: 1 | B9: UL approved, Dome Indoor type 2MP,Ceiling/Wall/Surface Mounted ,1920x1080@30fps resolution Dome type network Camera, 15m IR Distance 2.8 - 12 mm Verofocal Lens @ F1.6 & 120dB Wide Dynamic Range, H.264, H.265/MJPEG, WDR, 1/3”Progressive CMOS, Fixed-focal, (Field of View-90°),IR cut filter 12V DC & PoE(802.3af), Day / Night ,on board storage facility.Standards: IP67, IK10, ONVIF, multiple streams, video motion detection, camera tamper alarm, ONVIF compliant,Network Disconnetced ,IP Adress Conflit,Illegal Login,HDD Full,HDD error . The Camera shall be wall / ceiling mounted. The Rate shall include the cost of accessories required for mounting the cameras | C9: Nos | D9: =85 -> 85 | G9: =IF($D9="","",IFERROR($D9*E9,"")) -> 0 | H9: =IF($D9="","",IFERROR($D9*F9,"")) -> 0 | I9: Under Client Scope
A10: 2 | B10: UL approved, Out door type (IP 66) 2MP 30fps resolution IR Bullet type Network Camera, (Field of View-60°) 15m IR Distance 2.8 - 12 mm @ F1.4, motorized lens (-Z) & 120dB Wide Dynamic Range, H.265, H.265+, 12V DC & PoE(802.3af), Min. Illumination 0.005 lux @(F1.2, AGC ON), Shutter Speed 1/30 s ~ /100,000s, IR cut filter with auto switch, ONVIF Profile S, PSIA, CGI, 3D Digital noise reduction (video motion detection, camera tamper alarm, ONVIF compliant, and NEMA 4X-rated Housing).The Camera shall be wall / ceiling mounted. The Rate shall include the cost of accessories required for mounting the cameras | C10: Nos | D10: 1 | G10: =IF($D10="","",IFERROR($D10*E10,"")) -> 0 | H10: =IF($D10="","",IFERROR($D10*F10,"")) -> 0 | I10: Outdoor
A11: 3 | B11: Supply, installation, testing and Commissioning of 16 Channel NVR Ultra 4 K resolution and recording software with Storage capacity of 90Days .Network Throughput : Input 320 Mbps out put 320 Mbps : Resolution : 1080p (1920x1080):Frame rate : 1-25/30 FPS;Supports multi Stream,Compression format,Play back : 16 chan at 1080P Simultanious Play back ;Recording Bit Rate : 320Mbps;Recording Mode : Schedule (Regular Continous,Motion etection,Alarm Stop);Recording interval : 1-120 min (default 60 min);Pre Event Recording Interval : 1-30 sec;Post Event Recording Interval : 10-300 sec;Video Detection : Motion Detection MD Zones Video Loss Camera Blank ,Trigger events : Recording; Tour; Alarm;Video Push; Email; FTP;Snapshot; Buzzer; Remote playback, remote backup, remote I/O control and remote desktop configuration;2 HDMI/1 VGA output, Video output up to 12MP resolution, 3 USB & serial port interface, 4 SATA interfaces, Up to 8TB capacity for each HDD, 300 W Power Cosumption,2 Gigabit Ethernet network interfaces ;Storage : Internal HDD 4 SATA Ports supports upto 32TB,External HDD 1 eSATA Port ,ANR technology Vendor should submit the storage calculation & the components considered in detail. | C11: No | D11: 5 | G11: =IF($D11="","",IFERROR($D11*E11,"")) -> 0 | H11: =IF($D11="","",IFERROR($D11*F11,"")) -> 0 | I11: Under Client Scope
A12: 4 | B12: Supply, installation, testing and Commissioning of 8 Channel NVR Ultra 4 K resolution and recording software with Storage capacity of 90Days .Network Throughput : Input 320 Mbps out put 320 Mbps : Resolution : 1080p (1920x1080):Frame rate : 1-25/30 FPS;Supports multi Stream,Compression format,Play back : 16 chan at 1080P Simultanious Play back ;Recording Bit Rate : 320Mbps;Recording Mode : Schedule (Regular Continous,Motion etection,Alarm Stop);Recording interval : 1-120 min (default 60 min);Pre Event Recording Interval : 1-30 sec;Post Event Recording Interval : 10-300 sec;Video Detection : Motion Detection MD Zones Video Loss Camera Blank ,Trigger events : Recording; Tour; Alarm;Video Push; Email; FTP;Snapshot; Buzzer; Remote playback, remote backup, remote I/O control and remote desktop configuration;2 HDMI/1 VGA output, Video output up to 12MP resolution, 3 USB & serial port interface, 4 SATA interfaces, Up to 8TB capacity for each HDD, 300 W Power Cosumption,2 Gigabit Ethernet network interfaces ;Storage : Internal HDD 4 SATA Ports supports upto 32TB,External HDD 1 eSATA Port ,ANR technology Vendor should submit the storage calculation & the components considered in detail. | C12: No | D12: =1 -> 1 | G12: =IF($D12="","",IFERROR($D12*E12,"")) -> 0 | H12: =IF($D12="","",IFERROR($D12*F12,"")) -> 0 | I12: Under Client Scope
A13: 5 | B13: CAT 6A PoE Cable, as per the survey done, Rate shall include required accessories, tools etc., complete as required. | C13: Mtr | G13: =IF($D13="","",IFERROR($D13*E13,"")) | H13: =IF($D13="","",IFERROR($D13*F13,""))
A14: 6 | B14: Cat 6A Sngle Information Outlets including faceplates and backbox accessories.(CCTV) | C14: Nos | G14: =IF($D14="","",IFERROR($D14*E14,"")) | H14: =IF($D14="","",IFERROR($D14*F14,""))
A15: 7 | B15: Cat 6A PoE 24 Port Angled Discrete Jack panel - fully loaded (1U).The rate shall include the cost of Patch Panel, Information Outlets with all the required supporting accessories.(CCTV) | C15: Nos | G15: =IF($D15="","",IFERROR($D15*E15,"")) | H15: =IF($D15="","",IFERROR($D15*F15,""))
A16: 8 | B16: Cat 6A poE 12 Port Angled Discrete Jack panel - fully loaded (1U).The rate shall include the cost of Patch Panel, Information Outlets with all the required supporting accessories.(CCTV) | C16: Mtr | G16: =IF($D16="","",IFERROR($D16*E16,"")) | H16: =IF($D16="","",IFERROR($D16*F16,""))
A17: 9 | B17: Cat 6A, 7ft Gigabit Snagless Molded Patch Cable (RJ-45 Male) with factory crimping, these patch cords will suffice for connecting between Data Outlet & CCTV | C17: No | G17: =IF($D17="","",IFERROR($D17*E17,"")) | H17: =IF($D17="","",IFERROR($D17*F17,""))
A18: 10 | B18: Cat 6A, 4ft Gigabit Snagless Molded Patch Cable (RJ-45 Male) with factory crimping, these patch cords will suffice for connecting between Data Outlet & CCTV (100%) | C18: No | G18: =IF($D18="","",IFERROR($D18*E18,"")) | H18: =IF($D18="","",IFERROR($D18*F18,""))
A19: 11 | B19: Supply, installation, testing and Commissioning of Client lisences to monitor from internal LAN and remote, | C19: No | D19: 0 | G19: =IF($D19="","",IFERROR($D19*E19,"")) -> 0 | H19: =IF($D19="","",IFERROR($D19*F19,"")) -> 0 | I19: Under Client Scope
A20: 12 | B20: Supply, installation, testing and Commissioning of Client PC with i5 Processor, 16GB RAM(Expandable up to 32GB), 1TB HDD, Keyboard, mouse, NVIDIA graphics card with dual monitor output Genunine Windows 10/ latest windows operating system CPU | C20: No | D20: 0 | G20: =IF($D20="","",IFERROR($D20*E20,"")) -> 0 | H20: =IF($D20="","",IFERROR($D20*F20,"")) -> 0
A21: 13 | B21: 42", Full HD 1920x1080 Monitor Multiple connectivity, with Base and wall mount kit, suitable for 24/7 operation. Rate shall include required accessories, tools etc., complete as required. | C21: No | D21: 0 | G21: =IF($D21="","",IFERROR($D21*E21,"")) -> 0 | H21: =IF($D21="","",IFERROR($D21*F21,"")) -> 0
A22: 14 | B22: 06 U wall mount rack with required mounting accessories, Rate shall include required accessories, tools etc., complete as required. | C22: No | D22: 0 | G22: =IF($D22="","",IFERROR($D22*E22,"")) -> 0 | H22: =IF($D22="","",IFERROR($D22*F22,"")) -> 0
A23: 15 | B23: PVC pipes
B24: Supply and laying of 2 mm thick rigid FRLS PVC conduits in concealed conduit system using conduit accessories like junction boxes, collars, bends, elbows, binding wires, etc.
A25: a | B25: 32 mm dia conduit | C25: Mtrs | D25: 0 | G25: =IF($D25="","",IFERROR($D25*E25,"")) -> 0 | H25: =IF($D25="","",IFERROR($D25*F25,"")) -> 0
A26: b | B26: 25 mm dia conduit | C26: Mtrs | D26: 0 | G26: =IF($D26="","",IFERROR($D26*E26,"")) -> 0 | H26: =IF($D26="","",IFERROR($D26*F26,"")) -> 0
A27: c | B27: 19 mm dia conduit | C27: Mtrs | D27: 0 | G27: =IF($D27="","",IFERROR($D27*E27,"")) -> 0 | H27: =IF($D27="","",IFERROR($D27*F27,"")) -> 0
A28: 16 | B28: 1.5 meter length, Powder coated MS 25 mm dia Conduit supports for CCTV cameras with required supporting /mounting accessories complete. | C28: No | D28: 35 | G28: =IF($D28="","",IFERROR($D28*E28,"")) -> 0 | H28: =IF($D28="","",IFERROR($D28*F28,"")) -> 0
A29: 17 | B29: 6.5 Mts height outdoor type CCTV Pole with required mounting accessories | C29: No | D29: 0 | G29: =IF($D29="","",IFERROR($D29*E29,"")) -> 0 | H29: =IF($D29="","",IFERROR($D29*F29,"")) -> 0
A30: 18 | B30: Supervision, Programming, Testing & Commissioning, Documentation, Training. | C30: LS | D30: 1 | G30: =IF($D30="","",IFERROR($D30*E30,"")) -> 0 | H30: =IF($D30="","",IFERROR($D30*F30,"")) -> 0
B32: TOTAL AMOUNT | G32: =SUM(G9:G30) -> 0 | H32: =SUM(H9:H30) -> 0
B33: GRAND TOTAL - SUPPLY + INSTALLATION | H33: =H32+G32 -> 0
B35: Makes:
B36: CAMERAS & SOFTWARE: Bosch Honeywell Axis
B37: NVR: Bosch Honeywell Axis
B38: CAT 6A Cables : Commscope,Systimax
B39: RACKS : Rittal ,Valrack,Netrack
B41: Exclusions:
B42: Active components, Network Switch & servers ,Wifi Equipmnet
B43: Note:
B44: All Devices shall be of Enterprize Class Only

Sheet ACS
A1: ESTIMATION FOR ACS
A2: Project: Indegene_3F | H2: Date: | I2: 11.11.2025
A3: Location: | H3: Revision | I3: R0
A4: Project no:
A5: S.no | B5: Description | C5: Unit | D5: Qty | E5: Rate | G5: Amount | I5: Remarks
E6: Supply | F6: Installation | G6: Supply | H6: Installation
A7: 1 | B7: Supply and installation of UL, CE approved Access Controller - Smart card reader interfaces for 2 door controller 2 readers, Network connection to the host system and Compact Flash, RS485, RS232 or Ethernet connectivity, 20,000 cardholders data & up to 100,000 transaction detail storage | C7: Nos | D7: =20*0 -> 0 | E7: 19800 | F7: 1800 | G7: =IF($D7="","",IFERROR($D7*E7,"")) -> 0 | H7: =IF($D7="","",IFERROR($D7*F7,"")) -> 0
A8: 2 | B8: Supply and installation of Access Door Controller housing shall be in accordance with UL guidelines and is used for securely mounting and housing the Access Controller, extensions and the power supplies, | C8: Nos | D8: =1*0 -> 0 | E8: 9000 | F8: 600 | G8: =IF($D8="","",IFERROR($D8*E8,"")) -> 0 | H8: =IF($D8="","",IFERROR($D8*F8,"")) -> 0
A9: 3 | B9: Supply and installation of Power supply with battery charger for ACCESS DOOR CONTROLLER Shall be with Selectable 12 VDC or 24 VDC voltage output Overvoltage protection Regulates battery charging voltage The product is classified in accordance with the following standards: • EN 55022 Class B • EN 55024 • IEC / UL / EN 60950 & CSA (product safety) • CE The Power supply can be mounted on rails and installed in the housing | C9: Nos | D9: =1*0 -> 0 | E9: 3600 | F9: 600 | G9: =IF($D9="","",IFERROR($D9*E9,"")) -> 0 | H9: =IF($D9="","",IFERROR($D9*F9,"")) -> 0
A10: 4 | B10: Supply and installation of Smart card readers based on RFID technology, along with Back Plate including all fixing accessories. Rate shall include required accessories, tools, etc., complete as required. | C10: Nos | D10: =16*0 -> 0 | E10: 5400 | F10: 240 | G10: =IF($D10="","",IFERROR($D10*E10,"")) -> 0 | H10: =IF($D10="","",IFERROR($D10*F10,"")) -> 0
A11: 5 | B11: Supply and installation of Smart card readers based on RFID technology with Keypad, with Back Plate including all fixing accessories. Rate shall include required accessories, tools, etc., complete as required. | C11: Nos | D11: 0 | E11: 12600 | F11: 240 | G11: =IF($D11="","",IFERROR($D11*E11,"")) -> 0 | H11: =IF($D11="","",IFERROR($D11*F11,"")) -> 0
A12: 6 | B12: Supply and installation of Biometric unit consisting of Biometric Scanner and Smart card readers based on RFID technology, along with Back Plate including all fixing accessories. Rate shall include required accessories, tools, etc., complete as required. | C12: Nos | D12: 0 | E12: 9000 | F12: 240 | G12: =IF($D12="","",IFERROR($D12*E12,"")) -> 0 | H12: =IF($D12="","",IFERROR($D12*F12,"")) -> 0
A13: 7 | B13: Supply and installation of Biometric unit consisting of Biometric Scanner and Smart card readers based on RFID technology with Keypad, with Back Plate including all fixing accessories. Rate shall include required accessories, tools, etc., complete as required. | C13: Nos | D13: =4*0 -> 0 | E13: 27000 | F13: 600 | G13: =IF($D13="","",IFERROR($D13*E13,"")) -> 0 | H13: =IF($D13="","",IFERROR($D13*F13,"")) -> 0
A14: 8 | B14: Supply and installation of Smart Access Card (16k bit with 2 application areas) with print as per client requirement | C14: Nos | D14: RO | E14: 300 | F14: 60 | G14: =IF($D14="","",IFERROR($D14*E14,"")) | H14: =IF($D14="","",IFERROR($D14*F14,""))
A15: 9 | B15: Supply and installation of Single Leaf 600 Lbs Magnetic Lock with required mounting accessories, Rate shall include required accessories, tools, etc., complete as required. | C15: Nos | D15: =16*0 -> 0 | E15: 7800 | F15: 1080 | G15: =IF($D15="","",IFERROR($D15*E15,"")) -> 0 | H15: =IF($D15="","",IFERROR($D15*F15,"")) -> 0
A16: 10 | B16: Supply and installation of Double Leaf Magnetic Lock with required mounting accessories, Rate shall include required accessories, tools, etc., complete as required. | C16: Nos | D16: =2*0 -> 0 | E16: 10200 | F16: 1320 | G16: =IF($D16="","",IFERROR($D16*E16,"")) -> 0 | H16: =IF($D16="","",IFERROR($D16*F16,"")) -> 0
A17: 11 | B17: Supply and installation of Break Glass Unit, Rate shall include required accessories,MS junction box, tools etc., complete as required. | C17: Nos | D17: =20*0 -> 0 | E17: 1080 | F17: 360 | G17: =IF($D17="","",IFERROR($D17*E17,"")) -> 0 | H17: =IF($D17="","",IFERROR($D17*F17,"")) -> 0
A18: 12 | B18: Supply and installation of Exit Push Button, Rate shall include required accessories, tools etc., complete as required. | C18: Nos | D18: =20*0 -> 0 | E18: 780 | F18: 360 | G18: =IF($D18="","",IFERROR($D18*E18,"")) -> 0 | H18: =IF($D18="","",IFERROR($D18*F18,"")) -> 0
A19: 13 | B19: Supply and installation of Door Buzzer, Rate shall include required accessories, tools etc., complete as required. | C19: Nos | D19: =4*0 -> 0 | E19: 240 | F19: 120 | G19: =IF($D19="","",IFERROR($D19*E19,"")) -> 0 | H19: =IF($D19="","",IFERROR($D19*F19,"")) -> 0
A20: 14 | B20: ACS software with lisences to manage 200 card holder data including database management software like SQL also integarate with life saftey equipments like fire system : The ACS shall be modular, networked access control system having centralized architecture, capable of handling large corporation with multiple remote sites. The system control at the central computer location shall be under a single software program control, shall provide full integration of all components, and shall be alterable at any time, depending upon the facility requirements. The system shall include 100+ door licence and shall include 200 card holders. The ACS must provide a web server-based solution. Only Internet Explorer is required for a workstation to access the ACS login server. The system server shall be use latest edition of Windows Server 2012 R2 and Client shall support Windows 10 shall include network capability with the TCP/IP data communications network protocol and hardware. GUI shall support location tree display structure to allow easy selection of locations and sub-locations. The location tree display structure should have no limits in the number of levels or sub-levels. Shall support the integration of the Video Surveillance System interfacing shall be OPC compliant to provide direct import of existing video sub-system configuration. Audit trail for master record operations: The access control management must provide an audit trail for changes on cardholder master records as well as changes on access permissions. The audit trail must log at least the following operations. | C20: Nos | D20: RO | E20: 120000 | G20: =IF($D20="","",IFERROR($D20*E20,"")) | H20: =IF($D20="","",IFERROR($D20*F20,""))
B21: - create, delete a cardholder master record - change cardholder master record content, e.g. name, address - change cardholder access rights - create, delete an access permission - change access permission content, e.g. time profile,
B22: Hold up / Door hold up alarm: to provide the opening beyond set time to give pop indication and also CCTV to record the event | G22: =IF($D22="","",IFERROR($D22*E22,"")) | H22: =IF($D22="","",IFERROR($D22*F22,""))
A23: 15 | B23: Visitor Management system | C23: Nos | D23: RO | E23: 140400 | F23: 30000 | G23: =IF($D23="","",IFERROR($D23*E23,"")) | H23: =IF($D23="","",IFERROR($D23*F23,""))
A24: 16 | B24: Client PC with i5 Processor, 8GB RAM, 1TB HDD, Keyboard, mouse, NVIDIA graphics card with monitor , Windows 10 operating system CPU, with 19" Monitor alwong with webcam and printer | C24: Nos | D24: RO | E24: 66000 | F24: 1800 | G24: =IF($D24="","",IFERROR($D24*E24,"")) | H24: =IF($D24="","",IFERROR($D24*F24,""))
A25: 17 | B25: Attendance management and integrating of HRMS and customise reporting | C25: Nos | D25: RO | E25: 120000 | F25: 18000 | G25: =IF($D25="","",IFERROR($D25*E25,"")) | H25: =IF($D25="","",IFERROR($D25*F25,""))
B26: Access Control Cabling - Control and Communication Cable | G26: =IF($D26="","",IFERROR($D26*E26,"")) | H26: =IF($D26="","",IFERROR($D26*F26,""))
A27: 18 | B27: 8 Core .75 sq MM Shielded unarmoured Cable, as per the survey done, Rate shall include required accessories, tools etc., complete as required. | C27: Mtr | D27: 400 | E27: 118 | F27: 22 | G27: =IF($D27="","",IFERROR($D27*E27,"")) -> 47200 | H27: =IF($D27="","",IFERROR($D27*F27,"")) -> 8800
A28: 19 | B28: 4 Core .75 sq MM unarmoured Cable, as per the survey done, Rate shall include required accessories, tools etc., complete as required. | C28: Mtr | D28: 250 | E28: 94 | F28: 24 | G28: =IF($D28="","",IFERROR($D28*E28,"")) -> 23500 | H28: =IF($D28="","",IFERROR($D28*F28,"")) -> 6000
A29: 20 | B29: 2 Core .75 sq MM unarmoured Cable, as per the survey done, Rate shall include required accessories, tools etc., complete as required. | C29: Mtr | D29: 200 | E29: 54 | F29: 24 | G29: =IF($D29="","",IFERROR($D29*E29,"")) -> 10800 | H29: =IF($D29="","",IFERROR($D29*F29,"")) -> 4800
A30: 21 | B30: 4C 1 sq mm shielded cable (for Controller ) | C30: Mtr | D30: 150 | E30: 96 | F30: 24 | G30: =IF($D30="","",IFERROR($D30*E30,"")) -> 14400 | H30: =IF($D30="","",IFERROR($D30*F30,"")) -> 3600
A31: 22 | B31: 4C 1 sq mm Unshielded cable | C31: Mtr | D31: 150 | E31: 78 | F31: 24 | G31: =IF($D31="","",IFERROR($D31*E31,"")) -> 11700 | H31: =IF($D31="","",IFERROR($D31*F31,"")) -> 3600
A32: 23 | B32: CAT6A Cable, Rate shall include required accessories, tools etc., complete as required. | C32: Mtr | D32: 500 | E32: 72 | F32: 14 | G32: =IF($D32="","",IFERROR($D32*E32,"")) -> 36000 | H32: =IF($D32="","",IFERROR($D32*F32,"")) -> 7000
A33: 24 | B33: 6 core Multi mode optical fiber | C33: Mtr | D33: RO | E33: 77 | F33: 30 | G33: =IF($D33="","",IFERROR($D33*E33,"")) | H33: =IF($D33="","",IFERROR($D33*F33,""))
A34: 25 | B34: 25 MM PVC Conduit with required accessories, as per the survey done, Rate shall include required accessories, tools etc., complete as required. | C34: Mtr | D34: 450 | E34: 50 | F34: 24 | G34: =IF($D34="","",IFERROR($D34*E34,"")) -> 22500 | H34: =IF($D34="","",IFERROR($D34*F34,"")) -> 10800
A35: 26 | B35: 20 MM PVC Conduit with required accessories, as per the survey done, Rate shall include required accessories, tools etc., complete as required. | C35: Mtr | E35: 34 | F35: 18 | G35: =IF($D35="","",IFERROR($D35*E35,"")) | H35: =IF($D35="","",IFERROR($D35*F35,""))
A36: 27 | B36: Supply and installation of Panic push Bar with lock and leaver along integration with ACS and mini hooter / Buzzer | C36: Nos | D36: 0 | E36: 13800 | F36: 3000 | G36: =IF($D36="","",IFERROR($D36*E36,"")) -> 0 | H36: =IF($D36="","",IFERROR($D36*F36,"")) -> 0
A37: 28 | B37: Supervision, Programming, Testing & Commissioning, documentation, training. | C37: Lot | D37: 0 | E37: 0 | F37: 54000 | G37: =IF($D37="","",IFERROR($D37*E37,"")) -> 0 | H37: =IF($D37="","",IFERROR($D37*F37,"")) -> 0
B39: TOTAL AMOUNT | G39: =SUM(G7:G37) -> 166100 | H39: =SUM(H7:H37) -> 44600 | I39: =G39+H39 -> 210700
B40: TAX
B41: GRAND TOTAL - SUPPLY + INSTALLATION +TAXES
B43: Exclusions:
B44: 1. Active Components & Servers, Switches, Rack
B45: 2. Server: Dell PowerEdge R530
B46: 3. Ceiling Raceway
B47: 4. Intrusion system
B49: MAKES: BOSCH ,HONEYWELL,JCI

Sheet ACS - Indegene
A1: ESTIMATION FOR ACS
A2: Project: Indegene_3F | H2: Date: | I2: 11.11.2025
A3: Location: | H3: Revision | I3: R0
A4: Project no:
A5: S.no | B5: Description | C5: Unit | D5: Qty | E5: Rate | G5: Amount | I5: Remarks
E6: Supply | F6: Installation | G6: Supply | H6: Installation
A7: 1 | B7: Supply and installation of UL, CE approved Access Controller - Smart card reader interfaces for 2 door controller 2 readers, Network connection to the host system and Compact Flash, RS485, RS232 or Ethernet connectivity, 20,000 cardholders data & up to 100,000 transaction detail storage | C7: Nos | D7: 16 | G7: =IF($D7="","",IFERROR($D7*E7,"")) -> 0 | H7: =IF($D7="","",IFERROR($D7*F7,"")) -> 0 | I7: Under client scope
A8: 2 | B8: Supply and installation of Access Door Controller housing shall be in accordance with UL guidelines and is used for securely mounting and housing the Access Controller, extensions and the power supplies, | C8: Nos | D8: =1 -> 1 | G8: =IF($D8="","",IFERROR($D8*E8,"")) -> 0 | H8: =IF($D8="","",IFERROR($D8*F8,"")) -> 0 | I8: Centrallised
A9: 3 | B9: Supply and installation of Power supply with battery charger for ACCESS DOOR CONTROLLER Shall be with Selectable 12 VDC or 24 VDC voltage output Overvoltage protection Regulates battery charging voltage The product is classified in accordance with the following standards: • EN 55022 Class B • EN 55024 • IEC / UL / EN 60950 & CSA (product safety) • CE The Power supply can be mounted on rails and installed in the housing | C9: Nos | D9: =1 -> 1 | G9: =IF($D9="","",IFERROR($D9*E9,"")) -> 0 | H9: =IF($D9="","",IFERROR($D9*F9,"")) -> 0 | I9: Under client scope
A10: 4 | B10: Supply and installation of Smart card readers based on RFID technology, along with Back Plate including all fixing accessories. Rate shall include required accessories, tools, etc., complete as required. | C10: Nos | D10: 12 | G10: =IF($D10="","",IFERROR($D10*E10,"")) -> 0 | H10: =IF($D10="","",IFERROR($D10*F10,"")) -> 0
A11: 5 | B11: Supply and installation of Smart card readers based on RFID technology with Keypad, with Back Plate including all fixing accessories. Rate shall include required accessories, tools, etc., complete as required. | C11: Nos | D11: 0 | G11: =IF($D11="","",IFERROR($D11*E11,"")) -> 0 | H11: =IF($D11="","",IFERROR($D11*F11,"")) -> 0
A12: 6 | B12: Supply and installation of Biometric unit consisting of Biometric Scanner and Smart card readers based on RFID technology, along with Back Plate including all fixing accessories. Rate shall include required accessories, tools, etc., complete as required. | C12: Nos | D12: 0 | G12: =IF($D12="","",IFERROR($D12*E12,"")) -> 0 | H12: =IF($D12="","",IFERROR($D12*F12,"")) -> 0
A13: 7 | B13: Supply and installation of Biometric unit consisting of Biometric Scanner and Smart card readers based on RFID technology with Keypad, with Back Plate including all fixing accessories. Rate shall include required accessories, tools, etc., complete as required. | C13: Nos | D13: =4 -> 4 | G13: =IF($D13="","",IFERROR($D13*E13,"")) -> 0 | H13: =IF($D13="","",IFERROR($D13*F13,"")) -> 0
A14: 8 | B14: Supply and installation of Smart Access Card (16k bit with 2 application areas) with print as per client requirement | C14: Nos | D14: RO | G14: =IF($D14="","",IFERROR($D14*E14,"")) | H14: =IF($D14="","",IFERROR($D14*F14,""))
A15: 9 | B15: Supply and installation of Single Leaf 600 Lbs Magnetic Lock with required mounting accessories, Rate shall include required accessories, tools, etc., complete as required. | C15: Nos | D15: 14 | G15: =IF($D15="","",IFERROR($D15*E15,"")) -> 0 | H15: =IF($D15="","",IFERROR($D15*F15,"")) -> 0
A16: 10 | B16: Supply and installation of Double Leaf Magnetic Lock with required mounting accessories, Rate shall include required accessories, tools, etc., complete as required. | C16: Nos | D16: =2 -> 2 | G16: =IF($D16="","",IFERROR($D16*E16,"")) -> 0 | H16: =IF($D16="","",IFERROR($D16*F16,"")) -> 0
A17: 11 | B17: Supply and installation of Break Glass Unit, Rate shall include required accessories,MS junction box, tools etc., complete as required. | C17: Nos | D17: 16 | G17: =IF($D17="","",IFERROR($D17*E17,"")) -> 0 | H17: =IF($D17="","",IFERROR($D17*F17,"")) -> 0
A18: 12 | B18: Supply and installation of Exit Push Button, Rate shall include required accessories, tools etc., complete as required. | C18: Nos | D18: 16 | G18: =IF($D18="","",IFERROR($D18*E18,"")) -> 0 | H18: =IF($D18="","",IFERROR($D18*F18,"")) -> 0
A19: 13 | B19: Supply and installation of Door Buzzer, Rate shall include required accessories, tools etc., complete as required. | C19: Nos | D19: =4 -> 4 | G19: =IF($D19="","",IFERROR($D19*E19,"")) -> 0 | H19: =IF($D19="","",IFERROR($D19*F19,"")) -> 0
A20: 14 | B20: ACS software with lisences to manage 200 card holder data including database management software like SQL also integarate with life saftey equipments like fire system : The ACS shall be modular, networked access control system having centralized architecture, capable of handling large corporation with multiple remote sites. The system control at the central computer location shall be under a single software program control, shall provide full integration of all components, and shall be alterable at any time, depending upon the facility requirements. The system shall include 100+ door licence and shall include 200 card holders. The ACS must provide a web server-based solution. Only Internet Explorer is required for a workstation to access the ACS login server. The system server shall be use latest edition of Windows Server 2012 R2 and Client shall support Windows 10 shall include network capability with the TCP/IP data communications network protocol and hardware. GUI shall support location tree display structure to allow easy selection of locations and sub-locations. The location tree display structure should have no limits in the number of levels or sub-levels. Shall support the integration of the Video Surveillance System interfacing shall be OPC compliant to provide direct import of existing video sub-system configuration. Audit trail for master record operations: The access control management must provide an audit trail for changes on cardholder master records as well as changes on access permissions. The audit trail must log at least the following operations. | C20: Nos | D20: 1 | G20: =IF($D20="","",IFERROR($D20*E20,"")) -> 0 | H20: =IF($D20="","",IFERROR($D20*F20,"")) -> 0 | I20: Client to Confirm
B21: - create, delete a cardholder master record - change cardholder master record content, e.g. name, address - change cardholder access rights - create, delete an access permission - change access permission content, e.g. time profile,
B22: Hold up / Door hold up alarm: to provide the opening beyond set time to give pop indication and also CCTV to record the event | G22: =IF($D22="","",IFERROR($D22*E22,"")) | H22: =IF($D22="","",IFERROR($D22*F22,""))
A23: 15 | B23: Visitor Management system | C23: Nos | D23: 1 | G23: =IF($D23="","",IFERROR($D23*E23,"")) -> 0 | H23: =IF($D23="","",IFERROR($D23*F23,"")) -> 0
A24: 16 | B24: Client PC with i5 Processor, 8GB RAM, 1TB HDD, Keyboard, mouse, NVIDIA graphics card with monitor , Windows 10 operating system CPU, with 19" Monitor alwong with webcam and printer | C24: Nos | D24: 1 | G24: =IF($D24="","",IFERROR($D24*E24,"")) -> 0 | H24: =IF($D24="","",IFERROR($D24*F24,"")) -> 0
A25: 17 | B25: Attendance management and integrating of HRMS and customise reporting | C25: Nos | D25: 0 | G25: =IF($D25="","",IFERROR($D25*E25,"")) -> 0 | H25: =IF($D25="","",IFERROR($D25*F25,"")) -> 0 | I25: Client to Confirm
B26: Access Control Cabling - Control and Communication Cable | G26: =IF($D26="","",IFERROR($D26*E26,"")) | H26: =IF($D26="","",IFERROR($D26*F26,""))
A27: 18 | B27: 8 Core .75 sq MM Shielded unarmoured Cable, as per the survey done, Rate shall include required accessories, tools etc., complete as required. | C27: Mtr | D27: =400*0 -> 0 | G27: =IF($D27="","",IFERROR($D27*E27,"")) -> 0 | H27: =IF($D27="","",IFERROR($D27*F27,"")) -> 0
A28: 19 | B28: 4 Core .75 sq MM unarmoured Cable, as per the survey done, Rate shall include required accessories, tools etc., complete as required. | C28: Mtr | D28: =250*0 -> 0 | G28: =IF($D28="","",IFERROR($D28*E28,"")) -> 0 | H28: =IF($D28="","",IFERROR($D28*F28,"")) -> 0
A29: 20 | B29: 2 Core .75 sq MM unarmoured Cable, as per the survey done, Rate shall include required accessories, tools etc., complete as required. | C29: Mtr | D29: =450*0 -> 0 | G29: =IF($D29="","",IFERROR($D29*E29,"")) -> 0 | H29: =IF($D29="","",IFERROR($D29*F29,"")) -> 0
A30: 21 | B30: 4C 1 sq mm shielded cable (for Controller ) | C30: Mtr | D30: =300*0 -> 0 | G30: =IF($D30="","",IFERROR($D30*E30,"")) -> 0 | H30: =IF($D30="","",IFERROR($D30*F30,"")) -> 0
A31: 22 | B31: 4C 1 sq mm Unshielded cable | C31: Mtr | D31: =150*0 -> 0 | G31: =IF($D31="","",IFERROR($D31*E31,"")) -> 0 | H31: =IF($D31="","",IFERROR($D31*F31,"")) -> 0
A32: 23 | B32: CAT6A Cable, Rate shall include required accessories, tools etc., complete as required. | C32: Mtr | D32: =300*0 -> 0 | G32: =IF($D32="","",IFERROR($D32*E32,"")) -> 0 | H32: =IF($D32="","",IFERROR($D32*F32,"")) -> 0
A33: 24 | B33: 6 core Multi mode optical fiber | C33: Mtr | D33: RO | G33: =IF($D33="","",IFERROR($D33*E33,"")) | H33: =IF($D33="","",IFERROR($D33*F33,""))
A34: 25 | B34: 25 MM PVC Conduit with required accessories, as per the survey done, Rate shall include required accessories, tools etc., complete as required. | C34: Mtr | D34: =350*0 -> 0 | G34: =IF($D34="","",IFERROR($D34*E34,"")) -> 0 | H34: =IF($D34="","",IFERROR($D34*F34,"")) -> 0
A35: 26 | B35: 20 MM PVC Conduit with required accessories, as per the survey done, Rate shall include required accessories, tools etc., complete as required. | C35: Mtr | D35: =200*0 -> 0 | G35: =IF($D35="","",IFERROR($D35*E35,"")) -> 0 | H35: =IF($D35="","",IFERROR($D35*F35,"")) -> 0
A36: 27 | B36: Supply and installation of Panic push Bar with lock and leaver along integration with ACS and mini hooter / Buzzer | C36: Nos | D36: 0 | G36: =IF($D36="","",IFERROR($D36*E36,"")) -> 0 | H36: =IF($D36="","",IFERROR($D36*F36,"")) -> 0
A37: 28 | B37: Supervision, Programming, Testing & Commissioning, documentation, training. | C37: Lot | D37: 1 | G37: =IF($D37="","",IFERROR($D37*E37,"")) -> 0 | H37: =IF($D37="","",IFERROR($D37*F37,"")) -> 0
B39: TOTAL AMOUNT | G39: =SUM(G7:G37) -> 0 | H39: =SUM(H7:H37) -> 0
B40: GRAND TOTAL - SUPPLY + INSTALLATION | H40: =H39+G39 -> 0
B42: Exclusions:
B43: 1. Active Components & Servers, Switches, Rack
B44: 2. Server: Dell PowerEdge R530
B45: 3. Ceiling Raceway
B46: 4. Intrusion system
B48: MAKES: BOSCH ,HONEYWELL,JCI

Sheet LMS 
A1: Project: Indegene_3F | J1: Date : 27.01.2026
A2: LMS Works | J2: Rev No : R1
A5: SI NO | B5: DESCRIPTION | C5: IMAGE | D5: UNIT | E5: QTY | F5: TOTAL | G5: RATE | I5: AMOUNT
G6: SUPPLY | H6: INSTALLATION | I6: SUPPLY | J6: INSTALLATION
A7: 1 | B7: SITC of POWPAK DALI DIMMING module with 32 fixtures fixtures , radio frequency (RF) control electronic ballasts.. Communication utilizing Lutron Clear Connect RF technology with Occ sensor/DL sensor/Keypads etc RMNS-DAL-32-SZ | D7: Nos. | E7: 22 | F7: =E7 -> 22 | G7: 18600 | H7: 960 | I7: =F7*G7 -> 409200 | J7: =F7*H7 -> 21120
A8: 2 | B8: SITC of POWPAK DALI DIMMING module with 4 fixtures fixtures , radio frequency (RF) control electronic ballasts.. Communication utilizing Lutron Clear Connect RF technology with Occ sensor/DL sensor/Keypads etc RMNS-DAL-4-SZ | D8: Nos. | E8: 12 | F8: =E8 -> 12 | G8: 18600 | H8: 960 | I8: =F8*G8 -> 223200 | J8: =F8*H8 -> 11520
A9: 3 | B9: SITC of Wireless Ceiling mounted Occupancy Sensor with radio frequency and connect with single channel DALI module / relay module wirelessly. The sensors should not interfere with any other wireless devices. The device should be with battery life 8-10 years and dedicated frequency less than 1 GHz. Similar to Lutron LRF5 OCR2B WH / Equivalent | D9: Nos. | E9: 22 | F9: =E9 -> 22 | G9: 8760 | H9: 600 | I9: =F9*G9 -> 192720 | J9: =F9*H9 -> 13200
A10: 4 | B10: SITC of Wireless personlised control Keypad with a WPC approved frequency of 865 Mhz, 3 Button with raise and lower for bigger rooms, with faceplate,mounts on glass surfaces also, with guranteed 10 year battery life along with necessary fixing arrangements and programming at site etc, complete as required similar to Lutron PN2 3BRL TAW +LPFP S1 TAW | D10: Nos. | E10: 5 | F10: =E10 -> 5 | G10: 16200 | H10: 600 | I10: =F10*G10 -> 81000 | J10: =F10*H10 -> 3000
A11: 5 | B11: SITC of Wireless personalized control Keypad with a WPC approved frequency of 865 MHz, 6 Button with raise and lower for bigger rooms, with face plate, mounts on glass surfaces also, with guaranteed 10 year battery life along with necessary fixing arrangements and programming at site etc, complete as required similar to Lutron PN2 4B TAW +PN2 2BRL TAW +LPFP S2 TAW | D11: Nos. | E11: 4 | F11: =E11 -> 4 | G11: 24600 | H11: 600 | I11: =F11*G11 -> 98400 | J11: =F11*H11 -> 2400
A12: 6 | B12: Complete commissioning of the system | D12: Nos. | E12: 1 | F12: =E12 -> 1 | G12: 60000 | H12: 0 | I12: =F12*G12 -> 60000 | J12: =F12*H12 -> 0
I13: =SUM(I7:I12) -> 1064520 | J13: =SUM(J7:J12) -> 51240
H14: GST extra

Sheet Sprinkler
A1: Project : | B1: Indegene_3rd Floor
A2: Subject : | B2: Fire Alarm, Extinguisher Fire Signage,Fire Sprinkler and PA System
A3: Rev : | B3: R1 | H3: 27.01.2026
A4: S.L | B4: Description | C4: Unit | D4: Total Qty | E4: Supply Rate | F4: Installation Rate | G4: Total Amount | H4: Remarks
A8: 4 | B8: FIRE SPRINKLER SYSTEM
A9: 4.1 | B9: Supply, installation, testing and commissioning of G.I Heavy grade piping as per IS: 1239/3589 GI Forged Threaded GI forged socket welded & 65mm and above Seamless schedule 40) with necessary fittings such as tees, elbows,union,flanges, bends, rubber gaskets, reducers, GI nut bolt, washer etc. The pipes being suspended from ceilings by using support with clamps, hangers using anchor fastners upto 65 mm & above 80 mm pipe should be support with galvanized channel supports complete Rate quoted shall include painting with one coat of zinc cromet primer & 2 coats of synthetic enamel PO red paint and for painting of pipe & brackets and clamps as per IS-5 for above ground piping as per the NBC / IS standards and local fire service department requirement complete including supply and installation of G.I. Rods, clamps and , fasteners etc. All supports shall be hot dip galvanized in the range of DFT of micron 80 to 90 micron with 7 tank process, hot dip galvanizing shall be confirming to IS:2629/2633/4759/6745. Anchor fastners to be used of chemical type only where pipe supports to be taken from brick/block work.
A10: a | B10: 150mm nominal dia | C10: Rmt | E10: 3480 | F10: 720 | G10: =(E10+F10)*D10 -> 0
A11: b | B11: 100mm nominal dia | C11: Rmt | D11: 10 | E11: 3150 | F11: 660 | G11: =(E11+F11)*D11 -> 38100
A12: c | B12: 80mm nominal dia | C12: Rmt | E12: 2850 | F12: 586 | G12: =(E12+F12)*D12 -> 0
A13: d | B13: 65mm nominal dia | C13: Rmt | E13: 1650 | F13: 390 | G13: =(E13+F13)*D13 -> 0
A14: e | B14: 50mm nominal dia | C14: Rmt | E14: 1426 | F14: 526 | G14: =(E14+F14)*D14 -> 0
A15: f | B15: 40mm nominal dia | C15: Rmt | E15: 1140 | F15: 436 | G15: =(E15+F15)*D15 -> 0
A16: g | B16: 32mm nominal dia | C16: Rmt | D16: 20 | E16: 893 | F16: 286 | G16: =(E16+F16)*D16 -> 23580
A17: h | B17: 25mm nominal dia | C17: Rmt | D17: 100 | E17: 676 | F17: 270 | G17: =(E17+F17)*D17 -> 94600
A19: 4.2 | B19: Supplying, installing, testing and commissioning conventional Standard Response Sprinkler quartzoid bulb type with 15mm screwed end connection of 68 deg. C. temperature rating, K-Factor =5.6 GPM/psi½ (80.6 LPM/bar½) and orifice shall not be less than 6mm. Sprinklers shall be UL Listed / BIS approved with Chrome finished.
A20: a | B20: Pendent Sprinkler | C20: Nos | D20: 312 | E20: 484 | F20: 226 | G20: =(E20+F20)*D20 -> 221520
A21: b | B21: Upright Sprinkler | C21: Nos | D21: 184 | E21: 533 | F21: 226 | G21: =(E21+F21)*D21 -> 139656
A22: c | B22: Concealed Sprinkler | C22: Nos | D22: 35 | E22: 1560 | F22: 360 | G22: =(E22+F22)*D22 -> 67200
A23: 4.3 | B23: Stainless steel corrugated flexible pipe(hose) for dropping sprinklers below false ceiling, pipe shall be 16 bar pressure rating and 1500 mm long, 25 mm dia with union / reducer collar, clamps etc. as required. | C23: Nos | D23: =D20+D22+100 -> 447 | E23: 3180 | F23: 150 | G23: =(E23+F23)*D23 -> 1488510
A25: 4.4 | B25: Supplying, Installing, testing and commissioning CI butterfly valves as per BS 5155 ( PN 16) slim seal standared lever operated type with required flanges, nuts, bolts etc. complete.
B26: 150mm dia | C26: Nos | D26: 2 | E26: 18000 | F26: 1200 | G26: =(E26+F26)*D26 -> 38400
B27: 100mm dia | C27: Nos | D27: 0 | E27: 15000 | F27: 1200 | G27: =(E27+F27)*D27 -> 0
A28: 4.5 | B28: Supplying, Installing, testing and commissioning flow switch installed on the sprinkler main distribution line connected to the Fire Alarm panel. | C28: Nos | D28: 1 | E28: 12600 | F28: 900 | G28: =(E28+F28)*D28 -> 13500
A29: 4.6 | B29: Sprinkler Pipe Line Modifications based on the Proposed Interior Fit Out Plan | C29: Lot | D29: 1 | E29: 0 | F29: 240000 | G29: =(E29+F29)*D29 -> 240000
A30: 4.7 | B30: Removing, Relocating of existing srinklers , Spinkler Pipes , and all accessories complete set | C30: Nos | D30: 1 | E30: 0 | F30: 60000 | G30: =(E30+F30)*D30 -> 60000
A31: 4.8 | B31: Testing and Commissioning of New Sprinkler Line | C31: Lot | D31: 0 | E31: 0 | F31: 60000 | G31: =(E31+F31)*D31 -> 0
B33: Total Amount Section-4 ( Fire Sprinkler System ) | G33: =SUM(G8:G32) -> 2425066
B34: GRAND TOTAL - SECTION- 1+2+3+4 ( Excl GST) - [A] | G34: =G33 -> 2425066
B35: GST 18% | G35: =G34*0.18 -> 436511.88
B36: Total Amount ( Incl GST) -[B] | G36: =G34+G35 -> 2861577.9

Sheet Fire & Life Safety -Indegene
A1: Project : | B1: Indegene_3rd Floor
A2: Subject : | B2: Fire Alarm, Extinguisher Fire Signage,Fire Sprinkler and PA System
A3: Rev : | B3: R1 | H3: 27.01.2026
A4: S.L | B4: Description | C4: Unit | D4: Total Qty | E4: Supply Rate | F4: Installation Rate | G4: Total Amount | H4: Remarks
A5: 1 | B5: FIRE Alarm System Works
A6: 1.1 | B6: Supply, Installation, Testing & Comissioning of Analogue Addressable Multi Sensor detector. Shall be supplied with Detector base, Junction box and other accessories as required and Detectors shall be UL Listed or EN Approved
A7: a | B7: Multi Sensor detector - True Ceiling | C7: Nos | D7: 145 | G7: =(E7+F7)*D7 -> 0
A8: b | B8: Multi Sensor detector - Below False Ceiling | C8: Nos | D8: 90 | G8: =(E8+F8)*D8 -> 0
A9: 1.2 | B9: Supply, Installation, Testing & Comissioning of Analogue Addressable Rate of Rise Heat sensor detector. Shall be supplied with standard base and fixing accessories. Detectors shall be UL listed or EN Approved | C9: Nos | D9: 7 | G9: =(E9+F9)*D9 -> 0
A10: 1.3 | B10: Supply, Installation, Testing & Comissioning of Analogue Addressable Duct detector. Shall be supplied with standard base and fixing accessories. Detectors shall be UL listed or EN Approved | C10: Nos | D10: 0 | G10: =(E10+F10)*D10 -> 0
A11: 1.4 | B11: Supply, Installation, Testing & Comissioning of Response indicator for all detectors located above false ceiling | C11: Nos | D11: 90 | G11: =(E11+F11)*D11 -> 0
A12: 1.5 | B12: Supply, installation, testing & commissioning of Hooter Cum Strobe Wall mounted type with back box rated at 84 dBA @ 3m for Audible annunciation and 115cd flashintg at 1 Hz for visual indication. Hooter cum strobe with all necessary accesories complete, shall be UL listed or EN Approved | C12: Nos | D12: 7 | G12: =(E12+F12)*D12 -> 0
A13: 1.6 | B13: Supply, installation, testing & commissioning of Addressable break glass type Manual Call Point with back box. The device shall have an LED which shall blink in normal state & get steady on activation to monitor the heath status of the device. | C13: Nos | D13: 7 | G13: =(E13+F13)*D13 -> 0
A14: 1.7 | B14: Supply, Installation, Testing & Comissioning of Analogue Addressable Control module shall be capable of providing DPDT contact rated at 24v DC, 2A. Shall be supplied with mounting plate/base from OEM with necessary accessories to complete the installation. Device shall be UL Listed or EN Approved (for hooter cum strobe)
A15: a | B15: For Hooter cum Strobe | C15: Nos | D15: 7 | G15: =(E15+F15)*D15 -> 0
A16: 1.8 | B16: Supplying, installing, testing and commissioning of 5 Amps External Power Supply Unit for Hooters (if required) along with other necessary accessories to be considered | C16: Nos | D16: 1 | G16: =(E16+F16)*D16 -> 0
A17: 1.9 | B17: Supply, Installation, Testing & Comissioning of Analogue Addressable Control Relay module shall be capable of providing DPDTcontact rated at 24v DC, 2A. Shall be supplied with mounting plate/base from OEM with necessary accessories to complete the installation. Device shall be UL Listed or EN Approved
A18: a | B18: 3rd Party Integeration | C18: Nos | D18: 10 | G18: =(E18+F18)*D18 -> 0
A19: 1.10 | B19: Supply, Installation, Testing & Comissioning of Analogue Addressable Monitor module for monitoring the potential free contacts, field devices & shall be capable of providing DPDT contact rated at 24v DC, 2A. Shall be supplied with mounting plate/base from OEM with necessary accessories to complete the installation. Device shall be UL Listed or EN Approved | C19: Nos | D19: 6 | G19: =(E19+F19)*D19 -> 0
A20: 1.11 | B20: Supply, Installation, Testing & Comissioning of Analogue Addressable Fault isolator module with mounting plate / base from OEM, capable of monitoring shorted loop circuit and automatically restore communications when shorted conditions are corrected. Necessary accessories shall be considered complete for installation. The device shall be UL Listed or EN Approved | C20: Nos | D20: 15 | G20: =(E20+F20)*D20 -> 0
A21: 1.12 | B21: Supply and laying of PVC insulated, 2C x 1.5sq.mm shielded armored FRLS copper cable (RED COLUR) including cable glands,clamps to be provided at maximum 1mtr intervals and all fixing accessories where ever required complete with end terminations at both sides. | C21: Rmt | D21: 3200 | G21: =(E21+F21)*D21 -> 0
A22: 1.13 | B22: Supplying, installing, testing and commissioning approved make Microprocessor based Networkable Addressable Fire Alarm Control Panel .Inbuilt USB 2.0 Port for upload and download the Configuration tools, Two inbuilt programmable inputs, Two inbuilt NAC's, and Three Programmable Relays, The panel should be equipped with sufficient numbers of loops considering 20% spare capacity. Each loop shall have 20% spare. Loops shall be decided by SI/OEM based on the make of panel. 240 volts AC power supply, automatic battery charger, 24 volts sealed lead acid batteries sufficient for 24 hours normal working and 30 mins in alarm condition with the charging capacity of 200AH. Quoted rate shall include supply of hardware for progamming the panel with all necessary licence. Panel shall have option to mount Modbus over IP protocol for future integration with BMS. Designed to meet UL Listed or EN Approval, Lockable cabinet with vision panel and louvers shall be considered.
A23: a | B23: 2 Loop Analogue addressable fire alarm panel as per the above specifications. | C23: Nos | D23: 0 | G23: =(E23+F23)*D23 -> 0
A24: b | B24: 4 Loop Analogue addressable fire alarm panel as per the above specifications. | C24: Nos | D24: 1 | G24: =(E24+F24)*D24 -> 0
A25: c | B25: 6 Loop Analogue addressable fire alarm panel as per the above specifications. | C25: Nos | D25: 0 | G25: =(E25+F25)*D25 -> 0
A26: 1.14 | B26: Supply, Installation, Testing & Comissioning of 2 Loop cards in to the panel | C26: Nos | D26: 0 | G26: =(E26+F26)*D26 -> 0
A27: 1.15 | B27: Supply, Installation, Testing & Comissioning of Network cards in to the panel Network card 3X-NET | C27: Nos | D27: 0 | G27: =(E27+F27)*D27 -> 0
A28: 1.16 | B28: Active Repeater Panel with minimum 256 character display for monitoring & controlling other Panels on the network loop with Power supply. Peer To Peer Networked with main panel, such that the status of the entire system shall be available on individual Annunciator. | C28: Nos | D28: 0 | G28: =(E28+F28)*D28 -> 0
B30: Total Amount - Section-1 (FAS) | G30: =SUM(G5:G28) -> 0
A32: 2 | B32: FIRE EXTINGUISHERS
A33: 2.1 | B33: Supply, Installation & Commissioining of 4.5Kgs CO2 type fire extinguisher Capacity, with initial CO2 gas charged/filled in brand new seamless cylinder with powder coated finish, 1mtr High pressure wire braided discharge hose pipe & Horn, Wheel type valve, wall mounting bracket/floor stand, carrying/holding handle, etc. complete, confirming to latest IS:15683, IS 7285, IS 3224, CCOE & PESO Approved, (Electrical room, AHU Room Battery room & Ups room) | C33: Nos | D33: 50 | G33: =(E33+F33)*D33 -> 0
A34: 2.2 | B34: Supply, Installation & Commissioining of 4 Kgs ABC powder type fire extinguisher Capacity, MAP 90%, with initial filling in brand new seamless cylinder with internally epoxy polyster & externally pure poleyster powder coated, fitted with SS union, EPDM Flexible Discharge hose pipe, stored pressure type, Pressure gauge indicating the pressure inside cylinder, Squeeze grip type open/close lever, tamper proof seal, wall mounting bracket/Floor Stand Bracket etc. complete, confirming to latest IS:15683 code, CCOE & PESO Approved with ISI Mark. | C34: Nos | D34: 1 | G34: =(E34+F34)*D34 -> 0
A35: 2.3 | B35: Supply, Installation, Testing & Commissioning of Stand Alone Automatic Ceiling Suspended Clean agent (FE36/FM200) Stored Pressure Automatic Modular halon free fire extinguisher of 10 Kgs. Capacity, with initial filling in brand new cylinder with powder coated finish, all accessories like solenoid valve, 68Deg C sprinkler bulb type to discharge gas within 10-15seconds, ceiling mounting bracket, complete, (In UPS/Battery room) | C35: Nos | D35: 0 | G35: =(E35+F35)*D35 -> 0
A36: 2.4 | B36: Supply, Installation, Testing & Commissioning of Stand Alone Automatic Ceiling Suspended Clean agent (FE36/FM200) Stored Pressure Automatic Modular halon free fire extinguisher of 05 Kgs. Capacity, with initial filling in brand new cylinder with powder coated finish, all accessories like solenoid valve, 68Deg C sprinkler bulb type to discharge gas within 10-15seconds, ceiling mounting bracket, complete, (In Server Room) | C36: Nos | D36: 25 | G36: =(E36+F36)*D36 -> 0
A37: 2.5 | B37: SIGNAGES (FLOOR IDENTIFICATION & FIRE ORDER BOARD ONLY)
A38: a | B38: Extinguisher identification signage triangle type at each extinguisher, indicating the extinguisher symbol, board size shall be 6in. x 12 in. with contrasting colour from back ground. Shall be fixed at height as per site condition but not less that 1.2mtrs | C38: Nos | D38: =(D33+D34) -> 51 | G38: =(E38+F38)*D38 -> 0
A39: b | B39: Supply, installation of EMERGENCY EVACUATION PLAN, color which needs to be displayed onto a GLASS frame which are Self Glow type. Size should be A2. (samples to be shown before execution) to be putup showed location in drawings | C39: Nos | D39: =5 -> 5 | G39: =(E39+F39)*D39 -> 0
A40: c | B40: Supply & Installation of the sign boards with integral battery capacity of 3 hours & bicoloured LED states indicator, photoluminescent based glow-in-the-dark, complete with necessary SS string, hooks & rings for mounting at required height as necessary at site. SAMPLES SHALL BE SUBMITTED TO PMC/CLIENT/CONSULTANT AND APPROVAL SHALL BE SEEKED BEFORE PROCURING/INSTALLING THE SAME Following properties should be part of the signages: 1. Glow visible should be more than 24 hours in total darkness. 2. Fungistatic 3. Non-toxic 4. on-radioactive 5. Contains no lead or Phosphorus 6. No health or environmental problem 7. Suitable for indoor use only
A41: c.1 | B41: Supply, Installation, Testing & Commissioning of Fire Exit Signage visible from 20 mtrs (150x400mm) both sides, Available in Single Left, Single Right, Up, Down, Dual side arrow, Double arrow, Double side arrow with Exit or man symbol, etc.. With necessary 3mtr length Power cable and plug to get charged in electrical socket (180 Min Backup) (Make -Proloite /Equivalent) | C41: Nos | D41: =35 -> 35 | G41: =(E41+F41)*D41 -> 0
A42: c.2 | B42: Supply, Installation, Testing & Commissioning of Exit Signage visible from 20 mtrs (150x400mm) both sides, With necessary 3mtr length Power cable and plug to get charged in electrical socket (180 Min Backup) (Make -Proloite /Equivalent) | C42: Nos | D42: =4 -> 4 | G42: =(E42+F42)*D42 -> 0
B44: Total Amount -Section-2 (FES) | G44: =SUM(G32:G43) -> 0
A46: 3 | B46: PA/MUSIC SYSTEM
A47: 3.1 | B47: Supplying, installing, testing and commissioning of Speakers with built in line matching transformer, grill flush mounting type.
A48: a | B48: 6 Watts ceiling recessed mounted type Speakers (Tap 6W,3W,1.5W) | C48: Nos | D48: 68 | G48: =(E48+F48)*D48 -> 0
A49: b | B49: 6 Watts Surface mounted type Speakers (Tap 6W,3W,1.5W) | C49: Nos | D49: 30 | G49: =(E49+F49)*D49 -> 0
A50: c | B50: 6 Watts Wall mounted type Speakers (Tap 6W,3W,1.5W) | C50: Nos | D50: 10 | G50: =(E50+F50)*D50 -> 0
A51: 3.2 | B51: System Controller complete with Microprocessor based following No of Zone Call Station, Stem Type Microphone, Dual Tone Control for Speech & Music, tone generator for 5 pre-recorded message, priority modules, 2 mm thick CRCA Sheet Powder Coated Rack (to Amplifiers, tone generators, Zone selectors, priority modules etc.,) The controller shall have in-built messages for fire alert and evacuation which shall be played based on the relay status. In conjunction with an interconnected amplifier, the controller shall be able to provide BGM in some zones and Message in other zones simultaneously. In case of alarm inputs, the alarm messages would take priority over the BGM.
A52: a | B52: 4 Zone Call Station | C52: Nos | D52: 1 | G52: =(E52+F52)*D52 -> 0
A53: b | B53: 6 Zone Call Station | C53: Nos | D53: 0 | G53: =(E53+F53)*D53 -> 0
A54: c | B54: 8 Zone Call Station | C54: Nos | D54: 0 | G54: =(E54+F54)*D54 -> 0
A55: 3.3 | B55: SITC of Booster Amplifiers with 230 VAC networkable with all interconnecting Cables with following outputs of Rack Mounted Power Amplifier
A56: a | B56: 120 W | C56: Nos | D56: 0 | G56: =(E56+F56)*D56 -> 0
A57: b | B57: 240 W | C57: Nos | D57: 0 | G57: =(E57+F57)*D57 -> 0
A58: c | B58: 480W | C58: Nos | D58: 2 | G58: =(E58+F58)*D58 -> 0
A60: 3.4 | B60: Supplying, installing, testing and commissioning of 15U high amplifier rack assembly made of aluminium channel equivalent to euro rack system, with side and rear panels made of 14 swg powder coated sheet steel front transparent persplexdoor and with rails, rollers & bearings. Fans shall provided at the top for ventilation side panels will be ventilated type.The rack shall be powder coated of approved color and spare 'U' shall be covered with blank panels. | C60: Nos | D60: 1 | G60: =(E60+F60)*D60 -> 0
A61: 3.5 | B61: Supplying, installing, testing and commissioning of analogue double handheld wireless microphone. Location: Reception | C61: Nos | D61: 1 | G61: =(E61+F61)*D61 -> 0
A62: 3.6 | B62: Supply, installation, testing and commissioning of Control Module for EVC(Emergency Voice call) zone wise speakers with necessary accessories like back box, installation supports, etc. complete | C62: Nos | D62: 1 | G62: =(E62+F62)*D62 -> 0
A63: 3.7 | B63: Supplying, installing, testing and commissioning of 2 core x 1.5 sq. mm, shielded sheathed twisted pair armoured (FRLS) confirming to IS standards and specifications, with necessary clamps to be provided at maximum 1mtr intervals, EOL resistors to be considered wherever required. (Blue color) (For control modules to Amplifier, Mixer, Speakers - star network) | C63: Rmt | D63: 1800 | G63: =(E63+F63)*D63 -> 0
A64: 3.8 | B64: Supplying, installing, testing and commissioning approved make. PVC conduits on ceiling / wall / floor / cable trays, etc. complete with accessories like, Junction boxes, Collars, Bends, binding wires, etc.
A65: a | B65: 20 mm dia. | C65: Rmt | D65: 0 | G65: =(E65+F65)*D65 -> 0
A66: b | B66: 25 mm dia. | C66: Rmt | D66: 100 | G66: =(E66+F66)*D66 -> 0
B68: Total Amount Section-3 ( PA/Music System ) | G68: =SUM(G46:G67) -> 0
B70: Total Amount Section-4 ( Fire Sprinkler System ) | G70: =SUM(G69:G69) -> 0
B71: GRAND TOTAL - SECTION- 1+2+3+4 ( Excl GST) - [A] | G71: =G70+G68+G44+G30 -> 0
B72: GST 18% | G72: =G71*0.18 -> 0
B73: Total Amount ( Incl GST) -[B] | G73: =G71+G72 -> 0

Sheet WLD System - Indegne
A1: Project : | B1: Indegene_3rd Floor
A2: Subject : | B2: WLD System
A3: Rev : | B3: R0 | H3: 11.11.2025
A4: S.L | B4: Description | C4: Unit | D4: Total Qty | E4: Supply Rate | F4: Installation Rate | G4: Total Amount | H4: Remarks
B5: WATER LEAK DETECTION SYSTEM - SERVER ROOM
A6: 1 | B6: Supply, installation, testing & commissioning of water leak detection control panel of as mentiioned below zone capacity along with LCD display, individual relay contact for each zone. It should have LEDs indicating normal & alarm condition for individual zone, acknowledge & reset button. It should display water leakage with half meter accuracy. Panel shall have the provision on RS-485 Modbus connectivity for integration with BMS system qouted rate shall be included with all ncessory accessories with panel mounting etc.The rate shall include the cost of Water Leak Module.
A7: a | B7: 1 Zone | C7: Nos. | D7: 1 | G7: =(E7+F7)*D7 -> 0
A8: b | B8: 2 Zone | C8: Nos. | D8: 0 | G8: =(E8+F8)*D8 -> 0
A10: 2 | B10: Supply, installation, testing & commissioning of water leak detection cable of 4 wire sensing cable type using high quality polymer cable.
A11: a | B11: 03mts length. | C11: Nos. | D11: 2 | G11: =(E11+F11)*D11 -> 0
A12: b | B12: 06mts length. | C12: Nos. | D12: 2 | G12: =(E12+F12)*D12 -> 0
A13: c | B13: 10mts length. | C13: Nos. | D13: 1 | G13: =(E13+F13)*D13 -> 0
A14: d | B14: 15mts legnth | C14: Nos. | D14: 0 | G14: =(E14+F14)*D14 -> 0
A16: 3 | B16: Supply, installation, testing & commissioning of Hooter cum strobe. | C16: Nos. | D16: 1 | G16: =(E16+F16)*D16 -> 0
A18: 4 | B18: Supply, installation, testing & commissioning of Identification / mapping tags for sensor cable - Bag of 50 | C18: Bags | D18: 2 | G18: =(E18+F18)*D18 -> 0
A20: 5 | B20: Supply, installation, testing & commissioning of fixing clips & accessories. | C20: Packs | D20: 2 | G20: =(E20+F20)*D20 -> 0
A22: 6 | B22: Supply, installation, testing & commissioning of PVC conduits on ceiling / wall / floor etc. complete with accessories like, junction boxes, collars, bends, saddles, clips / clamps for supports etc.
A23: a | B23: 25 dia. | C23: Rmt. | D23: 30 | G23: =(E23+F23)*D23 -> 0
A25: 7 | B25: Supply, Installation, testing & commissioning of 2Cx1.5 sq.mm unarmoured Copper conductor cable. The rate shall include all necessary cable glands, lugs etc | C25: Rmt. | D25: 15 | G25: =(E25+F25)*D25 -> 0
A27: 8 | B27: Supply, installation, testing & commissioning of twisted pair RS-485 serial communication wires for connection b/w WLD panel & BMS system (for integration with BMS panel). | C27: Rmt. | D27: 0 | G27: =(E27+F27)*D27 -> 0
A29: 9 | B29: Supply, Installation, testing & commissioning of 2Cx1.0 sq.mm armoured copper conductor jumper cable. The rate shall include all necessary cable glands, lugs etc | C29: Rmt. | D29: 10 | G29: =(E29+F29)*D29 -> 0
A31: 9 | B31: Supply, Installation, testing & commissioning of 2Cx1.0 sq.mm armoured copper conductor Leader cable. The rate shall include all necessary cable glands, lugs etc | C31: Rmt. | D31: 10 | G31: =(E31+F31)*D31 -> 0
B32: GRAND TOTAL - WLD System ( Excl GST) - [A] | G32: =SUM(G5:G31) -> 0
B33: GST 18% | G33: =G32*0.18 -> 0
B34: Total Amount ( Incl GST) -[B] | G34: =G32+G33 -> 0

Sheet Rodent System - Indegene
A1: Project : | B1: Indegene_3rd Floor
A2: Subject : | B2: Rodent Repellent System
A3: Rev : | B3: R0 | H3: 11.11.2025
A4: S.L | B4: Description | C4: Unit | D4: Total Qty | E4: Supply Rate | F4: Installation Rate | G4: Total Amount | H4: Remarks
B5: RODENT REPELLENT SYSTEM
A6: 1 | B6: Supply, installation, testing & commissioning of Rodent repellent system network controller capable of supporting 12 Transducers. Quoted rate shall include a pair of stands, brackets, 3pin power supply cord (1.5 meters), etc. complete vide technical specifications. Quoted rate shall include necessary wall support required for installation. Panel shall have the provision on RS-485 Modbus connectivity for integration with BMS system. | C6: Nos. | D6: 3 | G6: =(E6+F6)*D6 -> 0
A8: 2 | B8: Supply, installation, testing & commissioning of Transducers, circular ceiling mounted type, having power output of 800mW/transducer. Quoted rate shall include necessary mounting clips / clamps etc. vide technical specification. | C8: Nos. | D8: 8 | G8: =(E8+F8)*D8 -> 0
A10: 3 | B10: Supply, installation, testing & commissioning of Transducers, circular Floor mounted type, having power output of 800mW/transducer. Quoted rate shall include necessary mounting clips / clamps etc. vide technical specification. | C10: Nos. | D10: 2 | G10: =(E10+F10)*D10 -> 0
A12: 4 | B12: Supply, installation, testing & commissioning of standard 2 core, flexible (14/40) SWG multi-stranded CT wires shall be used for connectivity between transducers & master console. | C12: Rmt | D12: 150 | G12: =(E12+F12)*D12 -> 0
A14: 5 | B14: Supply, installation, testing & commissioning of PVC conduits on ceiling / wall / floor etc. complete with accessories like, junction boxes, collars, bends, saddles, clips / clamps for supports etc.
A15: a | B15: 25 dia. | C15: Rmt. | D15: 75 | G15: =(E15+F15)*D15 -> 0
A17: 6 | B17: Supply, installation of suitable size GI junction box made of 16SWG for Rodent Transducers Quoted rate shall be included with suitable Glands, termination and screws with complete nccessory accessories. | C17: Nos | D17: 10 | G17: =(E17+F17)*D17 -> 0
B18: GRAND TOTAL - Rodent Repellent System ( Excl GST) - [A] | G18: =SUM(G5:G17) -> 0
B19: GST 18% | G19: =G18*0.18 -> 0
B20: Total Amount ( Incl GST) -[B] | G20: =G18+G19 -> 0

Sheet HVAC Cost-Summary
A1: Version | B1: : R0 | C1: Date: 09.11.2025
A2: Project | B2: : INDIGENE 3RD FLOOR, MANYATA
A3: Subject | B3: : SUMMARY - HVAC LOW SIDE, VAV & VRF WORKS
A4: Sl No | B4: Description | C4: Amount (INR)
A6: 1 | B6: HVAC Lowside Works - Part A | C6: ='HVAC Lowside works- Part A'!G409 -> 10562169
A7: 3 | B7: VAV Supply & Installation Works - Part-C | C7: ='VAV Supply & Install- Part-C'!G159 -> 3477824
B8: Total Amount ( Excl GST) - [A] | C8: =SUM(C6:C7) -> 14039993
B9: GST 18% | C9: =C8*0.18 -> 2527198.7
B10: Total Amount ( Incl GST) - [B] | C10: =C8+C9 -> 16567192

Sheet HVAC Lowside works- Part A
A1: Project : | B1: Indegene -3rd Floor- Manyata
A2: Subject : | B2: HVAC Low side works
A3: Rev : | B3: R1 | H3: 26.01.2026
A4: S.L | B4: Description | C4: Unit | D4: Qty | E4: Supply Rate | F4: Installation Rate | G4: Total Amount | H4: Remarks
B5: MECHANICAL SYSTEM
B6: AIR CONDITIONING WORKS
B7: Supply, Installation, Testing & Commissioning & Handing over of the following:
B8: PREAMBLE TO BOQ:
B9: Tendered Rates all Inclusive:
B10: Unless otherwise provided in the Bill of Quantities, the rates tendered by the Contractor for all items of the work shall be all inclusive and shall apply to all heights, lifts, leads and depths, in all positions of the building.
B12: PART A-LOW SIDE WORKS
A13: 1 | B13: AHU ROOM WORKS -DOUBLE SKIN PLENUM FOR AIR HANDLING UNIT
B14: Supply, Installation Testing & Commissioning of Sheet metal cabinet type double skin air plenum section of following sizes for air handling units supplied by Developer. All sheet metal connection, partitions and plenums, required to confine the flow of air to and through the filters and fans, shall be constructed of 18 gauge GSS / 16 Gauge aluminum, thoroughly stiffened with 25 mm x 25 mm x 3mm galvanized steel angle braces and fitted with all necessary inspection doors as required, to give access to all parts of the apparatus. Access doors shall be not less than 45 cm x 45 cm in size. Air plenums shall be modular in construction with powder coated aluminum frame work.
B15: Plenum box to be with 25mm thick puf insulation. The panels shall be fabricated out of 0.8 mm thick outer sheet duly powder coated and the inner sheet shall be perforated having a thickness of 0.63 mm thick having minimum 30% perforations shall be used to perform the acoustic functions. The panels shall be powder coated and finished to the shade as that of the air handling unit. Plenums shall be shop / factory fabricated panel type and assembled at site. Fixing of galvanized angle flanges on duct pieces shall be with rivers heads inside i.e. towards GS sheet and riveting shall be done from outside.
A16: 1.1 | B16: AHU ROOM NO.1
B17: 4000MM(l)x2000MM(w)x600 MM(h) as per technical specifications
A18: a | B18: Supply of Plenum as per technical specification | C18: Set | D18: 1 | E18: 104000 | F18: 0 | G18: =(E18+F18)*D18 -> 104000
A19: b | B19: Installation,testing & Commissioning of all items listed above | C19: Set | D19: 1 | E19: 0 | F19: 8670 | G19: =(E19+F19)*D19 -> 8670
A21: 1.2 | B21: AHU ROOM NO.2
B22: 3000MM(l)x1500MM(w)x750 MM(h) as per technical specifications
A23: a | B23: Supply of Plenum as per technical specification | C23: Set | D23: 1 | E23: 82134 | F23: 0 | G23: =(E23+F23)*D23 -> 82134
A24: b | B24: Installation,testing & Commissioning of all items listed above | C24: Set | D24: 1 | E24: 0 | F24: 8670 | G24: =(E24+F24)*D24 -> 8670
A26: 1.3 | B26: AHU ROOM NO.3
B27: 3000MM(l)x1500MM(w)x750 MM(h) as per technical specifications
A28: a | B28: Supply of Plenum as per technical specification | C28: Set | D28: 1 | E28: 82134 | F28: 0 | G28: =(E28+F28)*D28 -> 82134
A29: b | B29: Installation,testing & Commissioning of all items listed above | C29: Set | D29: 1 | E29: 0 | F29: 8670 | G29: =(E29+F29)*D29 -> 8670
A31: 2 | B31: NEW MERV -7 & MERV -13 FILTERS FOR EXSISTING AHU’S
A32: 2.1 | B32: Supply , Installation, Testing & Commissioning of Pre Filters for Air handling Units at 1st Floor with Rating (Grade) as per ASHRAE 52.2-MERV -8 & Rating (Grade) as per EN 779- G4 Efficiency grade 90% down to 10 microns Preferably Box type design (Pleated construction) in design. All Filters shall be covered with polyethylene cover and packed in good quality cartons box for safe handling and storage.The cost shall include the cost of removal of existing MERV-8 Filters and replacement with new MERV-8 Filters . Contractor to check the space avaialble in existing AHU and select the Filter depths accordingly. Initial & final pressure drops should not exceed 50 pa & 120 Pa.The Scope shall include the cost of removal of existing MERV-8 & replacement with new filters | C32: Sets | D32: 3 | E32: 21060 | F32: 1560 | G32: =(E32+F32)*D32 -> 67860
A33: 2.2 | B33: Supply , Installation, Testing & Commissioning of Fine Filters for Air handling Units at 1st Floor with Rating (Grade) as per ASHRAE 52.2-MERV -13 & Rating (Grade) as per EN 779- F7 Efficiency grade 95% down to 5 microns Preferably Box type design (Pleated construction) in design. All Filters shall be covered with polyethylene cover and packed in good quality cartons box for safe handling and storage.The cost shall include the cost of removal of existing MERV-13 Filters and replacement with new MERV-13 Filters . Contractor to check the space avaialble in existing AHU and select the Filter depths accordingly. Initial & final pressure drops should not exceed 160 Pa & 450 Pa.The Scope shall include the cost of removal of existing MERV-13 Filters & replacement with new filters | C33: Sets | D33: 3 | E33: 28080 | F33: 1560 | G33: =(E33+F33)*D33 -> 88920
B34: Sub Total-1 | G34: =SUM(G13:G33) -> 451058
A36: 3 | B36: INLINE CENTRIFUGAL CABINET TYPE EXHAUST AIR FANS
B37: Supply, Installation, Testing & Commissioning of Double Skin Inline Centrifugal Cabinet type exhaust air fan comprising of fan section of following capacity suitable for exhaust air system. Inner skin shall be constructed out of 24 gauge plain GS sheet & outer skin in 24 gauge pre-plasticized GS sheet sandwitched between 25mm thick injected PU foam insulation of density not less than 40 Kg /CuM and complete with inspection doors and marine light, limit switch including control wiring as required. Duct Flanges to be provided along with fan for inlet and outlet connections. Fan shall be ba curved DIDW type centrifugal fans , Motor- IP-55, IE-3 TEFC squirrel cage induction motor suitable to operate on 415+10%V, 50Hz, 3 phase AC power supply and belt drive package and spring type vibration isolators. Select the fans for lowest DB level ( <45 DB) as per the manufacturers selection.
B38: Fan intake velocity shall not be more than 1500 FPM. All fans should be AMCA certified. Fans shall be provided with Suction & Discharge openings with flanges as per approved shop drawing. Fan section should be provided with 25mm thick Armasound acoustic insulation covered with perforated sheet.In addition to the above fans shall be provided with adequate vibration isolation pads and fire retardent flexible canvass connections made out of canvass sleeve for inlet & discharge side of fans
A39: 3.1 | B39: Exhuast air Fan capacity : 2600 CFM @ 35 mmwg of external static pressure, Motor rating 1.5 KW- For Gents + Ladies Toilet Block-1 | C39: Nos | D39: QRO | E39: 105019 | F39: 3608
A41: 3.2 | B41: Exhuast air Fan capacity : 950CFM @ 30 mmwg of external static pressure, Motor rating 0.55 KW- For Gents Toilet Block-2 | C41: Nos | D41: 2 | E41: 99754 | F41: 3608 | G41: =(E41+F41)*D41 -> 206724
A43: 3.3 | B43: Exhuast air Fan capacity : 850CFM @ 30 mmwg of external static pressure, Motor rating 0.55 KW- For Ladies Toilet Block-2 | C43: Nos | D43: 2 | E43: 99060 | F43: 3608 | G43: =(E43+F43)*D43 -> 205336
A45: 4 | B45: LOW NOISE MIXED FLOW EXHAUST AIR FANS DUCTED TYPE
A46: 4.1 | B46: Supply, Installation, Testing and Commissioning of silent/ Low Noise Mixed flow type Exhuast air fan - duct type complete with suitable motor, fire resistive flexible connection with nut bolts at outlet, vibration isolators, inlet dampers etc. Fan capacity : 300 CFM @ 25- 30mmwg of external static pressure. Fan shall be suitable for operation on 220 ± 6 % volts, 50 Hz,1 phase AC power supply. Flanges to be provided on both sides to facilitate duct connections. Fans shall be provided with adequate vibration isolation pads/ Neoprene Rubber pads and fire retardent flexible canvass connections made out of canvass sleeve for inlet & discharge side of fans. Select the fans for lowest DB level ( <47 DB) as per the manufacturers selection- For Executive Dining Pantry exhuast | C46: Nos | D46: 1 | E46: 41570 | F46: 2165 | G46: =(E46+F46)*D46 -> 43735
A48: 4.2 | B48: Supply, Installation, Testing and Commissioning of silent/ Low Noise Mixed flow type Exhuast air fan - duct type complete with suitable motor, fire resistive flexible connection with nut bolts at outlet, vibration isolators, inlet dampers etc. Fan capacity : 500 CFM @ 25-30mmwg of external static pressure. Fan shall be suitable for operation on 220 ± 6 % volts, 50 Hz,1 phase AC power supply. Flanges to be provided on both sides to facilitate duct connections. Fans shall be provided with adequate vibration isolation pads/ Neoprene Rubber pads and fire retardent flexible canvass connections made out of canvass sleeve for inlet & discharge side of fans. Select the fans for lowest DB level ( <47 DB) as per the manufacturers selection- For Electrical Room- 02 Exhaust | C48: Nos | D48: 1 | E48: 41570 | F48: 2165 | G48: =(E48+F48)*D48 -> 43735
A50: 5 | B50: PROPELLOR FANS- EXHUAST AIR FANS
B51: WALL MOUNTED TYPE PROPELLER FAN
B52: The supply & installation of wall mountable propeller type inline fan with all accessories like fan, motor, mounting frame, duct sleeve, protection guards,etc.,. The motor should be of IP21, class 'B' insulation suitable for operating at 3 phase, 230V, 50hz power supply
A53: a | B53: 500 CFM - Free Static-For Electrical Room- 01 Exhaust | C53: Nos | D53: 1 | E53: 11570 | F53: 1274 | G53: =(E53+F53)*D53 -> 12844
A54: b | B54: 600 CFM - Free Static | C54: Nos | D54: QRO | E54: 27300 | F54: 2730
A55: c | B55: 100 CFM - Free Static | C55: Nos | D55: QRO | E55: 5200 | F55: 520
A57: 6 | B57: RECTANGULAR INLINE FANS- DUCTABLE TYPE
A58: 6.1 | B58: Supply, Installation Testing & Commissioning of Silent Rectangular inline fan - duct type complete with suitable motor, fire resistive flexible connection with nut bolts at outlet, vibration isolators, inlet dampers etc. Fan capacity : 300CFM @ 25 mmwg of external static pressure.Fan shall be suitable for operation on 220 ± 6 % volts, 50 Hz,1 phase AC power supply. Flanges to be provided on both sides to facilitate duct connections.. Fans shall be provided with adequate vibration isolation pads/ Neoprene Rubber pads and fire retardent flexible canvass connections made out of canvass sleeve for inlet & discharge side of fans. All Fans Should be complete with Plug Top & necessary FRLS power cable. Select the fans for lowest DB level ( <55 DB) as per the manufacturers selection- For Battery Room Exhaust | C58: Nos | D58: 1 | E58: 18233 | F58: 1732 | G58: =(E58+F58)*D58 -> 19965
A60: 7 | B60: KITCHEN EXHAUST CABINET FAN - DIRECT DRIVEN CENTRIFUGAL FAN WITH MOTOR & DRIVE OUTSIDE AIR STREAM
B61: Kitchen Exhaust Fans meeting or exceeding the following specifications shall be furnished and installed at locations shown in the plans or described in the schedules.
B62: Casing: Casing shall be made of double skin type with universal discharge type (left/right/top). Outer skin should be pre-painted galvanized sheet, these panels should be insulated with 25mm thick PUF. Panels shall be open able for easy cleaning and maintenance. Fan section and motor section should be made compartment wise making motor isolated from the air flow path. Motor section should have fixed acoustic louvers on both sides
B63: Fan: Fan should be AMCA certified Aerofoil curved plug fans, these fans should be epoxy painted. Fan should statically and dynamically balanced. Fan selected should low noise type.Complete assembly module with highest system efficiency, specifically developed and optimized for use without a spiral casing. Newly developed high-performance impeller with optimized shape and highest efficiency, comprising six backward curved hollow section true aerofoil blades with real turbulence profile and rounded, inclined blade leading edges from impeller shroud to back plate, for optimal impact over the entire width of the blade. Co-rotating radial diffuser with optimized exit curving on the cover disc to enhance efficiency. Impeller made of high tensile sheet steel in an automated manufacturing process, robotic welding, degreased, iron phosphated and coated with a high quality epoxy-polyester mixed powder, fastened with a clamping bush to the shaft of the foot motor, balanced statically and dynamically according to DIN ISO 21940-11, specification G 2,5, based on the maximum speed. Fan can only be used with a horizontal axis! Performance data (w/o drive) according to tolerance class 1 to DIN 24 166. AMCA Licensed for Air Performance and Efficiency.
B64: Motor: Motor should be TEFC energy efficient IE2/IE3 VFD Compatibility, Power supply - 415 Volts, 3 Phase, 50 Hz.
B65: Drive: Direct driven type
B66: Supply , installation Testing & Commissioning of Low noise Universal discharge type double skin fan section (Inner and outer thickness of casing should be 0.6 mm thick GSS and insulated with 25 mm thick PUF) . Fan and motor should be in separate compartment making motor outside the air stream. Fan should be energy efficient direct driven AMCA certified Aerofoil Plug fan. Motor should be IE-2/IE3/IE4/PM(BLDC) TEFC Sq. Cage suitable for 415Â±10 V, 3-Ph, 50 Hz. Power supply with VFD compatibility and VFD drive. Unit should be suitable for mounting in the ceiling level . The fan unit shall be supplied along with necessary spring vibration isolation arrangement or equivalent/better, Limit switches, Marine lamp, Inspection door, fire retardant non - canvas type flexible connection between fan outlet & inlet flange and duct and all necessary accessories. It shall be ceiling mounted with M S channel frame supports. Noise level should not exceed 55DB at 1.5 Meter.
B67: The motor should be selected for VFD Compatible type. Supply , Installation, testing and commisisoning of VFD shall be included HVAC vendor scope. Compartment provisions in statrter panel will be provided by others for install the VFD
B68: The details of the TEFU are given in the following order:
B69: The Fan shall be selected for the lowest operating noise power levels. Capacity ratings, power consumption, with operating points to be clearly indicated.
A70: 7.1 | B70: Supply Installation , Testing & commissioning of Double Skin -DIDW, 5100 CFM, 75 mmwg- Total Static , 3.0 KW & 1450 RPM - Motor to be outside Air Stream | C70: Nos | D70: 1 | E70: 232050 | F70: 23400 | G70: =(E70+F70)*D70 -> 255450
A71: 7.2 | B71: Supply, Installation , testing & Commissioning of Variable frequency drive (VFD) - for 3.0 KW Motor which shall be housed in Exhaust fan Startel Panel. Starter panel shall be part of Electrical contactor scope. VFD shall be supplied with IP 21 Protection. The construction of the fan motor shall be of IP 42. The VFD shall be capable of regulating the speed of the Exhuast air fan from 120 % to 20% of rated Exhaust fan speed at the specifed rated flow & static. The Communication card to transfer the entire data available on VFD to the BMS System. he VFD shall be capable of hooking to the BMS system .VFD should be supplied with Communication Card to transfer the necessary information from VFD to BMS System. All Hardware & Software required for integration should be part of scope. VFD should have capacity to read cumulative KWH of energy consumption and not instantaneous value. | C71: Nos | D71: 1 | E71: 58500 | F71: 5850 | G71: =(E71+F71)*D71 -> 64350
A72: 7.3 | B72: Supply & Installation of Limit switch wiring ,lighting & motor interlock to be provided with 3 core 2.5sqmm cable in 19mm dia GI conduit | C72: Nos | D72: 15 | E72: 324 | F72: 123 | G72: =(E72+F72)*D72 -> 6705
A74: 8 | B74: ELECTROSTATIC DRY SCRUBBER FOR KITCHEN EXHAUST OF 5100 CFM.
B75: Supply, installation, testing & Commissioning of Electro- Static Dry scrubber for the above exhaust rating of 5100 CFM. The vendor shall include the Pressure drop to be 20mm Wg, works with necessary valve arrangement. The scope of supply should include complete system for Electrostatic Dry scrubber operation. It shall also include the carbon filters for residual carbon content removal.The Electrostatic Air Cleaners shall be supplied as a one-piece factory joined assembly of individual section(s) selected to treat oil mist, smoke, fume, grease & dust/ powder problems.
B76: Housing shall be constructed with minimum 1.6mm thick steel sheet with reinforced structure & powder coated to protect against rust and corrosion. It shall have a hinged door for cell access, located one side of the unit. The door shall be gasketed to prevent air leakage. There shall be a safety interlock switch to cut off primary supply when the access door is opened.The external finish shall be a durable industrial grade semi-gloss epoxy-polyester coating suitable for outdoor installations.
B77: Ionizing-Collecting cell(s) shall be of one-piece construction 13.38” (340mm) deep in direction of airflow. The dimension of the collection cell shall be 18.89” (480mm) H x 19.76” (502mm)W Max. All support framing, end plates and ionizer ground electrodes shall be 0.080 inch (2mm) thick aluminum. Both repelling and collector plates shall be 0.032 inch (0.8mm) thick aluminum alloy material rigidly retained in place with tubular spacers and tie rods. Each plate shall be corrugated, perpendicular to airflow direction. Spacing between plates shall be no less than 0.318 inch (8mm). Each cell shall weigh at least 17 kg with at least 8 stainless steel spiked blade ionizers. Tungsten wire ionizers will not be accepted
B78: Ionizing spiked blade shall be made of Stainless steel 304 material, rigidly supported both vertically and laterally. Spiked ionizer to ground electrode spacing shall be 1.0" (25mm). High voltage support insulators shall be of Teflon material for dielectric strength.
B79: Equipment should be selected on the basis of required Air handling capacity so as to achieve 90-95% particulate matter removal efficiency according to DOP Test or EN779 European standard (Equivalent to ASHRAE 52.1). Vendor should submit the Test report from the Lab having Test facility according to ASHRAE 52.2 or EN779. In the absence of Test report Vendor should demonstrate the efficiency claim at their manufacturing facility at their expenses.
B80: Power supplies shall be 100% solid state, operate on 230 VAC, 50 Hz, 1 Phase input and provide a dual high voltage output of 12-13 KVDC for the ionizer and 6.0-6.5 KVDC for the collector in normal operation conditions. Current output at the high tension shall be 12mA. A maximum power output for the solid state power supply shall be 120 watts to maintain the specified collection efficiency. Integrally mounted Electrical interlocks shall be provided to prevent access to the high voltage components without first interrupting the primary input power. The power supply shall operate over a temperature range of -32 degrees F to 140 degrees F, be overloaded self-protecting and accommodate an LED lights indicating the performance status of the ionizing/collecting cell. High voltage output components in the power supply shall be sealed with epoxy for moisture resistance.
B81: The power pack shall incorporate a short circuit arc protection with automatic power restoration system to prevent overload.
